Workbook
Name b_3_A: 'Worksheet A'!$C$4
Name b_3_A: 'Worksheet B'!$C$4
Name b_3_A_i: 'Worksheet A'!$C$7
Name b_3_A_i: 'Worksheet B'!$C$7
Name b_3_A_ii: 'Worksheet A'!$C$8
Name b_3_A_ii: 'Worksheet B'!$C$8

Sheet Basic Information
A1: Current year end: | B1: 12/31/24
A2: Prior year end: | B2: 12/31/23
A3: Client Name:
A4: Entity Name:
A6: ="20"&RIGHT(B1,2)&" Tax Questionnaire" -> 2024 Tax Questionnaire
A9: Entity Information
A11: Legal Name of Entity
A13: Entity Address
A17: Date of Formation/Incorporation
A19: Country of Incorportion
A21: Name of person in
A22: charge of entity's
A23: books and records
A25: Principal Business Activity
A27: Functional currency
A31: FILER CATEGORY DETERMINATION
A33: Ownership % at start of year
... A44: Category 1c
A45: Category 2 | V45: Yes
A46: Category 3 | V46: No
A47: Category 4
A48: Category 5a
A49: Category 5b
A50: Category 5c
A55: FUNCTIONAL CURRENCY
A57: (Functional currency:1 $US)
C58: Divide rate
A59: Average Exchange Rate | B59: ="20"&RIGHT('Basic Information'!B1,2) -> 2024
A60: Current year end rate | B60: ='Basic Information'!B1 -> 12/31/24
A61: Prior year end rate | B61: ='Basic Information'!B2 -> 12/31/23

Sheet Shareholding Details
A1: ='Basic Information'!B4 -> 0 | U1: Yes
A2: Details of Shareholding and Changes during the year | U2: No
B4: Total shares outstanding (leave blank to use the direct-holder total)
A5: US Shareholders (Direct & Indirect)
B6: Name | E6: REF | F6: Class of Shares | G6: REF | H6: BOY Shares | I6: REF | J6: EOY Shares | L6: % Ownership at BOY | N6: % Ownership at EOY | P6: Subpart F %
A7: 1 | B7: =B19 -> A | H7: =H19 -> 60 | J7: =J19 -> 60 | L7: =IFERROR(H7/IF($H$4>0,$H$4,$H$27),0) | N7: =IFERROR(J7/IF($J$4>0,$J$4,$J$27),0)
A8: 2 | L8: =IFERROR(H8/IF($H$4>0,$H$4,$H$27),0) | N8: =IFERROR(J8/IF($J$4>0,$J$4,$J$27),0)
A9: 3 | L9: =IFERROR(H9/IF($H$4>0,$H$4,$H$27),0) -> 0 | N9: =IFERROR(J9/IF($J$4>0,$J$4,$J$27),0) -> 0
A10: 4 | L10: =IFERROR(H10/IF($H$4>0,$H$4,$H$27),0) -> 0 | N10: =IFERROR(J10/IF($J$4>0,$J$4,$J$27),0) -> 0
A11: 5 | L11: =IFERROR(H11/IF($H$4>0,$H$4,$H$27),0) -> 0 | N11: =IFERROR(J11/IF($J$4>0,$J$4,$J$27),0) -> 0
A12: 6 | L12: =IFERROR(H12/IF($H$4>0,$H$4,$H$27),0) -> 0 | N12: =IFERROR(J12/IF($J$4>0,$J$4,$J$27),0) -> 0
A13: 7 | L13: =IFERROR(H13/IF($H$4>0,$H$4,$H$27),0) -> 0 | N13: =IFERROR(J13/IF($J$4>0,$J$4,$J$27),0) -> 0
A14: 8 | L14: =IFERROR(H14/IF($H$4>0,$H$4,$H$27),0) -> 0 | N14: =IFERROR(J14/IF($J$4>0,$J$4,$J$27),0) -> 0
B15: Total | H15: =SUM(H7:H14) -> 60 | J15: =SUM(J7:J14) -> 60 | L15: =SUM(L7:L14) -> 1 | N15: =SUM(N7:N14) -> 0.6 | P15: =SUM(P7:P14) -> 0
J16: % held by "US Shareholders" | L16: =SUMIF(L$7:L$14,">=0.1",L$7:L$14) -> 1 | N16: =SUMIF(N$7:N$14,">=0.1",N$7:N$14) -> 0.6
A17: Direct Shareholders
B18: Name | C18: Cat 5 related? | D18: Cat 2, 3, 4 related? | E18: REF | F18: Class of Shares | G18: REF | H18: BOY Shares | I18: REF | J18: EOY Shares | L18: % Ownership at BOY | N18: % Ownership at EOY
A19: 1 | B19: A | H19: 60 | J19: 60 | L19: =IFERROR(H19/IF($H$4>0,$H$4,$H$27),0) | N19: =IFERROR(J19/IF($J$4>0,$J$4,$J$27),0)
A20: 2 | B20: B | J20: 20 | L20: =IFERROR(H20/IF($H$4>0,$H$4,$H$27),0) -> 0 | N20: =IFERROR(J20/IF($J$4>0,$J$4,$J$27),0)
A21: 3 | B21: C | J21: 10 | L21: =IFERROR(H21/IF($H$4>0,$H$4,$H$27),0) -> 0 | N21: =IFERROR(J21/IF($J$4>0,$J$4,$J$27),0) -> 0.1
A22: 4 | B22: D | J22: 10 | L22: =IFERROR(H22/IF($H$4>0,$H$4,$H$27),0) -> 0 | N22: =IFERROR(J22/IF($J$4>0,$J$4,$J$27),0) -> 0.1
A23: 5 | L23: =IFERROR(H23/IF($H$4>0,$H$4,$H$27),0) -> 0 | N23: =IFERROR(J23/IF($J$4>0,$J$4,$J$27),0) -> 0
A24: 6 | L24: =IFERROR(H24/IF($H$4>0,$H$4,$H$27),0) -> 0 | N24: =IFERROR(J24/IF($J$4>0,$J$4,$J$27),0) -> 0
A25: 7 | L25: =IFERROR(H25/IF($H$4>0,$H$4,$H$27),0) -> 0 | N25: =IFERROR(J25/IF($J$4>0,$J$4,$J$27),0) -> 0
A26: 8 | L26: =IFERROR(H26/IF($H$4>0,$H$4,$H$27),0) -> 0 | N26: =IFERROR(J26/IF($J$4>0,$J$4,$J$27),0) -> 0
B27: Total | H27: =SUM(H19:H26) -> 60 | J27: =SUM(J19:J26) -> 100 | L27: =SUM(L19:L26) -> 1 | N27: =SUM(N19:N26) -> 1
A31: Sch - O Details
A35: Details of Filer's Acquisition of Stock since inception
B36: Name of Seller | E36: REF | F36: Class of Shares | G36: REF | H36: Date of Acquisition | I36: REF | J36: Method of Acquisition | K36: REF | L36: Number Acquired | M36: REF | N36: Purchase Price (local Currency) | P36: Ex. Rate | R36: Purchase Price (USD)
A37: 1
A38: 2
A39: 3
A40: 4
A41: 5
A42: 6
A43: 7
A44: 8
B45: Total | H45: =SUM(H37:H44) -> 0 | J45: =SUM(J37:J44) -> 0 | L45: =SUM(L37:L44) -> 0 | N45: =SUM(N37:N44) -> 0 | P45: =SUM(P37:P44) -> 0 | R45: =SUM(R37:R44) -> 0
A47: Filer's Dispositions of Stock Since Inception
B48: Name of Buyer | E48: REF | F48: Class of Shares | G48: REF | H48: Date of Disposition | I48: REF | J48: Method of Disposition | K48: REF | L48: Number Sold | M48: REF | N48: Sale Price (local Currency) | P48: Ex. Rate | R48: Sale Price (USD)
A49: 1
A50: 2
A51: 3
A52: 4
A53: 5
A54: 6
A55: 7
A56: 8
B57: Total | H57: =SUM(H49:H56) -> 0 | J57: =SUM(J49:J56) -> 0 | L57: =SUM(L49:L56) -> 0 | N57: =SUM(N49:N56) -> 0 | P57: =SUM(P49:P56) -> 0 | R57: =SUM(R49:R56) -> 0

Sheet Income Statement
A1: ='Basic Information'!B4 -> 0
A2: SCHEDULE C INCOME STATEMENT - SCHEDULE C
A3: ='Basic Information'!B1 -> 12/31/24
A4: (Amounts in Local Currency and US Dollars)
K5: Weighted Average Rate: | L5: ='Basic Information'!C59 -> 0
A6: Income (Loss) | D6: REF | F6: Book Income | H6: Book Adj | J6: Adj Book Income | L6: USD Book Income
B7: 1a | C7: Gross receipts | E7: 1a | J7: =H7+F7 -> 0 | L7: =J7/$L$5 -> #DIV/0!
B8: b | C8: Less returns and allowances | E8: b | J8: =H8+F8 -> 0 | L8: =J8/$L$5 -> #DIV/0!
B9: 2 | C9: Cost of good sold | E9: 2 | F9: =SUM(F10:F12) -> 0 | H9: =SUM(H10:H12) -> 0 | J9: =SUM(J10:J12) -> 0 | L9: =SUM(L10:L12) -> #DIV/0!
C10: Cost of Labor | J10: =H10+F10 -> 0 | L10: =J10/$L$5 -> #DIV/0!
C11: Purchases | J11: =H11+F11 -> 0 | L11: =J11/$L$5 -> #DIV/0!
C12: Other Costs | J12: =H12+F12 -> 0 | L12: =J12/$L$5 -> #DIV/0!
B13: 3 | C13: Gross profit | E13: 3 | F13: =F7-F8-F9 -> 0 | H13: =H7-H8-H9 -> 0 | J13: =J7-J8-J9 -> 0 | L13: =L7-L8-L9 -> #DIV/0!
B14: 4 | C14: Dividends | E14: 4 | J14: =H14+F14 -> 0 | L14: =J14/$L$5 -> #DIV/0!
B15: 5 | C15: Interest income | E15: 5 | J15: =H15+F15 -> 0 | L15: =J15/$L$5 -> #DIV/0!
B16: 6a | C16: Gross rents | E16: 6a | J16: =H16+F16 -> 0 | L16: =J16/$L$5 -> #DIV/0!
B17: b | C17: Gross royalties and licence fees | E17: b | J17: =H17+F17 -> 0 | L17: =J17/$L$5 -> #DIV/0!
B18: 7 | C18: Net gain or (loss) on sale of capital assets | E18: 7 | J18: =H18+F18 -> 0 | L18: =J18/$L$5 -> #DIV/0!
B19: 8a | C19: Foreign currency transaction gain or loss - unrealized | E19: 8a | J19: =H19+F19 -> 0 | L19: =J19/$L$5 -> #DIV/0!
B20: b | C20: Foreign currency transaction gain or loss - realized | E20: b | J20: =H20+F20 -> 0 | L20: =J20/$L$5 -> #DIV/0!
B21: 9 | C21: Other income (attach schedule) | E21: 9 | F21: =SUM(F22:F24) -> 0 | H21: =SUM(H22:H24) -> 0 | J21: =SUM(J22:J24) -> 0 | L21: =SUM(L22:L24) -> #DIV/0!
C22: Other income 1 | J22: =H22+F22 -> 0 | L22: =J22/$L$5 -> #DIV/0!
C23: Other income 2 | J23: =H23+F23 -> 0 | L23: =J23/$L$5 -> #DIV/0!
C24: Other income 3 | J24: =H24+F24 -> 0 | L24: =J24/$L$5 -> #DIV/0!
B25: 10 | C25: Total Income | E25: 10 | F25: =SUM(F13:F21) -> 0 | H25: =SUM(H13:H21) -> 0 | J25: =SUM(J13:J21) -> 0 | L25: =SUM(L13:L21) -> #DIV/0!
A26: Deductions | B26: 11 | C26: Compensation not deducted elsewhere | E26: 11 | J26: =H26+F26 -> 0 | L26: =J26/$L$5 -> #DIV/0!
B27: 12a | C27: Rents | E27: 12a | J27: =H27+F27 -> 0 | L27: =J27/$L$5 -> #DIV/0!
B28: b | C28: Royalties and licence fees | E28: b | J28: =H28+F28 -> 0 | L28: =J28/$L$5 -> #DIV/0!
B29: 13 | C29: Interest | E29: 13 | J29: =H29+F29 -> 0 | L29: =J29/$L$5 -> #DIV/0!
B30: 14 | C30: Depreciation not deducted elsewhere | E30: 14 | J30: =H30+F30 -> 0 | L30: =J30/$L$5 -> #DIV/0!
B31: 15 | C31: Depletion | E31: 15 | J31: =H31+F31 -> 0 | L31: =J31/$L$5 -> #DIV/0!
B32: 16 | C32: Taxes (exclude income tax expense) | E32: 16 | J32: =H32+F32 -> 0 | L32: =J32/$L$5 -> #DIV/0!
B33: 17 | C33: Other deductions (attach schedule) | E33: 17 | F33: =SUM(F34:F58) -> 0 | H33: =SUM(H34:H58) -> 0 | J33: =SUM(J34:J58) -> 0 | L33: =SUM(L34:L58) -> #DIV/0!
C34: MAINTENANCE SUPPLIES AND SMALL EQUIPMENT | J34: =H34+F34 -> 0 | L34: =J34/$L$5 -> #DIV/0!
C35: OFFICE SUPPLIES | J35: =H35+F35 -> 0 | L35: =J35/$L$5 -> #DIV/0!
C36: INSURANCE PREMIUMS | J36: =H36+F36 -> 0 | L36: =J36/$L$5 -> #DIV/0!
C37: MISCELLANEOUS-GENERAL DOCUMENTATION | J37: =H37+F37 -> 0 | L37: =J37/$L$5 -> #DIV/0!
C38: PROFESSIONNAL CONTRIBUTIONS | J38: =H38+F38 -> 0 | L38: =J38/$L$5 -> #DIV/0!
C39: DEEDS & LITIGATION COSTS | J39: =H39+F39 -> 0 | L39: =J39/$L$5 -> #DIV/0!
C40: COSTS OF ACTS FOR CLIENTS | J40: =H40+F40 -> 0 | L40: =J40/$L$5 -> #DIV/0!
C41: ADVERTISING - DEEDS & LITIGATION COSTS | J41: =H41+F41 -> 0 | L41: =J41/$L$5 -> #DIV/0!
C42: TRAVEL MISSIONS | J42: =H42+F42 -> 0 | L42: =J42/$L$5 -> #DIV/0!
C43: RECEPTIONS FEES | J43: =H43+F43 -> 0 | L43: =J43/$L$5 -> #DIV/0!
C44: POSTAGE COSTS | J44: =H44+F44 -> 0 | L44: =J44/$L$5 -> #DIV/0!
C45: TELEPHONE AND INTERNET EXPENSES | J45: =H45+F45 -> 0 | L45: =J45/$L$5 -> #DIV/0!
... C58: Other deduction 25 | J58: =H58+F58 -> 0 | L58: =J58/$L$5 -> #DIV/0!
B59: 18 | C59: Total Deductions | E59: 18 | F59: =SUM(F26:F33) -> 0 | H59: =SUM(H26:H33) -> 0 | J59: =SUM(J26:J33) -> 0 | L59: =SUM(L26:L33) -> #DIV/0!
A60: Net Income | B60: 19 | C60: Net Income or (loss) before exceptional items and income tax | E60: 19 | F60: =F25-F59 -> 0 | H60: =H25-H59 -> 0 | J60: =J25-J59 -> 0 | L60: =L25-L59 -> #DIV/0!
B61: 20 | C61: Unusual or infrequently ocurring items | E61: 20 | J61: =H61+F61 -> 0 | L61: =J61/$L$5 -> #DIV/0! | N61: ETR Pre-GILTI | P61: =-J62/J60 -> #DIV/0!
B62: 21a | C62: Income tax expense - current | E62: 21a | J62: =H62+F62 -> 0 | L62: =J62/$L$5 -> #DIV/0!
B63: b | C63: Income tax expense - deferred | E63: b | J63: =H63+F63 -> 0 | L63: =J63/$L$5 -> #DIV/0!
B64: 22 | C64: Current year net income or (loss) per books | E64: 22 | F64: =F60-F62-F63 | H64: =H60-H62-H63 | J64: =J60-J62-J63 | L64: =L60-L62-L63
A65: Other Comprehensive Income | B65: 23a | C65: Current year net income or (loss) per books | E65: 23a | J65: =H65+F65 -> 0 | L65: =J65/$L$5 -> #DIV/0!
B66: b | C66: Other | E66: b | J66: =H66+F66 -> 0 | L66: =J66/$L$5 -> #DIV/0!
B67: c | C67: Income tax expense related to other comprehensive income | E67: c | J67: =H67+F67 -> 0 | L67: =J67/$L$5 -> #DIV/0!
B68: 24 | C68: Other comprehensive income (loss), net of tax | E68: 24 | F68: =F65+F66-F67 -> 0 | H68: =H65+H66-H67 -> 0 | J68: =J65+J66-J67 -> 0 | L68: =L65+L66-L67 -> #DIV/0!

Sheet D-110 Flow-through K-1s
A1: ='Basic Information'!B4 -> 0
A2: INCOME FROM FLOW-THROUGH K-1S
A3: ='Basic Information'!B1 -> 12/31/24
A4: (Amounts in US Dollars)
A5: D-110
A6: Income (Loss) | D6: REF | F6: K-1 1 | H6: K-1 2 | J6: K-1 3 | L6: Total of all K-1s
B7: 1 | C7: Ordinary Income (loss) from trade or business activites | E7: 1 | L7: =J7+H7+F7 -> 0
B8: 2 | C8: Net income (loss) from rental real estate activities | E8: 2 | L8: =J8+H8+F8 -> 0
B9: 3a | C9: Gross income from other rental activites | E9: 3a | L9: =J9+H9+F9 -> 0
B10: b | C10: Expenses from other rental activities (attach schedule) | E10: b | L10: =J10+H10+F10 -> 0
B11: c | C11: Net income (loss) from rental activites. Subtract line 3b from line 3a | E11: c | L11: =J11+H11+F11 -> 0
B12: 4 | C12: Guaranteed payments to partners | E12: 4 | L12: =J12+H12+F12 -> 0
B13: 5 | C13: Interest Income | E13: 5 | L13: =J13+H13+F13 -> 0
B14: 6 | C14: Dividends: | E14: 6 | L14: =J14+H14+F14 -> 0
B15: a | C15: Ordinary dividends | E15: a | L15: =J15+H15+F15 -> 0
B16: b | C16: Qualified dividends | E16: b | L16: =J16+H16+F16 -> 0
B17: 7 | C17: Royalties | E17: 7 | L17: =J17+H17+F17 -> 0
B18: 8 | C18: Net short-term capital gain (loss) | E18: 8 | L18: =J18+H18+F18 -> 0
B19: 9a | C19: Net long-term capital gain (loss) | E19: 9a | L19: =J19+H19+F19 -> 0
B20: b | C20: Collectibles (28%) rate gain (loss) | E20: b | L20: =J20+H20+F20 -> 0
B21: c | C21: Unrecaptured section 1250 gain (attach statement) | E21: c | L21: =J21+H21+F21 -> 0
B22: 10 | C22: Net section 1231gain (loss) (attach Form 4797) | E22: 10 | L22: =J22+H22+F22 -> 0
B23: 11 | C23: Other income (loss) (attach schedule) | E23: 11 | F23: =SUM(F24:F26) -> 0 | H23: =SUM(H24:H26) -> 0 | J23: =SUM(J24:J26) -> 0 | L23: =J23+H23+F23 -> 0
C24: Other income 1 | L24: =J24+H24+F24 -> 0
C25: Other income 2 | L25: =J25+H25+F25 -> 0
C26: Other income 3
A27: Deductions | B27: 12 | C27: Section 179 expense deduction | E27: 12 | L27: =J27+H27+F27 -> 0
B28: 13a | C28: Contributions | E28: 13a | L28: =J28+H28+F28 -> 0
B29: b | C29: Investment interest expense | E29: 13b | L29: =J29+H29+F29 -> 0
B30: c | C30: Section 59(e)(2) expenditures | E30: 13c | L30: =J30+H30+F30 -> 0
B31: d | C31: Other deductions (attach schedule) | E31: 13d | F31: =SUM(F32:F36) -> 0 | H31: =SUM(H32:H36) -> 0 | J31: =SUM(J32:J36) -> 0 | L31: =J31+H31+F31 -> 0
C32: Other deduction 1 | L32: =J32+H32+F32 -> 0
C33: Other deduction 2 | L33: =J33+H33+F33 -> 0
C34: Other deduction 3 | L34: =J34+H34+F34 -> 0
C35: Other deduction 4 | L35: =J35+H35+F35 -> 0
C36: Other deduction 5 | L36: =J36+H36+F36 -> 0
B37: 14a | C37: Net earnings (loss) from self employment | E37: 14a | L37: =J37+H37+F37 -> 0
B38: b | C38: Gross farm or fishing income | E38: b | L38: =J38+H38+F38 -> 0
B39: c | C39: Gross nonfarm income | E39: c | L39: =J39+H39+F39 -> 0
A40: Credits | B40: 15a | C40: Low-income housing credit (section 42(j)(5)): | E40: 15a | L40: =J40+H40+F40 -> 0
B41: b | C41: Low-income housing credit (other) | E41: 15b | L41: =J41+H41+F41 -> 0
B42: c | C42: Qualified rehabilitation expenditures related to rental real estate activites | E42: 15c | L42: =J42+H42+F42 -> 0
B43: d | C43: Other rental real estate credits | E43: 15d | L43: =J43+H43+F43 -> 0
B44: e | C44: Other rental credits | E44: 15e | L44: =J44+H44+F44 -> 0
B45: f | C45: Other credits and credit recapture (attach statement) | E45: 15f | L45: =J45+H45+F45 -> 0
C47: Total Income | F47: =F7+F13+F15+F19+F23-F29-F31 -> 0 | H47: =H7+H13+H15+H19+H23-H29-H31 -> 0 | J47: =J7+J13+J15+J19+J23-J29-J31 -> 0 | L47: =L7+L13+L15+L19+L23-L29-L31 -> 0 | M47: /D-100
A50: Foreign Transactions | B50: 16a | C50: Name or foreign country or US posession | E50: 16a | F50: Enter Country | H50: Enter Country | J50: Enter Country
B51: b | C51: Gross income from all sources | E51: b | F51: =SUM(F7:F23) -> 0 | H51: =SUM(H7:H23) -> 0 | J51: =SUM(J7:J23) -> 0 | L51: =J51+H51+F51 -> 0
B52: c | C52: Gross income sourced at partner level | E52: c | F52: =SUM(F18:F23) -> 0 | H52: =SUM(H18:H23) -> 0 | J52: =SUM(J18:J23) -> 0 | L52: =J52+H52+F52 -> 0
C53: Foreign gross income sourced at partnership level | L53: =J53+H53+F53 -> 0
B54: d | C54: Passive | E54: d | F54: =SUM(F7:F17) -> 0 | H54: =SUM(H7:H17) -> 0 | J54: =SUM(J7:J17) -> 0 | L54: =J54+H54+F54 -> 0
B55: e | C55: Listed categories (attach Schedule) | E55: e | L55: =J55+H55+F55 -> 0
B56: f | C56: General limitation | E56: f | L56: =J56+H56+F56 -> 0
C57: Deductions allocated and apportioned at partner level | L57: =J57+H57+F57 -> 0
B58: g | C58: Interest expense | E58: g | F58: =+F29 -> 0 | H58: =+H29 -> 0 | J58: =+J29 -> 0 | L58: =J58+H58+F58 -> 0
B59: h | C59: Other | E59: h | L59: =J59+H59+F59 -> 0
C60: Deductions allocated and apportioned at partnership level to foreign source income | L60: =J60+H60+F60 -> 0
B61: I | C61: Passive | E61: I | F61: =+F31 -> 0 | H61: =+H31 -> 0 | J61: =+J31 -> 0 | L61: =J61+H61+F61 -> 0
B62: j | C62: Listed categories (attach Schedule) | E62: j | L62: =J62+H62+F62 -> 0
B63: k | C63: General limitation | E63: k | L63: =J63+H63+F63 -> 0
B64: l | C64: Total foreign taxes (1) paid | E64: l1 | L64: =J64+H64+F64 -> 0
C65: (2) Accrued | E65: l2 | L65: =J65+H65+F65 -> 0
B66: m | C66: Reduction in taxes available for credit (attach schedule) | E66: m | L66: =J66+H66+F66 -> 0
A67: AMT Items | B67: 17a | C67: Depreciation adjustment on property placed in service after 1986 | E67: 17a | L67: =J67+H67+F67 -> 0
B68: b | C68: Adjusted gain or loss | E68: b | L68: =J68+H68+F68 -> 0
B69: c | C69: Depletion (other than oil and gas) | E69: c | L69: =J69+H69+F69 -> 0
B70: d | C70: Gross income from , oil, gas, and geothermal properties | E70: d | L70: =J70+H70+F70 -> 0
B71: e | C71: Deductions allocable to oil, gas, and geothermal properties | E71: e | L71: =J71+H71+F71 -> 0
B72: f | C72: Ohter adjustments and tax preference items (attach schedule) | E72: f | L72: =J72+H72+F72 -> 0
A73: Other | B73: 18a | C73: Tax-exempt interest income | E73: 18a | L73: =J73+H73+F73 -> 0
B74: b | C74: Other tax-exempt income | E74: b | L74: =J74+H74+F74 -> 0
B75: c | C75: Nondeductible expenses | E75: c | L75: =J75+H75+F75 -> 0
B76: 19a | C76: Distributions of money (cash and marketable securities) | E76: 19a | L76: =J76+H76+F76 -> 0
B77: b | C77: Distributions of property other than money | E77: b | L77: =J77+H77+F77 -> 0
B78: 20a | C78: Investment Income | E78: 20a | F78: =+F13+F15+F17 -> 0 | H78: =+H13+H15+H17 -> 0 | J78: =+J13+J15+J17 -> 0 | L78: =J78+H78+F78 -> 0
B79: b | C79: Investment expenses | E79: b | F79: =+F31 -> 0 | H79: =+H31 -> 0 | J79: =+J31 -> 0 | L79: =J79+H79+F79 -> 0
B80: c | C80: Other items and amounts (attach schedule) | E80: c | L80: =J80+H80+F80 -> 0
A83: =CELL("filename") -> https://unisonglobus-my.sharepoint.com/personal/pragya_dugar_unisonglobus_com/Documents/Form 5471-Automation/[Final Copy of 5471 workpaper.XLSX]Entity Structure and changes

Sheet Balance Sheet
A1: ='Basic Information'!B4 -> 0
A2: BALANCE SHEET - SCHEDULE F
A3: ='Basic Information'!B1 -> 12/31/24
A4: (Amounts in Local Currency and US Dollars)
G5: Spot Rate @ PY End | H5: Spot Rate @ CY End
G6: ='Basic Information'!C61 -> 0 | H6: ='Basic Information'!C60 -> 0
B9: Assets | C9: REF | D9: (a) Beginning of annual accounting period (LC) | E9: REF | F9: (b) End of annual accounting period (LC) | G9: (a) Beginning of annual accounting period (USD) | H9: (b) End of annual accounting period (USD)
A10: 1 | B10: Cash | G10: =ROUND(D10/$G$6,0) -> #DIV/0! | H10: =ROUND($F10/$H$6,0) -> #DIV/0!
A11: 2 a | B11: Trade notes and accounts receivable | G11: =ROUND(D11/$G$6,0) -> #DIV/0! | H11: =ROUND($F11/$H$6,0) -> #DIV/0!
A12: b | B12: Less allowance for bad debts | G12: =ROUND(D12/$G$6,0) -> #DIV/0! | H12: =ROUND($F12/$H$6,0) -> #DIV/0!
A13: 3 | B13: Derivatives | G13: =ROUND(D13/$G$6,0) -> #DIV/0! | H13: =ROUND($F13/$H$6,0) -> #DIV/0!
A14: 4 | B14: Inventories | G14: =ROUND(D14/$G$6,0) -> #DIV/0! | H14: =ROUND($F14/$H$6,0) -> #DIV/0!
A15: 5 | B15: Other current assets (attach schedule) | D15: =SUM(D16:D18) -> 0 | F15: =SUM(F16:F18) -> 0 | G15: =SUM(G16:G18) -> #DIV/0! | H15: =SUM(H16:H18) -> #DIV/0!
B16: Prepaid expenses | G16: =ROUND(D16/$G$6,0) -> #DIV/0! | H16: =ROUND($F16/$H$6,0) -> #DIV/0!
B17: Other current asset 2 | G17: =ROUND(D17/$G$6,0) -> #DIV/0! | H17: =ROUND($F17/$H$6,0) -> #DIV/0!
B18: Other current asset 3 | G18: =ROUND(D18/$G$6,0) -> #DIV/0! | H18: =ROUND($F18/$H$6,0) -> #DIV/0!
A19: 6 | B19: Loans to shareholders and other related persons | G19: =ROUND(D19/$G$6,0) -> #DIV/0! | H19: =ROUND($F19/$H$6,0) -> #DIV/0!
A20: 7 | B20: Investment in subsidiaries | D20: =SUM(D21:D24) -> 0 | F20: =SUM(F21:F24) -> 0 | G20: =SUM(G21:G23) -> #DIV/0! | H20: =SUM(H21:H23) -> #DIV/0!
B21: Investment in subsidiary 1 | G21: =ROUND(D21/$G$6,0) -> #DIV/0! | H21: =ROUND($F21/$H$6,0) -> #DIV/0!
B22: Investment in subsidiary 2 | G22: =ROUND(D22/$G$6,0) -> #DIV/0! | H22: =ROUND($F22/$H$6,0) -> #DIV/0!
B23: Investment in subsidiary 3 | G23: =ROUND(D23/$G$6,0) -> #DIV/0! | H23: =ROUND($F23/$H$6,0) -> #DIV/0!
A24: 8 | B24: Other investments (attach schedule) | D24: =SUM(D25:D27) -> 0 | F24: =SUM(F25:F27) -> 0 | G24: =SUM(G25:G27) -> #DIV/0! | H24: =SUM(H25:H27) -> #DIV/0!
B25: Other Investment 1 | G25: =ROUND(D25/$G$6,0) -> #DIV/0! | H25: =ROUND($F25/$H$6,0) -> #DIV/0!
B26: Other Investment 2 | G26: =ROUND(D26/$G$6,0) -> #DIV/0! | H26: =ROUND($F26/$H$6,0) -> #DIV/0!
B27: Other Investment 3 | G27: =ROUND(D27/$G$6,0) -> #DIV/0! | H27: =ROUND($F27/$H$6,0) -> #DIV/0!
A28: 9a | B28: Buildings and other depreciable assets | G28: =ROUND(D28/$G$6,0) -> #DIV/0! | H28: =ROUND($F28/$H$6,0) -> #DIV/0!
A29: b | B29: Less accumulated depreciation (Enter as Negative) | G29: =ROUND(D29/$G$6,0) -> #DIV/0! | H29: =ROUND($F29/$H$6,0) -> #DIV/0!
A30: 10a | B30: Depletable assets | G30: =ROUND(D30/$G$6,0) -> #DIV/0! | H30: =ROUND($F30/$H$6,0) -> #DIV/0!
A31: b | B31: Less accumulated depletion (Enter as Negative) | G31: =ROUND(D31/$G$6,0) -> #DIV/0! | H31: =ROUND($F31/$H$6,0) -> #DIV/0!
A32: 11 | B32: Land (net of any amortization) | G32: =ROUND(D32/$G$6,0) -> #DIV/0! | H32: =ROUND($F32/$H$6,0) -> #DIV/0!
A33: 12 | B33: Intangible assets
A34: a | B34: Goodwill | G34: =ROUND(D34/$G$6,0) -> #DIV/0! | H34: =ROUND($F34/$H$6,0) -> #DIV/0!
A35: b | B35: Organization costs | G35: =ROUND(D35/$G$6,0) -> #DIV/0! | H35: =ROUND($F35/$H$6,0) -> #DIV/0!
A36: c | B36: Patents, trademarks, and other intangible assets | G36: =ROUND(D36/$G$6,0) -> #DIV/0! | H36: =ROUND($F36/$H$6,0) -> #DIV/0!
A37: d | B37: Less accumulated amortization (Enter as negative) | G37: =ROUND(D37/$G$6,0) -> #DIV/0! | H37: =ROUND($F37/$H$6,0) -> #DIV/0!
A38: 13 | B38: Other assets (attach schedule) | D38: =SUM(D39:D41) -> 0 | F38: =SUM(F39:F41) -> 0 | G38: =SUM(G39:G41) -> #DIV/0! | H38: =SUM(H39:H41) -> #DIV/0!
B39: Other asset 1 | G39: =ROUND(D39/$G$6,0) -> #DIV/0! | H39: =ROUND($F39/$H$6,0) -> #DIV/0!
B40: Other asset 2 | G40: =ROUND(D40/$G$6,0) -> #DIV/0! | H40: =ROUND($F40/$H$6,0) -> #DIV/0!
B41: Other asset 3 | G41: =ROUND(D41/$G$6,0) -> #DIV/0! | H41: =ROUND($F41/$H$6,0) -> #DIV/0!
A42: 14 | B42: Total assets | D42: =SUM(D10:D15)+SUM(D21:D24)+SUM(D28:D38)+D19 -> 0 | F42: =SUM(F10:F15)+SUM(F21:F24)+SUM(F28:F38)+F19 -> 0 | G42: =SUM(G10:G15)+SUM(G21:G24)+SUM(G28:G38)+G19 -> #DIV/0! | H42: =SUM(H10:H15)+SUM(H21:H24)+SUM(H28:H38)+H19 -> #DIV/0!
B45: Liabilities and Stockholders' Equity | C45: REF | D45: (a) Beginning of annual accounting period (LC) | E45: REF | F45: (b) End of annual accounting period (LC) | G45: (a) Beginning of annual accounting period (USD) | H45: (b) End of annual accounting period (USD)
A46: 15 | B46: Accounts payable | G46: =ROUND(D46/$G$6,0) -> #DIV/0! | H46: =ROUND(F46/$H$6,0) -> #DIV/0!
A47: 16 | B47: Other current liabilities (attach schedule) | D47: =SUM(D48:D50) -> 0 | F47: =SUM(F48:F50) -> 0 | G47: =SUM(G48:G50) -> #DIV/0! | H47: =SUM(H48:H50) -> #DIV/0!
B48: VAT Payable | G48: =ROUND(D48/$G$6,0) -> #DIV/0! | H48: =ROUND($F48/$H$6,0) -> #DIV/0!
B49: Other current liability 2 | G49: =ROUND(D49/$G$6,0) -> #DIV/0! | H49: =ROUND($F49/$H$6,0) -> #DIV/0!
B50: Other current liability 3 | G50: =ROUND(D50/$G$6,0) -> #DIV/0! | H50: =ROUND($F50/$H$6,0) -> #DIV/0!
A51: 17 | B51: Derivatives | G51: =ROUND(D51/$G$6,0) -> #DIV/0! | H51: =ROUND($F51/$H$6,0) -> #DIV/0!
A52: 18 | B52: Loans from shareholders and other related persons | G52: =ROUND(D52/$G$6,0) -> #DIV/0! | H52: =ROUND($F52/$H$6,0) -> #DIV/0!
A53: 19 | B53: Other liabilities (attach schedule) | D53: =SUM(D54:D56) -> 0 | F53: =SUM(F54:F56) -> 0 | G53: =SUM(G54:G56) -> #DIV/0! | H53: =SUM(H54:H56) -> #DIV/0!
B54: LOAN - CAISSE D'EPARGNE BANK | G54: =ROUND(D54/$G$6,0) -> #DIV/0! | H54: =ROUND($F54/$H$6,0) -> #DIV/0!
B55: LOAN- 50K EUR BPI BANK | G55: =ROUND(D55/$G$6,0) -> #DIV/0! | H55: =ROUND($F55/$H$6,0) -> #DIV/0!
B56: Other liability 3 | G56: =ROUND(D56/$G$6,0) -> #DIV/0! | H56: =ROUND($F56/$H$6,0) -> #DIV/0!
A57: 20 | B57: Capital Stock
A58: a | B58: Preferred stock | G58: =ROUND(D58/$G$6,0) -> #DIV/0! | H58: =ROUND($F58/$H$6,0) -> #DIV/0!
A59: b | B59: Common stock | G59: =ROUND(D59/$G$6,0) -> #DIV/0! | H59: =ROUND($F59/$H$6,0) -> #DIV/0!
A60: 21 | B60: Paid-in or capital surplus | G60: =ROUND(D60/$G$6,0) -> #DIV/0! | H60: =ROUND($F60/$H$6,0) -> #DIV/0!
A61: 22 | B61: Retained earnings | C61: Next Tab | E61: Next Tab | G61: =ROUND(D61/$G$6,0) -> #DIV/0! | H61: =ROUND($F61/$H$6,0) -> #DIV/0!
A62: 23 | B62: Less cost of treasury stock | G62: =ROUND(D62/$G$6,0) -> #DIV/0! | H62: =ROUND($F62/$H$6,0) -> #DIV/0!
A63: 24 | B63: Total liabilities and capital | D63: =SUM(D46:D47)+SUM(D51:D53)+SUM(D57:D61)-D62 -> 0 | F63: =SUM(F46:F47)+SUM(F51:F53)+SUM(F57:F61)-F62 -> 0 | G63: =SUM(G46:G47)+SUM(G51:G53)+SUM(G57:G61)-G62 -> #DIV/0! | H63: =SUM(H46:H47)+SUM(H51:H53)+SUM(H57:H61)-H62 -> #DIV/0!
B64: Out of balance (assets less liabilities and capital) — must be nil in every column before filing | D64: =ROUND(D63-D42,2) | F64: =ROUND(F63-F42,2) | G64: =ROUND(G63-G42,0) | H64: =ROUND(H63-H42,0)

Sheet Retained Earnings
A1: ='Basic Information'!B4
A2: RETAINED EARNINGS RECONCILIATION
A3: ='Basic Information'!B1
A4: (Amounts in Local Currency and US Dollars)
F5: Rate @ PY End | H5: Rate @ CY End | J5: Average rate
F6: ='Basic Information'!C61 | H6: ='Basic Information'!C60 | J6: ='Basic Information'!C59
E8: REF | F8: FC | G8: REF | H8: USD
A10: BOY Retained Earnings (prior-year Form 5471, Schedule F line 22) | C10: ='Basic Information'!B2 | E10: Prior 5471 | F10: ='Balance Sheet'!D61 | H10: =IF(F10="","",ROUND(F10/$F$6,0))
A13: Net Income (Loss) per books | E13: Income Statement | F13: ='Income Statement'!F64 | H13: =ROUND(F13/$J$6,0)
A15: Other Increases
A16: Other increase 1 | H16: =IF(F16="","",ROUND(F16/$H$6,0))
A17: Other increase 2 | H17: =IF(F17="","",ROUND(F17/$H$6,0))
A19: Distributions
A20: Cash | E20: Dividends | F20: =Dividends!C12 | H20: =Dividends!E12
A21: Property | H21: =IF(F21="","",ROUND(F21/$H$6,0))
A23: Other Decreases / Adjustments
A24: Currency translation adjustment (computed: opening balance, income and closing balance translate at three different rates) | H24: =IF(OR(H28="",H10=""),"",H28-(H10+H13+N(H16)+N(H17)-N(H20)-N(H21)+N(H25)))
A25: Other decrease 2 | H25: =IF(F25="","",ROUND(F25/$H$6,0))
A27: EOY Retained Earnings (computed) | C27: ='Basic Information'!B1 | F27: =F10+F13+F16+F17-F20-F21+F24+F25 | H27: =IF(H10="","",H10+H13+N(H16)+N(H17)-N(H20)-N(H21)+N(H25)+N(H24))
A28: EOY Retained Earnings per Schedule F line 22 | F28: ='Balance Sheet'!F61 | H28: ='Balance Sheet'!H61
A29: Difference — must be nil before filing | F29: =ROUND(F27-F28,2) | H29: =IF(OR(H27="",H28=""),"",ROUND(H27-H28,0))
A31: * Enter increases as positive and decreases as negative in column F. Column H translates at the rates on Basic Information: opening at the prior year-end rate, net income at the average rate, everything else at the current year-end rate.

Sheet Dividends
A2: Ref | B2: Date | C2: £ Amount | D2: FX Rate | E2: $ Amount
B3: 00/00/00 | E3: =C3*D3 -> 0
B4: 00/00/00 | E4: =C4*D4 -> 0
B5: 00/00/00 | E5: =C5*D5 -> 0
B6: 00/00/00 | E6: =C6*D6 -> 0
E8: =C8*D8 -> 0
E9: =C9*D9 -> 0
E10: =C10*D10 -> 0
C12: =SUM(C3:C11) -> 0 | E12: =SUM(E3:E11) -> 0

Sheet Schedule E & E-1
A1: ='Basic Information'!B4 -> 0 | M1: 951A
A2: TAXES PAID, ACCRUED OR DEEMED PAID | M2: FB - Foreign Branch
A3: ='Basic Information'!B1 -> 12/31/24 | M3: PAS - Passive
A4: (Amounts in Local Currency) | M4: 901j
M5: RBT - Re-sourced by Treaty
M6: GEN - General
B8: Income Category Code:
B9: GEN - General
A11: Schedule E
B12: Part I- Taxes for Which a Foreign Tax Credit is Allowed
B13: Section 1 - Taxes paid or accrued directly by foreign corporations
B14: (a) | E14: (b) | G14: (c) | I14: (d) | K14: (e) | M14: (f) | O14: (g) | Q14: (h) | S14: (i) | U14: (j)
B15: Name of Payor Entity | D15: REF | E15: EIN or Ref ID | F15: REF | G15: Country to which tax is paid | H15: REF | I15: Foreign tax year to which tax relates | J15: REF | K15: US tax year to which tax relates | L15: REF | M15: Income subject to tax in foreign jurisdiction | N15: REF | O15: Tax Paid or Incured (Local CC) | P15: REF | Q15: FX rate to USD | S15: USD Amount | U15: Amount in Functional Currency of Entity
A16: 1 | M16: ='Income Statement'!J60 | O16: ='Income Statement'!J62 | Q16: ='Basic Information'!C59 | S16: =ROUND(IFERROR(O16/Q16,0),0) -> 0 | U16: =S16*'Income Statement'!$L$5 -> 0
A17: 2 | S17: =ROUND(IFERROR(O17/Q17,0),0) -> 0 | U17: =S17*'Income Statement'!$L$5 -> 0
A18: 3 | S18: =ROUND(IFERROR(O18/Q18,0),0) -> 0 | U18: =S18*'Income Statement'!$L$5 -> 0
A19: 4 | S19: =ROUND(IFERROR(O19/Q19,0),0) -> 0 | U19: =S19*'Income Statement'!$L$5 -> 0
A20: 5 | B20: Total USD Tax | R20: 5 | S20: =SUM(S16:S19) -> 0
A21: 6 | B21: Total Functional Currency Tax | R21: Ties to Schedule E-1? | S21: =IF(S20=(SUM(E57:AE57)),"Yes","No") -> Yes | T21: 6 | U21: =SUM(U16:U19) -> 0
B24: Section 2 - Taxes deemed paid
B25: (a) | E25: (b) | G25: (c) | I25: (d) | K25: (e) | M25: (f) | O25: (g) | Q25: (h) | S25: (i)
B26: Name of Payor Entity | D26: REF | E26: EIN or Ref ID | F26: REF | G26: Country to which tax is paid | H26: REF | I26: PTEP Group (code) | J26: REF | K26: Annual PTEP account (year) | L26: REF | M26: PTEP distributed (Local CC) | N26: REF | O26: Total amount of PTEP in the PTEP Group (Local CC) | P26: REF | Q26: Total amount of PTEP Group Taxes with respect to PTEP Group (USD) | S26: Foreign income taxes properly attributable to PTEP and not previously deeemed paid
A27: 1 | S27: =(M27/O27)*Q27 -> #DIV/0!
A28: 2 | S28: =(M28/O28)*Q28 -> #DIV/0!
A29: 3 | S29: =(M29/O29)*Q29 -> #DIV/0!
A30: 4 | S30: =(M30/O30)*Q30 -> #DIV/0!
A31: 5 | B31: Total | R31: 5 | S31: =SUM(S27:S30) -> #DIV/0! | U31: Report on E-1, line 6
B35: Part III - Taxes for Which a Foreign Tax Credit is Disallowed
B36: (a) | E36: (b) | G36: (c) | I36: (d) | K36: (e) | M36: (f) | O36: (g) | Q36: (h) | S36: (i)
B37: Name of Payor Entity | D37: REF | E37: EIN or Ref ID | F37: REF | G37: Section 901(j) | H37: REF | I37: Section 901(k) and (l) | J37: REF | K37: Section 901(m) | L37: REF | M37: US Taxes | N37: REF | O37: Taxes Related to Sec 959(c)(3) E&P | P37: REF | Q37: Other | S37: Total
A38: 1 | S38: =Q38+M38+K38+I38+G38 -> 0
A39: 2 | S39: =Q39+M39+K39+I39+G39 -> 0
A40: 3 | B40: Functional Currency Amount | R40: 3 | S40: =S38+S39 -> 0
A41: 4 | B41: US Dollars Amount at wtd avg FX | R41: 4 | S41: =+S40/'Income Statement'!L5 -> #DIV/0!
B45: Schedule E-1
B46: Taxes Paid, Accrued, or Deemed Paid on Accumulated E&P fo Foreign Corporation | E46: (a) | G46: (b) | I46: (c) | K46: (d) | L46: (e) Previously Taxed E&P (section 959(c)(1)(A)) | V46: (e) Previously Taxed E&P (reclassed) (section 959(c)(2))
D47: REF | E47: Current E&P | F47: REF | G47: Post-1986 Undistributed Earnings | H47: REF | I47: Pre-1987 E&P Not Previously Taxed | J47: REF | K47: Hovering Deficit and Deduction for Suspended Taxes | L47: REF | M47: (i) Section 965(a) "DFIC income" | N47: REF | O47: (ii) Section 965(b) "DFIC Deficit" | P47: REF | Q47: (iii) General section 959(c)(1) | R47: REF | S47: (iv) Section 951A Inclusion "GILTI" | T47: REF | U47: (v) Section 245A(d) Inclusion "Hybrid Dividends" | V47: REF | W47: (vi) Section 965(a) Inclusion "DFIC Income" | X47: REF | Y47: (vii) Section 965(b)(4)(A) "DFIC Deficit" | Z47: REF | AA47: (viii) Section 951A Inclusion "GILTI" | AB47: REF | AC47: (ix) Section 245A(d) Inclusion "Hybrid Dividends" | AD47: REF | AE47: (x) Section 951(a)(1)(A)) Inclusion "Subpart F"
A48: 1a | B48: Balance at beginning of year | C48: 1a
A49: b | B49: Beginning balance adjustments | C49: b | E49: =SUM(E50:E52) -> 0 | G49: =SUM(G50:G52) -> 0 | I49: =SUM(I50:I52) -> 0 | K49: =SUM(K50:K52) -> 0 | M49: =SUM(M50:M52) -> 0 | O49: =SUM(O50:O52) -> 0 | Q49: =SUM(Q50:Q52) -> 0 | S49: =SUM(S50:S52) -> 0 | U49: =SUM(U50:U52) -> 0 | W49: =SUM(W50:W52) -> 0 | Y49: =SUM(Y50:Y52) -> 0 | AA49: =SUM(AA50:AA52) -> 0 | AC49: =SUM(AC50:AC52) -> 0 | AE49: =SUM(AE50:AE52) -> 0
B50: Beginning balance adjustment 1
B51: Beginning balance adjustment 2
B52: Beginning balance adjustment 3
A53: c | B53: Adjusted beginning balance | C53: c | E53: =E48+E49 -> 0 | G53: =G48+G49 -> 0 | I53: =I48+I49 -> 0 | K53: =K48+K49 -> 0 | M53: =M48+M49 -> 0 | O53: =O48+O49 -> 0 | Q53: =Q48+Q49 -> 0 | S53: =S48+S49 -> 0 | U53: =U48+U49 -> 0 | W53: =W48+W49 -> 0 | Y53: =Y48+Y49 -> 0 | AA53: =AA48+AA49 -> 0 | AC53: =AC48+AC49 -> 0 | AE53: =AE48+AE49 -> 0
A54: 2 | B54: Adjustment for redetermination of prior year US Tax | C54: 2
A55: 3a | B55: Taxes unsuspended under anti-splitter rules | C55: 3a
A56: b | B56: Taxes suspended under anti-splitter rules | C56: b
A57: 4 | B57: Taxes reported on Schedule E line 8 | C57: 4
A58: 5a | B58: Taxes carried over in nonrecognition transactions | C58: 5a
A59: b | B59: Taxes reclassified as related to hovering deficit after nonrecognition transaction | C59: b
A60: 6 | B60: Taxes reported on Schedule E, Part I, Section 2, line 5, column (i) | C60: 6
A61: 7 | B61: Other pre-tax adjustments | C61: 7 | E61: =SUM(E62:E64) -> 0 | G61: =SUM(G62:G64) -> 0 | I61: =SUM(I62:I64) -> 0 | K61: =SUM(K62:K64) -> 0 | M61: =SUM(M62:M64) -> 0 | O61: =SUM(O62:O64) -> 0 | Q61: =SUM(Q62:Q64) -> 0 | S61: =SUM(S62:S64) -> 0 | U61: =SUM(U62:U64) -> 0 | W61: =SUM(W62:W64) -> 0 | Y61: =SUM(Y62:Y64) -> 0 | AA61: =SUM(AA62:AA64) -> 0 | AC61: =SUM(AC62:AC64) -> 0 | AE61: =SUM(AE62:AE64) -> 0
B62: Other adjustment 1
B63: Other adjustment 2
B64: Other adjustment 3
A65: 8 | B65: Taxes paid or accrued on accumulated E&P | C65: 8 | E65: =SUM(E53:E61) -> 0 | G65: =SUM(G53:G61) -> 0 | I65: =SUM(I53:I61) -> 0 | K65: =SUM(K53:K61) -> 0 | M65: =SUM(M53:M61) -> 0 | O65: =SUM(O53:O61) -> 0 | Q65: =SUM(Q53:Q61) -> 0 | S65: =SUM(S53:S61) -> 0 | U65: =SUM(U53:U61) -> 0 | W65: =SUM(W53:W61) -> 0 | Y65: =SUM(Y53:Y61) -> 0 | AA65: =SUM(AA53:AA61) -> 0 | AC65: =SUM(AC53:AC61) -> 0 | AE65: =SUM(AE53:AE61) -> 0
A66: 9 | B66: Taxes deemed paid with respect to 951(a)(1) inclusions | C66: 9
A67: 10 | B67: Taxes deemed paid with respect to 951A | C67: 10
A68: 11 | B68: Taxes deemed paid with respect to actual distributions | C68: 11
A69: 12 | B69: Taxes on amounts reclassified to 959(c)(1) from 959 (c)(2) | C69: 12
A70: 13 | B70: Other pre-tax adjustments | C70: 13 | E70: =SUM(E71:E73) -> 0 | G70: =SUM(G71:G73) -> 0 | I70: =SUM(I71:I73) -> 0 | K70: =SUM(K71:K73) -> 0 | M70: =SUM(M71:M73) -> 0 | O70: =SUM(O71:O73) -> 0 | Q70: =SUM(Q71:Q73) -> 0 | S70: =SUM(S71:S73) -> 0 | U70: =SUM(U71:U73) -> 0 | W70: =SUM(W71:W73) -> 0 | Y70: =SUM(Y71:Y73) -> 0 | AA70: =SUM(AA71:AA73) -> 0 | AC70: =SUM(AC71:AC73) -> 0 | AE70: =SUM(AE71:AE73) -> 0
B71: Other adjustment 1
B72: Other adjustment 2
B73: Other adjustment 3
A74: 14 | B74: Taxes related to hovering deficit offset of undistributed E&P | C74: 14
A75: 15 | B75: Balance of taxes paid or accrued | C75: 15 | E75: =E74+E70+E69+E68+E67+E65 -> 0
A76: 16 | B76: Reduction for tested income taxes not deemed paid | C76: 16
A77: 17 | B77: Reduction for other taxes not deemed paid | C77: 17
A78: 18 | B78: Balance at beginning of next year | C78: 18 | E78: 0 | G78: =G65+G66+G67+G68++G69+G70+G74 -> 0 | I78: =I65+I66+I67+I68++I69+I70+I74 -> 0 | K78: =K65+K66+K67+K68++K69+K70+K74 -> 0 | M78: =M65+M66+M67+M68++M69+M70+M74 -> 0 | O78: =O65+O66+O67+O68++O69+O70+O74 -> 0 | Q78: =Q65+Q66+Q67+Q68++Q69+Q70+Q74 -> 0 | S78: =S65+S66+S67+S68++S69+S70+S74 -> 0 | U78: =SUM(U65:U70)+U74 -> 0 | W78: =W65+W66+W67+W68++W69+W70+W74 -> 0 | Y78: =Y65+Y66+Y67+Y68++Y69+Y70+Y74 -> 0 | AA78: =AA65+AA66+AA67+AA68++AA69+AA70+AA74 -> 0 | AC78: =AC65+AC66+AC67+AC68++AC69+AC70+AC74 -> 0 | AE78: =AE65+AE66+AE67+AE68++AE69+AE70+AE74 -> 0

Sheet Sch - H
A1: ='Basic Information'!B4 -> 0
A2: CURRENT YEAR E&P SCHEDULE H
A3: ='Basic Information'!B1 -> 12/31/24
A4: (Amounts in Local Currency and US Dollars)
C7: Income Category Code:
C8: GEN - General
A10: 1 | B10: Current year net income per foreign books | H10: 1 | I10: =+'Income Statement'!J64 -> 0
A11: 2 | B11: Net adjustments to Line 1 to determine current | E11: Net Additions | G11: Net Subtractions
B12: E&P for US GAAP and tax
A13: a | B13: Capital gains or losses | D13: REF | F13: REF
A14: b | B14: Depreciation and amortization (SL ACE)
A15: c | B15: Depletion
A16: d | B16: Investment or incentive allowance
A17: e | B17: Charges to statutory reserves
A18: f | B18: Inventory adjustments
A19: g | B19: Income Taxes | G19: ='Schedule E & E-1'!U21 -> 0
A20: h | B20: Foreign currency gains or losses
A21: i | B21: Other
A22: 3 | B22: Total net additions | E22: =SUM(E13:E21) -> 0
A23: 4 | B23: Total net subtractions | G23: =SUM(G13:G21) -> 0
A24: 5a | B24: Current E&P (lines 1 plus 3 minus 4) | H24: 5a | I24: =I10+E22-G23 -> 0
A25: b | B25: DASTM gain or (loss) | H25: b
A26: c | B26: Combine 5a and 5b | H26: c | I26: =SUM(I24:I25) -> 0
A27: c(i) | B27: General category | G27: 0
A28: c(ii) | B28: Passive category | G28: 0
A29: c(iii) | B29: Section 901(j) category | G29: 0
A30: d | B30: Current E&P in US$ | H30: d | I30: =I26/G31 -> #DIV/0!
D31: Weighted average exchange rate used on 5d | G31: ='Basic Information'!C59 -> 0

Sheet Schedule I & I-1
A1: ='Basic Information'!B4 -> 0 | M1: 951A
A2: SUMMARY OF FOREIGN INCOME AND GILTI - SCHEDULE I | M2: FB - Foreign Branch
A3: ='Basic Information'!B1 -> 12/31/24 | M3: PAS - Passive
A4: (Amounts in Local Currency and US Dollars) | M4: 901j
M5: RBT - Re-sourced by Treaty
M6: GEN - General
A7: Schedule I - Summary of Shareholder's Income from Foreign Corporation
C8: REF
A9: 1a | B9: Section 964(e)(4) Subpart F dividend income from the sale of stock of a lower-tier foreign corporation
A10: b | B10: Section 245A(e)(2) Subpart F income from hybrid dividends of tiered corporations
A11: c | B11: Subpart F income from tiered extraordinary disposition amounts not eligible for Subpart F exception under section 954(c)(6)
A12: d | B12: Subpart F income from tiered extraordinary reduction amounts not eligible for Subpart F exception under section 954(c)(6)
A13: e | B13: Section 954(c) Subpart F FPHCI income from Worksheet A | D13: ='Worksheet A'!F90 -> 0
A14: f | B14: Section 954(d) Subpart F Foreign Base Sales income from Worksheet A | D14: ='Worksheet A'!F20 -> 0
A15: g | B15: Section 954(e) Subpart F Foreign Base Servcies income from Worksheet A | D15: ='Worksheet A'!F21 -> 0
A16: h | B16: Other subpart F Income
A17: 2 | B17: Earnings invested in US property from Worksheet B | D17: ='Worksheet B'!F33 -> 0
A18: 3 | B18: Reserved for future use
A19: 4 | B19: Factoring Income
A20: 5a | B20: Section 245A eligible dividends
A21: 5b | B21: Extaordinary disposition amounts
A22: 5c | B22: Extaordinary reduction amounts
A23: 5d | B23: Section 245(A)(e) dividends
A24: 5e | B24: Dividends not reported on line 5a, 5b, 5c, or 5d
A25: 6 | B25: Exchange gain or (loss) on a distribution of previously taxed income
B29: Income Category Code:
B30: GEN - General
A32: Schedule I-1 - Information for Global Intangible Low-Taxed Income
C33: REF | D33: FC | E33: REF | F33: FX Rate | G33: REF | H33: USD
A34: 1 | B34: Gross Income | D34: ='Income Statement'!J25-'Income Statement'!J19 -> 0
A35: 2 | B35: Exclusions
A36: a | B36: Effectively connected income
A37: b | B37: Subpart F income
A38: c | B38: High-tax exception income
A39: d | B39: Related party dividends
A40: e | B40: Foreign oil and gas extraction income
A41: 3 | B41: Total exclusions | D41: =SUM(D36:D40) -> 0 | J41: ETR
A42: 4 | B42: Gross income less total exclusions | D42: =D34-D41 -> 0 | J42: =+H45/(H44+H45) -> #DIV/0! | K42: Can make GILTI High Tax Exception as if this is greater than 18.9% (for proof, you need to remove the exclusion amount, if necessary).
A43: 5 | B43: Deductions properly allocable to line 4 | D43: ='Income Statement'!J59 -> 0
A44: 6 | B44: Tested income (loss) | D44: =D42-D43 -> 0 | F44: ='Income Statement'!$L$5 -> 0 | H44: =ROUND(D44/F44,0) -> #DIV/0!
A45: 7 | B45: Tested foreign income taxes | D45: =IF(D44<0,0,'Schedule E & E-1'!U21) -> 0 | F45: ='Income Statement'!$L$5 -> 0 | H45: =ROUND(D45/F45,0) -> #DIV/0!
A46: 8 | B46: Qualified business asset investment (QBAI) | F46: ='Income Statement'!$L$5 -> 0 | H46: =ROUND(D46/F46,0) -> #DIV/0!
A47: 9a | B47: Interest expense (included on line 5) | D47: ='Income Statement'!J29 -> 0 | F47: ='Income Statement'!$L$5 -> 0 | H47: =ROUND(D47/F47,0) -> #DIV/0!
A48: b | B48: Qualified interest Expense
A49: c | B49: Tested QBAI Amount
A50: d | B50: Tested Interest Expense (Line 9a minus (9B + 9C). Enter Zero if < 0) | D50: =IF(D47-(D48+D49) < 0, 0, D47-(D48+D49)) -> 0 | F50: ='Income Statement'!$L$5 -> 0 | H50: =ROUND(D50/F50,0) -> #DIV/0!
A51: 10a | B51: Interest Income Included in Line 4 | D51: ='Income Statement'!J15 -> 0
A52: b | B52: Qualified Interest Income
A53: c | B53: Tested Interest Income (Line 10a minus line 10b. Enter Zero if < 0) | D53: =IF(D51-D52<0,0,D51-D52) -> 0 | F53: ='Income Statement'!$L$5 -> 0 | H53: =ROUND(D53/F53,0) -> #DIV/0!

Sheet Schedule J
B1: ='Basic Information'!B4 -> 0 | N1: 951A | X1: 951A
B2: ACCUMULATED E&P SCHEDULE J | N2: FB - Foreign Branch | X2: FB - Foreign Branch
B3: ='Basic Information'!B1 -> 12/31/24 | N3: PAS - Passive | X3: PAS - Passive
B4: (Amounts in Local Currency) | N4: 901j
N5: RBT - Re-sourced by Treaty
N6: GEN - General
C9: Income Category Code:
C10: GEN - General
A12: look up
C13: Part I - Accumulated E&P of Controlled Foreign Corporation | F13: (a) | H13: (b) | J13: (c) | L13: (d) | M13: (e) Previously Taxed E&P (section 959(c)(1)(A)) | W13: (e) Previously Taxed E&P (reclassed) (section 959(c)(2)) | AH13: (f)
E14: REF | F14: Post-2017 E&P Not Previously Taxed | G14: REF | H14: Post-1986 Undistributed Earnings | I14: REF | J14: Pre-1987 E&P Not Previously Taxed | K14: REF | L14: Hovering Deficit and Deduction for Suspended Taxes | M14: REF | N14: (i) Section 965(a) "DFIC income" | O14: REF | P14: (ii) Section 965(b) "DFIC Deficit" | Q14: REF | R14: (iii) General section 959(c)(1) | S14: REF | T14: (iv) Section 951A Inclusion "GILTI" | U14: REF | V14: (v) Section 245A(d) Inclusion "Hybrid Dividends" | W14: REF | X14: (vi) Section 965(a) Inclusion "DFIC Income" | Y14: REF | Z14: (vii) Section 965(b)(4)(A) "DFIC Deficit" | AA14: REF | AB14: (viii) Section 951A Inclusion "GILTI" | AC14: REF | AD14: (ix) Section 245A(d) Inclusion "Hybrid Dividends" | AE14: REF | AF14: (x) Section 951(a)(1)(A)) Inclusion "Subpart F" | AG14: REF | AH14: Total E&P
A15: 1a | B15: 1a | C15: Balance at beginning of year | D15: 1a | AH15: =SUM(F15:AF15) -> 0
A16: 1b | B16: 1b | C16: Beginning balance adjustments | D16: 1b | F16: =SUM(F17:F19) -> 0 | H16: =SUM(H17:H19) -> 0 | J16: =SUM(J17:J19) -> 0 | L16: =SUM(L17:L19) -> 0 | N16: =SUM(N17:N19) -> 0 | P16: =SUM(P17:P19) -> 0 | R16: =SUM(R17:R19) -> 0 | T16: =SUM(T17:T19) -> 0 | V16: =SUM(V17:V19) -> 0 | X16: =SUM(X17:X19) -> 0 | Z16: =SUM(Z17:Z19) -> 0 | AB16: =SUM(AB17:AB19) -> 0 | AD16: =SUM(AD17:AD19) -> 0 | AF16: =SUM(AF17:AF19) -> 0 | AH16: =SUM(F16:AF16) -> 0
C17: Beginning balance adjustment 1 | AH17: =SUM(F17:AF17) -> 0
C18: Beginning balance adjustment 2 | AH18: =SUM(F18:AF18) -> 0
C19: Beginning balance adjustment 3 | AH19: =SUM(F19:AF19) -> 0
A20: 1c | B20: 1c | C20: Adjusted beginning balance | D20: 1c | F20: =F15+F16 -> 0 | H20: =H15+H16 -> 0 | J20: =J15+J16 -> 0 | L20: =L15+L16 -> 0 | N20: =N15+N16 -> 0 | P20: =P15+P16 -> 0 | R20: =R15+R16 -> 0 | T20: =T15+T16 -> 0 | V20: =V15+V16 -> 0 | X20: =X15+X16 -> 0 | Z20: =Z15+Z16 -> 0 | AB20: =AB15+AB16 -> 0 | AD20: =AD15+AD16 -> 0 | AF20: =AF15+AF16 -> 0 | AH20: =SUM(F20:AF20) -> 0
A21: 2 | B21: 2a | C21: Reduction for taxes unsuspended under anti-splitter rules | D21: 2a
B22: 2b | C22: Disallowed deduction for taxes suspended under anti-splitter rules | D22: 2b
B23: 3 | C23: Current year E&P (or deficit) | D23: 3 | F23: ='Sch - H'!I26-'Schedule J'!H23 -> 0
A24: 3 | B24: 4 | C24: E&P attributable to distributions of PTEP from lower-tier | D24: 4 | AH24: =SUM(M24:AF24) -> 0
A25: 4 | B25: 5a | C25: E&P carried over in nonrecognition transaction | D25: 5a
B26: 5b | C26: Reclassify deficit in E&P as hovering deficit after nonrecognition transaction | D26: 5b
A27: 5 | B27: 6 | C27: Other pre-distribution & inclusion adjustments | D27: 6 | F27: =SUM(F28:F30) -> 0 | H27: =SUM(H28:H30) -> 0 | J27: =SUM(J28:J30) -> 0 | L27: =SUM(L28:L30) -> 0 | N27: =SUM(N28:N30) -> 0 | P27: =SUM(P28:P30) -> 0 | R27: =SUM(R28:R30) -> 0 | T27: =SUM(T28:T30) -> 0 | V27: =SUM(V28:V30) -> 0 | X27: =SUM(X28:X30) -> 0 | Z27: =SUM(Z28:Z30) -> 0 | AB27: =SUM(AB28:AB30) -> 0 | AD27: =SUM(AD28:AD30) -> 0 | AF27: =SUM(AF28:AF30) -> 0
C28: Other adjustment 1
C29: Other adjustment 2
C30: Other adjustment 3
A31: 6 | B31: 7 | C31: Total current and accumulated E&P | D31: 7 | F31: =SUM(F20:F27) -> 0 | H31: =SUM(H20:H27) -> 0 | J31: =SUM(J20:J27) -> 0 | L31: =SUM(L20:L27) -> 0 | N31: =SUM(N20:N27) -> 0 | P31: =SUM(P20:P27) -> 0 | R31: =SUM(R20:R27) -> 0 | T31: =SUM(T20:T27) -> 0 | V31: =SUM(V20:V27) -> 0 | X31: =SUM(X20:X27) -> 0 | Z31: =SUM(Z20:Z27) -> 0 | AB31: =SUM(AB20:AB27) -> 0 | AD31: =SUM(AD20:AD27) -> 0 | AF31: =SUM(AF20:AF27) -> 0
A32: 7 | B32: 8 | C32: Amounts reclasified to 959(c)(2) from 959(c)(3) E&P | D32: 8
A33: 8 | B33: 9 | C33: Actual distributions | D33: 9
A34: 9 | B34: 10 | C34: Amounts reclasified to 959(c)(1) from 959(c)(2) E&P | D34: 10
A35: 10 | B35: 11 | C35: Amounts included as earnings invested in US property and reclassified to 959(c)(1) E&P | D35: 11
A36: 11 | B36: 12 | C36: Other adjustments | D36: 12 | F36: =SUM(F37:F39) -> 0 | H36: =SUM(H37:H39) -> 0 | J36: =SUM(J37:J39) -> 0 | L36: =SUM(L37:L39) -> 0 | N36: =SUM(N37:N39) -> 0 | P36: =SUM(P37:P39) -> 0 | R36: =SUM(R37:R39) -> 0 | T36: =SUM(T37:T39) -> 0 | V36: =SUM(V37:V39) -> 0 | X36: =SUM(X37:X39) -> 0 | Z36: =SUM(Z37:Z39) -> 0 | AB36: =SUM(AB37:AB39) -> 0 | AD36: =SUM(AD37:AD39) -> 0 | AF36: =SUM(AF37:AF39) -> 0
C37: Other adjustment 1
C38: Other adjustment 2
C39: Other adjustment 3
B40: 13 | C40: Hovering deficit offset of undistributed posttransaction E&P | D40: 13
B41: 14 | C41: Balance at beginning of next year | D41: 14 | F41: =SUM(F31:F36)+F40 -> 0 | H41: =SUM(H31:H36)+H40 -> 0 | J41: =SUM(J31:J36)+J40 -> 0 | L41: =SUM(L31:L36)+L40 -> 0 | N41: =SUM(N31:N36)+N40 -> 0 | P41: =SUM(P31:P36)+P40 -> 0 | R41: =SUM(R31:R36)+R40 -> 0 | T41: =SUM(T31:T36)+T40 -> 0 | V41: =SUM(V31:V36)+V40 -> 0 | X41: =SUM(X31:X36)+X40 -> 0 | Z41: =SUM(Z31:Z36)+Z40 -> 0 | AB41: =SUM(AB31:AB36)+AB40 -> 0 | AD41: =SUM(AD31:AD36)+AD40 -> 0 | AF41: =SUM(AF31:AF36)+AF40 -> 0 | AH41: =SUM(F41:AF41) -> 0
C44: Part II - Nonpreviously Taxed E&P Subject to Recapture as Subpart F Income
B46: 1 | C46: Balance at beginning of year | E46: 1
B47: 2 | C47: Additions (amounts subject to future recapture) | E47: 2
B48: 3 | C48: Subtractions (amounts recaptured in current year) | E48: 3
B49: 4 | C49: Balance at end of year | E49: 4 | F49: =SUM(F46:F48) -> 0

Sheet Schedule M
A1: ='Basic Information'!B4 -> 0
A2: TRANSACTIONS BETWEEN CFC AND RELATED PERSONS - SCHEDULE M
A3: ='Basic Information'!B1 -> 12/31/24
A4: (Amounts in US Dollars)
B8: (a) | E8: (b) | G8: (c) | I8: (d) | K8: (e) | M8: (f)
B9: Transactions of foreign corporation | D9: REF | E9: US person filing this return | F9: REF | G9: US entity controlled by US person filing this return | H9: REF | I9: Foreign entity controlled by US person filing this return | J9: REF | K9: 10% US shareholder of CFC | L9: REF | M9: 10% US shareholder of any corporate shareholder
A10: 1 | B10: Sales of stock in trade | C10: 1
A11: 2 | B11: Sales of tangible property other than stock in trade | C11: 2
A12: 3 | B12: Sales of property rights | C12: 3
A13: 4 | B13: Platform contribution transaction payments received | C13: 4
A14: 5 | B14: Cost sharing transaction payments received | C14: 5
A15: 6 | B15: Compensation received for technical, managerial, engineering, construction | C15: 6
A16: 7 | B16: Commissions received | C16: 7
A17: 8 | B17: Rents, royalties, and license fees received | C17: 8
A18: 9 | B18: Hybrid dividends received | C18: 9
A19: 10 | B19: Dividends received | C19: 10
A20: 11 | B20: Interest received | C20: 11
A21: 12 | B21: Premiums received for insurance or reinsurance | C21: 12
A22: 13 | B22: Total | C22: 13 | E22: =SUM(E10:E21) -> 0 | G22: =SUM(G10:G21) -> 0 | I22: =SUM(I10:I21) -> 0 | K22: =SUM(K10:K21) -> 0 | M22: =SUM(M10:M21) -> 0
A23: 14 | B23: Purchases of stock in trade | C23: 14
A24: 15 | B24: Purchases of tangible property other than stock in trade | C24: 15
A25: 16 | B25: Purchases of property rights | C25: 16
A26: 17 | B26: Platform contribution transaction payments paid | C26: 17
A27: 18 | B27: Cost sharing transaction payments paid | C27: 18
A28: 19 | B28: Compensation paid for technical, managerial, engineering, construction | C28: 19
A29: 20 | B29: Commissions paid | C29: 20
A30: 21 | B30: Rents, royalties, and license fees paid | C30: 21
A31: 22 | B31: Hybrid dividends paid | C31: 22
A32: 23 | B32: Dividends paid | C32: 23
A33: 24 | B33: Interest paid | C33: 24
A34: 25 | B34: Premiums paid for insurance or reinsurance | C34: 25
A35: 26 | B35: Total | C35: 26 | E35: =SUM(E23:E34) -> 0 | G35: =SUM(G23:G34) -> 0 | I35: =SUM(I23:I34) -> 0 | K35: =SUM(K23:K34) -> 0 | M35: =SUM(M23:M34) -> 0
A36: 27 | B36: Accounts Payable | C36: 27
A37: 28 | B37: Amounts borrowed (max balance during year) | C37: 28
A38: 29 | B38: Accounts Receivable | C38: 29
A39: 30 | B39: Amounts loaned (max balance during year) | C39: 30

Sheet Schedule P
A1: ='Basic Information'!B4 -> 0 | M1: 951A
A2: PREVIOUSLY TAXED E&P - SCHEDULE P | M2: FB - Foreign Branch
A3: ='Basic Information'!B1 -> 12/31/24 | M3: PAS - Passive
A4: (Amounts in Local Currency) | M4: 901j
M5: RBT - Re-sourced by Treaty
M6: GEN - General
B9: Income Category Code:
E10: TP Ownership % | G10: 1
B13: Part I - Accumulated E&P of Controlled Foreign Corporation | D13: (e) Previously Taxed E&P (section 959(c)(1)(A)) | N13: (e) Previously Taxed E&P (section 959(c)(2)(A)) | Y13: (q)
D14: REF | E14: (i) Section 965(a) "DFIC income" | F14: REF | G14: (ii) Section 965(b) "DFIC Deficit" | H14: REF | I14: (iii) General section 959(c)(1) | J14: REF | K14: (iv) Section 951A Inclusion "GILTI" | L14: REF | M14: (v) Section 245A(d) Inclusion "Hybrid Dividends" | N14: REF | O14: (vi) Section 965(a) Inclusion "DFIC Income" | P14: REF | Q14: (vii) Section 965(b)(4)(A) "DFIC Deficit" | R14: REF | S14: (viii) Section 951A Inclusion "GILTI" | T14: REF | U14: (ix) Section 245A(d) Inclusion "Hybrid Dividends" | V14: REF | W14: (x) Section 951(a)(1)(A)) Inclusion "Subpart F" | X14: REF | Y14: Total E&P
A15: 1a | B15: Balance at beginning of year | C15: 1a | E15: =INDEX('Schedule J'!N$15:N$41,MATCH($A15,'Schedule J'!$A$15:$A$41,0))*$G$10 -> 0 | G15: =INDEX('Schedule J'!P$15:P$41,MATCH($A15,'Schedule J'!$A$15:$A$41,0))*$G$10 -> 0 | I15: =INDEX('Schedule J'!R$15:R$41,MATCH($A15,'Schedule J'!$A$15:$A$41,0))*$G$10 -> 0 | K15: =INDEX('Schedule J'!T$15:T$41,MATCH($A15,'Schedule J'!$A$15:$A$41,0))*$G$10 -> 0 | M15: =INDEX('Schedule J'!V$15:V$41,MATCH($A15,'Schedule J'!$A$15:$A$41,0))*$G$10 -> 0 | O15: =INDEX('Schedule J'!X$15:X$41,MATCH($A15,'Schedule J'!$A$15:$A$41,0))*$G$10 -> 0 | Q15: =INDEX('Schedule J'!Z$15:Z$41,MATCH($A15,'Schedule J'!$A$15:$A$41,0))*$G$10 -> 0 | S15: =INDEX('Schedule J'!AB$15:AB$41,MATCH($A15,'Schedule J'!$A$15:$A$41,0))*$G$10 -> 0 | U15: =INDEX('Schedule J'!AD$15:AD$41,MATCH($A15,'Schedule J'!$A$15:$A$41,0))*$G$10 -> 0 | W15: =INDEX('Schedule J'!AF$15:AF$41,MATCH($A15,'Schedule J'!$A$15:$A$41,0))*$G$10 -> 0 | Y15: =SUM(E15:W15) -> 0
A16: 1b | B16: Beginning balance adjustments | C16: 1b | E16: =INDEX('Schedule J'!N$15:N$41,MATCH($A16,'Schedule J'!$A$15:$A$41,0))*$G$10 -> 0 | G16: =INDEX('Schedule J'!P$15:P$41,MATCH($A16,'Schedule J'!$A$15:$A$41,0))*$G$10 -> 0 | I16: =INDEX('Schedule J'!R$15:R$41,MATCH($A16,'Schedule J'!$A$15:$A$41,0))*$G$10 -> 0 | K16: =INDEX('Schedule J'!T$15:T$41,MATCH($A16,'Schedule J'!$A$15:$A$41,0))*$G$10 -> 0 | M16: =INDEX('Schedule J'!V$15:V$41,MATCH($A16,'Schedule J'!$A$15:$A$41,0))*$G$10 -> 0 | O16: =INDEX('Schedule J'!X$15:X$41,MATCH($A16,'Schedule J'!$A$15:$A$41,0))*$G$10 -> 0 | Q16: =INDEX('Schedule J'!Z$15:Z$41,MATCH($A16,'Schedule J'!$A$15:$A$41,0))*$G$10 -> 0 | S16: =INDEX('Schedule J'!AB$15:AB$41,MATCH($A16,'Schedule J'!$A$15:$A$41,0))*$G$10 -> 0 | U16: =INDEX('Schedule J'!AD$15:AD$41,MATCH($A16,'Schedule J'!$A$15:$A$41,0))*$G$10 -> 0 | W16: =INDEX('Schedule J'!AF$15:AF$41,MATCH($A16,'Schedule J'!$A$15:$A$41,0))*$G$10 -> 0 | Y16: =SUM(E16:W16) -> 0
A17: 1c | B17: Adjusted beginning balance | C17: 1c | E17: =INDEX('Schedule J'!N$15:N$41,MATCH($A17,'Schedule J'!$A$15:$A$41,0))*$G$10 -> 0 | G17: =INDEX('Schedule J'!P$15:P$41,MATCH($A17,'Schedule J'!$A$15:$A$41,0))*$G$10 -> 0 | I17: =INDEX('Schedule J'!R$15:R$41,MATCH($A17,'Schedule J'!$A$15:$A$41,0))*$G$10 -> 0 | K17: =INDEX('Schedule J'!T$15:T$41,MATCH($A17,'Schedule J'!$A$15:$A$41,0))*$G$10 -> 0 | M17: =INDEX('Schedule J'!V$15:V$41,MATCH($A17,'Schedule J'!$A$15:$A$41,0))*$G$10 -> 0 | O17: =INDEX('Schedule J'!X$15:X$41,MATCH($A17,'Schedule J'!$A$15:$A$41,0))*$G$10 -> 0 | Q17: =INDEX('Schedule J'!Z$15:Z$41,MATCH($A17,'Schedule J'!$A$15:$A$41,0))*$G$10 -> 0 | S17: =INDEX('Schedule J'!AB$15:AB$41,MATCH($A17,'Schedule J'!$A$15:$A$41,0))*$G$10 -> 0 | U17: =INDEX('Schedule J'!AD$15:AD$41,MATCH($A17,'Schedule J'!$A$15:$A$41,0))*$G$10 -> 0 | W17: =INDEX('Schedule J'!AF$15:AF$41,MATCH($A17,'Schedule J'!$A$15:$A$41,0))*$G$10 -> 0 | Y17: =SUM(E17:W17) -> 0
A18: 2 | B18: Reduction for taxes unsuspended under anti-splitter rules | C18: 2 | E18: =INDEX('Schedule J'!N$15:N$41,MATCH($A18,'Schedule J'!$A$15:$A$41,0))*$G$10 -> 0 | G18: =INDEX('Schedule J'!P$15:P$41,MATCH($A18,'Schedule J'!$A$15:$A$41,0))*$G$10 -> 0 | I18: =INDEX('Schedule J'!R$15:R$41,MATCH($A18,'Schedule J'!$A$15:$A$41,0))*$G$10 -> 0 | K18: =INDEX('Schedule J'!T$15:T$41,MATCH($A18,'Schedule J'!$A$15:$A$41,0))*$G$10 -> 0 | M18: =INDEX('Schedule J'!V$15:V$41,MATCH($A18,'Schedule J'!$A$15:$A$41,0))*$G$10 -> 0 | O18: =INDEX('Schedule J'!X$15:X$41,MATCH($A18,'Schedule J'!$A$15:$A$41,0))*$G$10 -> 0 | Q18: =INDEX('Schedule J'!Z$15:Z$41,MATCH($A18,'Schedule J'!$A$15:$A$41,0))*$G$10 -> 0 | S18: =INDEX('Schedule J'!AB$15:AB$41,MATCH($A18,'Schedule J'!$A$15:$A$41,0))*$G$10 -> 0 | U18: =INDEX('Schedule J'!AD$15:AD$41,MATCH($A18,'Schedule J'!$A$15:$A$41,0))*$G$10 -> 0 | W18: =INDEX('Schedule J'!AF$15:AF$41,MATCH($A18,'Schedule J'!$A$15:$A$41,0))*$G$10 -> 0
A19: 3 | B19: E&P attributable to distributions of PTEP from lower-tier | C19: 3 | E19: =INDEX('Schedule J'!N$15:N$41,MATCH($A19,'Schedule J'!$A$15:$A$41,0))*$G$10 -> 0 | G19: =INDEX('Schedule J'!P$15:P$41,MATCH($A19,'Schedule J'!$A$15:$A$41,0))*$G$10 -> 0 | I19: =INDEX('Schedule J'!R$15:R$41,MATCH($A19,'Schedule J'!$A$15:$A$41,0))*$G$10 -> 0 | K19: =INDEX('Schedule J'!T$15:T$41,MATCH($A19,'Schedule J'!$A$15:$A$41,0))*$G$10 -> 0 | M19: =INDEX('Schedule J'!V$15:V$41,MATCH($A19,'Schedule J'!$A$15:$A$41,0))*$G$10 -> 0 | O19: =INDEX('Schedule J'!X$15:X$41,MATCH($A19,'Schedule J'!$A$15:$A$41,0))*$G$10 -> 0 | Q19: =INDEX('Schedule J'!Z$15:Z$41,MATCH($A19,'Schedule J'!$A$15:$A$41,0))*$G$10 -> 0 | S19: =INDEX('Schedule J'!AB$15:AB$41,MATCH($A19,'Schedule J'!$A$15:$A$41,0))*$G$10 -> 0 | U19: =INDEX('Schedule J'!AD$15:AD$41,MATCH($A19,'Schedule J'!$A$15:$A$41,0))*$G$10 -> 0 | W19: =INDEX('Schedule J'!AF$15:AF$41,MATCH($A19,'Schedule J'!$A$15:$A$41,0))*$G$10 -> 0 | Y19: =SUM(E19:W19) -> 0
A20: 4 | B20: E&P carried over in nonrecognition transaction | C20: 4 | E20: =INDEX('Schedule J'!N$15:N$41,MATCH($A20,'Schedule J'!$A$15:$A$41,0))*$G$10 -> 0 | G20: =INDEX('Schedule J'!P$15:P$41,MATCH($A20,'Schedule J'!$A$15:$A$41,0))*$G$10 -> 0 | I20: =INDEX('Schedule J'!R$15:R$41,MATCH($A20,'Schedule J'!$A$15:$A$41,0))*$G$10 -> 0 | K20: =INDEX('Schedule J'!T$15:T$41,MATCH($A20,'Schedule J'!$A$15:$A$41,0))*$G$10 -> 0 | M20: =INDEX('Schedule J'!V$15:V$41,MATCH($A20,'Schedule J'!$A$15:$A$41,0))*$G$10 -> 0 | O20: =INDEX('Schedule J'!X$15:X$41,MATCH($A20,'Schedule J'!$A$15:$A$41,0))*$G$10 -> 0 | Q20: =INDEX('Schedule J'!Z$15:Z$41,MATCH($A20,'Schedule J'!$A$15:$A$41,0))*$G$10 -> 0 | S20: =INDEX('Schedule J'!AB$15:AB$41,MATCH($A20,'Schedule J'!$A$15:$A$41,0))*$G$10 -> 0 | U20: =INDEX('Schedule J'!AD$15:AD$41,MATCH($A20,'Schedule J'!$A$15:$A$41,0))*$G$10 -> 0 | W20: =INDEX('Schedule J'!AF$15:AF$41,MATCH($A20,'Schedule J'!$A$15:$A$41,0))*$G$10 -> 0
A21: 5 | B21: Other pre-distribution & inclusion adjustments | C21: 5 | E21: =INDEX('Schedule J'!N$15:N$41,MATCH($A21,'Schedule J'!$A$15:$A$41,0))*$G$10 -> 0 | G21: =INDEX('Schedule J'!P$15:P$41,MATCH($A21,'Schedule J'!$A$15:$A$41,0))*$G$10 -> 0 | I21: =INDEX('Schedule J'!R$15:R$41,MATCH($A21,'Schedule J'!$A$15:$A$41,0))*$G$10 -> 0 | K21: =INDEX('Schedule J'!T$15:T$41,MATCH($A21,'Schedule J'!$A$15:$A$41,0))*$G$10 -> 0 | M21: =INDEX('Schedule J'!V$15:V$41,MATCH($A21,'Schedule J'!$A$15:$A$41,0))*$G$10 -> 0 | O21: =INDEX('Schedule J'!X$15:X$41,MATCH($A21,'Schedule J'!$A$15:$A$41,0))*$G$10 -> 0 | Q21: =INDEX('Schedule J'!Z$15:Z$41,MATCH($A21,'Schedule J'!$A$15:$A$41,0))*$G$10 -> 0 | S21: =INDEX('Schedule J'!AB$15:AB$41,MATCH($A21,'Schedule J'!$A$15:$A$41,0))*$G$10 -> 0 | U21: =INDEX('Schedule J'!AD$15:AD$41,MATCH($A21,'Schedule J'!$A$15:$A$41,0))*$G$10 -> 0 | W21: =INDEX('Schedule J'!AF$15:AF$41,MATCH($A21,'Schedule J'!$A$15:$A$41,0))*$G$10 -> 0
A22: 6 | B22: Total current and accumulated E&P | C22: 6 | E22: =INDEX('Schedule J'!N$15:N$41,MATCH($A22,'Schedule J'!$A$15:$A$41,0))*$G$10 -> 0 | G22: =INDEX('Schedule J'!P$15:P$41,MATCH($A22,'Schedule J'!$A$15:$A$41,0))*$G$10 -> 0 | I22: =INDEX('Schedule J'!R$15:R$41,MATCH($A22,'Schedule J'!$A$15:$A$41,0))*$G$10 -> 0 | K22: =INDEX('Schedule J'!T$15:T$41,MATCH($A22,'Schedule J'!$A$15:$A$41,0))*$G$10 -> 0 | M22: =INDEX('Schedule J'!V$15:V$41,MATCH($A22,'Schedule J'!$A$15:$A$41,0))*$G$10 -> 0 | O22: =INDEX('Schedule J'!X$15:X$41,MATCH($A22,'Schedule J'!$A$15:$A$41,0))*$G$10 -> 0 | Q22: =INDEX('Schedule J'!Z$15:Z$41,MATCH($A22,'Schedule J'!$A$15:$A$41,0))*$G$10 -> 0 | S22: =INDEX('Schedule J'!AB$15:AB$41,MATCH($A22,'Schedule J'!$A$15:$A$41,0))*$G$10 -> 0 | U22: =INDEX('Schedule J'!AD$15:AD$41,MATCH($A22,'Schedule J'!$A$15:$A$41,0))*$G$10 -> 0 | W22: =INDEX('Schedule J'!AF$15:AF$41,MATCH($A22,'Schedule J'!$A$15:$A$41,0))*$G$10 -> 0
A23: 7 | B23: Amounts reclasified to 959(c)(2) from 959(c)(3) E&P | C23: 7 | O23: =INDEX('Schedule J'!X$15:X$41,MATCH($A23,'Schedule J'!$A$15:$A$41,0))*$G$10 -> 0 | Q23: =INDEX('Schedule J'!Z$15:Z$41,MATCH($A23,'Schedule J'!$A$15:$A$41,0))*$G$10 -> 0 | S23: =INDEX('Schedule J'!AB$15:AB$41,MATCH($A23,'Schedule J'!$A$15:$A$41,0))*$G$10 -> 0 | U23: =INDEX('Schedule J'!AD$15:AD$41,MATCH($A23,'Schedule J'!$A$15:$A$41,0))*$G$10 -> 0 | W23: =INDEX('Schedule J'!AF$15:AF$41,MATCH($A23,'Schedule J'!$A$15:$A$41,0))*$G$10 -> 0
A24: 8 | B24: Actual distributions | C24: 8 | E24: =INDEX('Schedule J'!N$15:N$41,MATCH($A24,'Schedule J'!$A$15:$A$41,0))*$G$10 -> 0 | G24: =INDEX('Schedule J'!P$15:P$41,MATCH($A24,'Schedule J'!$A$15:$A$41,0))*$G$10 -> 0 | I24: =INDEX('Schedule J'!R$15:R$41,MATCH($A24,'Schedule J'!$A$15:$A$41,0))*$G$10 -> 0 | K24: =INDEX('Schedule J'!T$15:T$41,MATCH($A24,'Schedule J'!$A$15:$A$41,0))*$G$10 -> 0 | M24: =INDEX('Schedule J'!V$15:V$41,MATCH($A24,'Schedule J'!$A$15:$A$41,0))*$G$10 -> 0 | O24: =INDEX('Schedule J'!X$15:X$41,MATCH($A24,'Schedule J'!$A$15:$A$41,0))*$G$10 -> 0 | Q24: =INDEX('Schedule J'!Z$15:Z$41,MATCH($A24,'Schedule J'!$A$15:$A$41,0))*$G$10 -> 0 | S24: =INDEX('Schedule J'!AB$15:AB$41,MATCH($A24,'Schedule J'!$A$15:$A$41,0))*$G$10 -> 0 | U24: =INDEX('Schedule J'!AD$15:AD$41,MATCH($A24,'Schedule J'!$A$15:$A$41,0))*$G$10 -> 0 | W24: =INDEX('Schedule J'!AF$15:AF$41,MATCH($A24,'Schedule J'!$A$15:$A$41,0))*$G$10 -> 0
A25: 9 | B25: Amounts reclasified to 959(c)(1) from 959(c)(2) E&P | C25: 9 | E25: =INDEX('Schedule J'!N$15:N$41,MATCH($A25,'Schedule J'!$A$15:$A$41,0))*$G$10 -> 0 | G25: =INDEX('Schedule J'!P$15:P$41,MATCH($A25,'Schedule J'!$A$15:$A$41,0))*$G$10 -> 0 | I25: =INDEX('Schedule J'!R$15:R$41,MATCH($A25,'Schedule J'!$A$15:$A$41,0))*$G$10 -> 0 | K25: =INDEX('Schedule J'!T$15:T$41,MATCH($A25,'Schedule J'!$A$15:$A$41,0))*$G$10 -> 0 | M25: =INDEX('Schedule J'!V$15:V$41,MATCH($A25,'Schedule J'!$A$15:$A$41,0))*$G$10 -> 0 | O25: =INDEX('Schedule J'!X$15:X$41,MATCH($A25,'Schedule J'!$A$15:$A$41,0))*$G$10 -> 0 | Q25: =INDEX('Schedule J'!Z$15:Z$41,MATCH($A25,'Schedule J'!$A$15:$A$41,0))*$G$10 -> 0 | S25: =INDEX('Schedule J'!AB$15:AB$41,MATCH($A25,'Schedule J'!$A$15:$A$41,0))*$G$10 -> 0 | U25: =INDEX('Schedule J'!AD$15:AD$41,MATCH($A25,'Schedule J'!$A$15:$A$41,0))*$G$10 -> 0 | W25: =INDEX('Schedule J'!AF$15:AF$41,MATCH($A25,'Schedule J'!$A$15:$A$41,0))*$G$10 -> 0
A26: 10 | B26: Amounts included as earnings invested in US property and reclassified to 959(c)(1) E&P | C26: 10 | I26: =INDEX('Schedule J'!R$15:R$41,MATCH($A26,'Schedule J'!$A$15:$A$41,0)) -> 0
A27: 11 | B27: Other adjustments | C27: 11 | E27: =INDEX('Schedule J'!N$15:N$41,MATCH($A27,'Schedule J'!$A$15:$A$41,0))*$G$10 -> 0 | G27: =INDEX('Schedule J'!P$15:P$41,MATCH($A27,'Schedule J'!$A$15:$A$41,0))*$G$10 -> 0 | I27: ='Schedule J'!R36 -> 0 | K27: =INDEX('Schedule J'!T$15:T$41,MATCH($A27,'Schedule J'!$A$15:$A$41,0))*$G$10 -> 0 | M27: =INDEX('Schedule J'!V$15:V$41,MATCH($A27,'Schedule J'!$A$15:$A$41,0))*$G$10 -> 0 | O27: =INDEX('Schedule J'!X$15:X$41,MATCH($A27,'Schedule J'!$A$15:$A$41,0))*$G$10 -> 0 | Q27: =INDEX('Schedule J'!Z$15:Z$41,MATCH($A27,'Schedule J'!$A$15:$A$41,0))*$G$10 -> 0 | S27: =INDEX('Schedule J'!AB$15:AB$41,MATCH($A27,'Schedule J'!$A$15:$A$41,0))*$G$10 -> 0 | U27: =INDEX('Schedule J'!AD$15:AD$41,MATCH($A27,'Schedule J'!$A$15:$A$41,0))*$G$10 -> 0 | W27: =INDEX('Schedule J'!AF$15:AF$41,MATCH($A27,'Schedule J'!$A$15:$A$41,0))*$G$10 -> 0
A28: 12 | B28: Balance at beginning of next year | C28: 12 | E28: =SUM(E22:E27) -> 0 | G28: =SUM(G22:G27) -> 0 | I28: =SUM(I22:I27) -> 0 | K28: =SUM(K22:K27) -> 0 | M28: =SUM(M22:M27) -> 0 | O28: =SUM(O22:O27) -> 0 | Q28: =SUM(Q22:Q27) -> 0 | S28: =SUM(S22:S27) -> 0 | U28: =SUM(U22:U27) -> 0 | W28: =SUM(W22:W27) -> 0 | Y28: =SUM(E28:W28) -> 0
B32: USD Currency | H32: Weighed Avarege Exchange Rate: | I32: ='Basic Information'!C59 -> 0 | J32: D-50
B33: Part I - Accumulated E&P of Controlled Foreign Corporation | D33: (e) Previously Taxed E&P (section 959(c)(1)(A)) | N33: (e) Previously Taxed E&P (section 959(c)(2)(A)) | Y33: (q)
D34: REF | E34: (i) Section 965(a) "DFIC income" | F34: REF | G34: (ii) Section 965(b) "DFIC Deficit" | H34: REF | I34: (iii) General section 959(c)(1) | J34: REF | K34: (iv) Section 951A Inclusion "GILTI" | L34: REF | M34: (v) Section 245A(d) Inclusion "Hybrid Dividends" | N34: REF | O34: (vi) Section 965(a) Inclusion "DFIC Income" | P34: REF | Q34: (vii) Section 965(b)(4)(A) "DFIC Deficit" | R34: REF | S34: (viii) Section 951A Inclusion "GILTI" | T34: REF | U34: (ix) Section 245A(d) Inclusion "Hybrid Dividends" | V34: REF | W34: (x) Section 951(a)(1)(A)) Inclusion "Subpart F" | X34: REF | Y34: Total E&P
A35: 1a | B35: Balance at beginning of year | C35: 1a | E35: =ROUND(E15/$I$32,0) -> #DIV/0! | G35: =ROUND(G15/$I$32,0) -> #DIV/0! | I35: =ROUND(I15/$I$32,0) -> #DIV/0! | K35: =ROUND(K15/$I$32,0) -> #DIV/0! | M35: =ROUND(M15/$I$32,0) -> #DIV/0! | O35: =ROUND(O15/$I$32,0) -> #DIV/0! | Q35: =ROUND(Q15/$I$32,0) -> #DIV/0! | S35: =ROUND(S15/$I$32,0) -> #DIV/0! | U35: =ROUND(U15/$I$32,0) -> #DIV/0! | W35: =ROUND(W15/$I$32,0) -> #DIV/0! | Y35: =SUM(E35:W35) -> #DIV/0!
A36: 1b | B36: Beginning balance adjustments | C36: 1b | E36: =ROUND(E16/$I$32,0) -> #DIV/0! | G36: =ROUND(G16/$I$32,0) -> #DIV/0! | I36: =ROUND(I16/$I$32,0) -> #DIV/0! | K36: =ROUND(K16/$I$32,0) -> #DIV/0! | M36: =ROUND(M16/$I$32,0) -> #DIV/0! | O36: =ROUND(O16/$I$32,0) -> #DIV/0! | Q36: =ROUND(Q16/$I$32,0) -> #DIV/0! | S36: =ROUND(S16/$I$32,0) -> #DIV/0! | U36: =ROUND(U16/$I$32,0) -> #DIV/0! | W36: =ROUND(W16/$I$32,0) -> #DIV/0! | Y36: =SUM(E36:W36) -> #DIV/0!
A37: 1c | B37: Adjusted beginning balance | C37: 1c | E37: =ROUND(E17/$I$32,0) -> #DIV/0! | G37: =ROUND(G17/$I$32,0) -> #DIV/0! | I37: =ROUND(I17/$I$32,0) -> #DIV/0! | K37: =ROUND(K17/$I$32,0) -> #DIV/0! | M37: =ROUND(M17/$I$32,0) -> #DIV/0! | O37: =ROUND(O17/$I$32,0) -> #DIV/0! | Q37: =ROUND(Q17/$I$32,0) -> #DIV/0! | S37: =ROUND(S17/$I$32,0) -> #DIV/0! | U37: =ROUND(U17/$I$32,0) -> #DIV/0! | W37: =ROUND(W17/$I$32,0) -> #DIV/0! | Y37: =SUM(E37:W37) -> #DIV/0!
A38: 2 | B38: Reduction for taxes unsuspended under anti-splitter rules | C38: 2 | E38: =ROUND(E18/$I$32,0) -> #DIV/0! | G38: =ROUND(G18/$I$32,0) -> #DIV/0! | I38: =ROUND(I18/$I$32,0) -> #DIV/0! | K38: =ROUND(K18/$I$32,0) -> #DIV/0! | M38: =ROUND(M18/$I$32,0) -> #DIV/0! | O38: =ROUND(O18/$I$32,0) -> #DIV/0! | Q38: =ROUND(Q18/$I$32,0) -> #DIV/0! | S38: =ROUND(S18/$I$32,0) -> #DIV/0! | U38: =ROUND(U18/$I$32,0) -> #DIV/0! | W38: =ROUND(W18/$I$32,0) -> #DIV/0!
A39: 3 | B39: E&P attributable to distributions of PTEP from lower-tier | C39: 3 | E39: =ROUND(E19/$I$32,0) -> #DIV/0! | G39: =ROUND(G19/$I$32,0) -> #DIV/0! | I39: =ROUND(I19/$I$32,0) -> #DIV/0! | K39: =ROUND(K19/$I$32,0) -> #DIV/0! | M39: =ROUND(M19/$I$32,0) -> #DIV/0! | O39: =ROUND(O19/$I$32,0) -> #DIV/0! | Q39: =ROUND(Q19/$I$32,0) -> #DIV/0! | S39: =ROUND(S19/$I$32,0) -> #DIV/0! | U39: =ROUND(U19/$I$32,0) -> #DIV/0! | W39: =ROUND(W19/$I$32,0) -> #DIV/0! | Y39: =SUM(E39:W39) -> #DIV/0!
A40: 4 | B40: E&P carried over in nonrecognition transaction | C40: 4 | E40: =ROUND(E20/$I$32,0) -> #DIV/0! | G40: =ROUND(G20/$I$32,0) -> #DIV/0! | I40: =ROUND(I20/$I$32,0) -> #DIV/0! | K40: =ROUND(K20/$I$32,0) -> #DIV/0! | M40: =ROUND(M20/$I$32,0) -> #DIV/0! | O40: =ROUND(O20/$I$32,0) -> #DIV/0! | Q40: =ROUND(Q20/$I$32,0) -> #DIV/0! | S40: =ROUND(S20/$I$32,0) -> #DIV/0! | U40: =ROUND(U20/$I$32,0) -> #DIV/0! | W40: =ROUND(W20/$I$32,0) -> #DIV/0!
A41: 5 | B41: Other pre-distribution & inclusion adjustments | C41: 5 | E41: =ROUND(E21/$I$32,0) -> #DIV/0! | G41: =ROUND(G21/$I$32,0) -> #DIV/0! | I41: =ROUND(I21/$I$32,0) -> #DIV/0! | K41: =ROUND(K21/$I$32,0) -> #DIV/0! | M41: =ROUND(M21/$I$32,0) -> #DIV/0! | O41: =ROUND(O21/$I$32,0) -> #DIV/0! | Q41: =ROUND(Q21/$I$32,0) -> #DIV/0! | S41: =ROUND(S21/$I$32,0) -> #DIV/0! | U41: =ROUND(U21/$I$32,0) -> #DIV/0! | W41: =ROUND(W21/$I$32,0) -> #DIV/0!
A42: 6 | B42: Total current and accumulated E&P | C42: 6 | E42: =ROUND(E22/$I$32,0) -> #DIV/0! | G42: =ROUND(G22/$I$32,0) -> #DIV/0! | I42: =ROUND(I22/$I$32,0) -> #DIV/0! | K42: =ROUND(K22/$I$32,0) -> #DIV/0! | M42: =ROUND(M22/$I$32,0) -> #DIV/0! | O42: =ROUND(O22/$I$32,0) -> #DIV/0! | Q42: =ROUND(Q22/$I$32,0) -> #DIV/0! | S42: =ROUND(S22/$I$32,0) -> #DIV/0! | U42: =ROUND(U22/$I$32,0) -> #DIV/0! | W42: =ROUND(W22/$I$32,0) -> #DIV/0!
A43: 7 | B43: Amounts reclasified to 959(c)(2) from 959(c)(3) E&P | C43: 7 | O43: =ROUND(O23/$I$32,0) -> #DIV/0! | Q43: =ROUND(Q23/$I$32,0) -> #DIV/0! | S43: =ROUND(S23/$I$32,0) -> #DIV/0! | U43: =ROUND(U23/$I$32,0) -> #DIV/0! | W43: =ROUND(W23/$I$32,0) -> #DIV/0!
A44: 8 | B44: Actual distributions | C44: 8 | E44: =ROUND(E24/$I$32,0) -> #DIV/0! | G44: =ROUND(G24/$I$32,0) -> #DIV/0! | I44: =ROUND(I24/$I$32,0) -> #DIV/0! | K44: =ROUND(K24/$I$32,0) -> #DIV/0! | M44: =ROUND(M24/$I$32,0) -> #DIV/0! | O44: =ROUND(O24/$I$32,0) -> #DIV/0! | Q44: =ROUND(Q24/$I$32,0) -> #DIV/0! | S44: =ROUND(S24/$I$32,0) -> #DIV/0! | U44: =ROUND(U24/$I$32,0) -> #DIV/0! | W44: =ROUND(W24/$I$32,0) -> #DIV/0!
A45: 9 | B45: Amounts reclasified to 959(c)(1) from 959(c)(2) E&P | C45: 9 | E45: =ROUND(E25/$I$32,0) -> #DIV/0! | G45: =ROUND(G25/$I$32,0) -> #DIV/0! | I45: =ROUND(I25/$I$32,0) -> #DIV/0! | K45: =ROUND(K25/$I$32,0) -> #DIV/0! | O45: =ROUND(O25/$I$32,0) -> #DIV/0! | Q45: =ROUND(Q25/$I$32,0) -> #DIV/0! | S45: =ROUND(S25/$I$32,0) -> #DIV/0! | U45: =ROUND(U25/$I$32,0) -> #DIV/0! | W45: =ROUND(W25/$I$32,0) -> #DIV/0!
A46: 10 | B46: Amounts included as earnings invested in US property and reclassified to 959(c)(1) E&P | C46: 10 | I46: =ROUND(I26/$I$32,0) -> #DIV/0!
A47: 11 | B47: Other adjustments | C47: 11 | E47: =ROUND(E27/$I$32,0) -> #DIV/0! | G47: =ROUND(G27/$I$32,0) -> #DIV/0! | I47: =ROUND(I27/$I$32,0) -> #DIV/0! | K47: =ROUND(K27/$I$32,0) -> #DIV/0! | M47: =ROUND(M27/$I$32,0) -> #DIV/0! | O47: =ROUND(O27/$I$32,0) -> #DIV/0! | Q47: =ROUND(Q27/$I$32,0) -> #DIV/0! | S47: =ROUND(S27/$I$32,0) -> #DIV/0! | U47: =ROUND(U27/$I$32,0) -> #DIV/0! | W47: =ROUND(W27/$I$32,0) -> #DIV/0!
A48: 12 | B48: Balance at beginning of next year | C48: 12 | E48: =SUM(E42:E47) -> #DIV/0! | G48: =SUM(G42:G47) -> #DIV/0! | I48: =SUM(I42:I47) -> #DIV/0! | K48: =SUM(K42:K47) -> #DIV/0! | M48: =SUM(M42:M47) -> #DIV/0! | O48: =SUM(O42:O47) -> #DIV/0! | Q48: =SUM(Q42:Q47) -> #DIV/0! | S48: =SUM(S42:S47) -> #DIV/0! | U48: =SUM(U42:U47) -> #DIV/0! | W48: =SUM(W42:W47) -> #DIV/0! | Y48: =SUM(E48:W48) -> #DIV/0!

Sheet Schedule Q
B1: ='Basic Information'!B4 -> 0 | N1: 951A | X1: 951A
B2: CFC Income by CFC Income Groups - SCHEDULE Q | N2: FB - Foreign Branch | X2: FB - Foreign Branch
B3: ='Basic Information'!B1 -> 12/31/24 | N3: PAS - Passive | X3: PAS - Passive
B4: (Amounts in Local Currency) | N4: 901j
N5: RBT - Re-sourced by Treaty
N6: GEN - General
C9: Income Category Code:
C13: Enter amounts in functional currency of the foreign corporation
E14: REF | F14: (i) Country code | G14: REF | H14: (ii) Gross income | I14: REF | J14: (iii) Definitely related expenses | K14: REF | L14: (iv) Related person interest expense | M14: REF | N14: (v) Other interest expense | O14: REF | P14: (vi) Research & experimental expenses | Q14: REF | R14: (vii) Other expenses (attach schedule) | S14: REF | T14: (viii) Current year tax on reattribution income from disregarded payments | U14: REF | V14: (ix) Current year tax on all other disregarded payments | W14: REF | X14: (x) Other current year taxes | Y14: REF | Z14: (xi) Net income | AA14: REF | AB14: (xii) Foreign taxes for which credit allowed (USD) | AC14: REF | AD14: (xiii) Average asset value | AE14: REF | AF14: (xiv) high tax election
B15: 1 | C15: Subpart F Income Groups
B16: 1a | C16: Dividends, interest, rents, royalties & annuities (total) | H16: =SUM(H17:H19) -> 0 | J16: =SUM(J17:J19) -> 0 | L16: =SUM(L17:L19) -> 0 | N16: =SUM(N17:N19) -> 0 | P16: =SUM(P17:P19) -> 0 | R16: =SUM(R17:R19) -> 0 | T16: =SUM(T17:T19) -> 0 | V16: =SUM(V17:V19) -> 0 | X16: =SUM(X17:X19) -> 0 | Z16: =SUM(Z17:Z19) -> 0 | AB16: =SUM(AB17:AB19) -> 0 | AD16: =SUM(AD17:AD19) -> 0
C17: Unit name 1 | H17: 0 | J17: 0 | L17: 0 | N17: 0 | P17: 0 | R17: 0 | T17: 0 | V17: 0 | X17: 0 | Z17: =H17-(J17+L17+N17+P17+R17+T17+V17+X17) -> 0 | AB17: 0 | AD17: 0
C18: Unit name 2 | H18: 0 | J18: 0 | L18: 0 | N18: 0 | P18: 0 | R18: 0 | T18: 0 | V18: 0 | X18: 0 | Z18: =H18-(J18+L18+N18+P18+R18+T18+V18+X18) -> 0 | AB18: 0 | AD18: 0
C19: Unit name 3 | H19: 0 | J19: 0 | L19: 0 | N19: 0 | P19: 0 | R19: 0 | T19: 0 | V19: 0 | X19: 0 | Z19: =H19-(J19+L19+N19+P19+R19+T19+V19+X19) -> 0 | AB19: 0 | AD19: 0
B20: 1b | C20: Net gain from certain property transactions (total) | H20: =SUM(H21:H23) -> 0 | J20: =SUM(J21:J23) -> 0 | L20: =SUM(L21:L23) -> 0 | N20: =SUM(N21:N23) -> 0 | P20: =SUM(P21:P23) -> 0 | R20: =SUM(R21:R23) -> 0 | T20: =SUM(T21:T23) -> 0 | V20: =SUM(V21:V23) -> 0 | X20: =SUM(X21:X23) -> 0 | Z20: =SUM(Z21:Z23) -> 0 | AB20: =SUM(AB21:AB23) -> 0 | AD20: =SUM(AD21:AD23) -> 0
C21: Unit name 1 | H21: 0 | J21: 0 | L21: 0 | N21: 0 | P21: 0 | R21: 0 | T21: 0 | V21: 0 | X21: 0 | Z21: =H21-(J21+L21+N21+P21+R21+T21+V21+X21) -> 0 | AB21: 0 | AD21: 0
C22: Unit name 2 | H22: 0 | J22: 0 | L22: 0 | N22: 0 | P22: 0 | R22: 0 | T22: 0 | V22: 0 | X22: 0 | Z22: =H22-(J22+L22+N22+P22+R22+T22+V22+X22) -> 0 | AB22: 0 | AD22: 0
C23: Unit name 3 | H23: 0 | J23: 0 | L23: 0 | N23: 0 | P23: 0 | R23: 0 | T23: 0 | V23: 0 | X23: 0 | Z23: =H23-(J23+L23+N23+P23+R23+T23+V23+X23) -> 0 | AB23: 0 | AD23: 0
B24: 1c | C24: Net gain from commodities transactions (total) | H24: =SUM(H25:H27) -> 0 | J24: =SUM(J25:J27) -> 0 | L24: =SUM(L25:L27) -> 0 | N24: =SUM(N25:N27) -> 0 | P24: =SUM(P25:P27) -> 0 | R24: =SUM(R25:R27) -> 0 | T24: =SUM(T25:T27) -> 0 | V24: =SUM(V25:V27) -> 0 | X24: =SUM(X25:X27) -> 0 | Z24: =SUM(Z25:Z27) -> 0 | AB24: =SUM(AB25:AB27) -> 0 | AD24: =SUM(AD25:AD27) -> 0
C25: Unit name 1 | H25: 0 | J25: 0 | L25: 0 | N25: 0 | P25: 0 | R25: 0 | T25: 0 | V25: 0 | X25: 0 | Z25: =H25-(J25+L25+N25+P25+R25+T25+V25+X25) -> 0 | AB25: 0 | AD25: 0
C26: Unit name 2 | H26: 0 | J26: 0 | L26: 0 | N26: 0 | P26: 0 | R26: 0 | T26: 0 | V26: 0 | X26: 0 | Z26: =H26-(J26+L26+N26+P26+R26+T26+V26+X26) -> 0 | AB26: 0 | AD26: 0
C27: Unit name 3 | H27: 0 | J27: 0 | L27: 0 | N27: 0 | P27: 0 | R27: 0 | T27: 0 | V27: 0 | X27: 0 | Z27: =H27-(J27+L27+N27+P27+R27+T27+V27+X27) -> 0 | AB27: 0 | AD27: 0
B28: 1d | C28: Net foreign currency gain (total) | H28: =SUM(H29:H31) -> 0 | J28: =SUM(J29:J31) -> 0 | L28: =SUM(L29:L31) -> 0 | N28: =SUM(N29:N31) -> 0 | P28: =SUM(P29:P31) -> 0 | R28: =SUM(R29:R31) -> 0 | T28: =SUM(T29:T31) -> 0 | V28: =SUM(V29:V31) -> 0 | X28: =SUM(X29:X31) -> 0 | Z28: =SUM(Z29:Z31) -> 0 | AB28: =SUM(AB29:AB31) -> 0 | AD28: =SUM(AD29:AD31) -> 0
C29: Unit name 1 | H29: 0 | J29: 0 | L29: 0 | N29: 0 | P29: 0 | R29: 0 | T29: 0 | V29: 0 | X29: 0 | Z29: =H29-(J29+L29+N29+P29+R29+T29+V29+X29) -> 0 | AB29: 0 | AD29: 0
C30: Unit name 2 | H30: 0 | J30: 0 | L30: 0 | N30: 0 | P30: 0 | R30: 0 | T30: 0 | V30: 0 | X30: 0 | Z30: =H30-(J30+L30+N30+P30+R30+T30+V30+X30) -> 0 | AB30: 0 | AD30: 0
C31: Unit name 3 | H31: 0 | J31: 0 | L31: 0 | N31: 0 | P31: 0 | R31: 0 | T31: 0 | V31: 0 | X31: 0 | Z31: =H31-(J31+L31+N31+P31+R31+T31+V31+X31) -> 0 | AB31: 0 | AD31: 0
B32: 1e | C32: Income equivalent to interest (total) | H32: =SUM(H33:H35) -> 0 | J32: =SUM(J33:J35) -> 0 | L32: =SUM(L33:L35) -> 0 | N32: =SUM(N33:N35) -> 0 | P32: =SUM(P33:P35) -> 0 | R32: =SUM(R33:R35) -> 0 | T32: =SUM(T33:T35) -> 0 | V32: =SUM(V33:V35) -> 0 | X32: =SUM(X33:X35) -> 0 | Z32: =SUM(Z33:Z35) -> 0 | AB32: =SUM(AB33:AB35) -> 0 | AD32: =SUM(AD33:AD35) -> 0
C33: Unit name 1 | H33: 0 | J33: 0 | L33: 0 | N33: 0 | P33: 0 | R33: 0 | T33: 0 | V33: 0 | X33: 0 | Z33: =H33-(J33+L33+N33+P33+R33+T33+V33+X33) -> 0 | AB33: 0 | AD33: 0
C34: Unit name 2 | H34: 0 | J34: 0 | L34: 0 | N34: 0 | P34: 0 | R34: 0 | T34: 0 | V34: 0 | X34: 0 | Z34: =H34-(J34+L34+N34+P34+R34+T34+V34+X34) -> 0 | AB34: 0 | AD34: 0
C35: Unit name 3 | H35: 0 | J35: 0 | L35: 0 | N35: 0 | P35: 0 | R35: 0 | T35: 0 | V35: 0 | X35: 0 | Z35: =H35-(J35+L35+N35+P35+R35+T35+V35+X35) -> 0 | AB35: 0 | AD35: 0
B36: 1f | C36: Foreign base company sales income (total) | H36: =SUM(H37:H39) -> 0 | J36: =SUM(J37:J39) -> 0 | L36: =SUM(L37:L39) -> 0 | N36: =SUM(N37:N39) -> 0 | P36: =SUM(P37:P39) -> 0 | R36: =SUM(R37:R39) -> 0 | T36: =SUM(T37:T39) -> 0 | V36: =SUM(V37:V39) -> 0 | X36: =SUM(X37:X39) -> 0 | Z36: =SUM(Z37:Z39) -> 0 | AB36: =SUM(AB37:AB39) -> 0 | AD36: =SUM(AD37:AD39) -> 0
C37: Unit name 1 | H37: 0 | J37: 0 | L37: 0 | N37: 0 | P37: 0 | R37: 0 | T37: 0 | V37: 0 | X37: 0 | Z37: =H37-(J37+L37+N37+P37+R37+T37+V37+X37) -> 0 | AB37: 0 | AD37: 0
C38: Unit name 2 | H38: 0 | J38: 0 | L38: 0 | N38: 0 | P38: 0 | R38: 0 | T38: 0 | V38: 0 | X38: 0 | Z38: =H38-(J38+L38+N38+P38+R38+T38+V38+X38) -> 0 | AB38: 0 | AD38: 0
C39: Unit name 3 | H39: 0 | J39: 0 | L39: 0 | N39: 0 | P39: 0 | R39: 0 | T39: 0 | V39: 0 | X39: 0 | Z39: =H39-(J39+L39+N39+P39+R39+T39+V39+X39) -> 0 | AB39: 0 | AD39: 0
B40: 1g | C40: Foreign base company services income (total) | H40: =SUM(H41:H43) -> 0 | J40: =SUM(J41:J43) -> 0 | L40: =SUM(L41:L43) -> 0 | N40: =SUM(N41:N43) -> 0 | P40: =SUM(P41:P43) -> 0 | R40: =SUM(R41:R43) -> 0 | T40: =SUM(T41:T43) -> 0 | V40: =SUM(V41:V43) -> 0 | X40: =SUM(X41:X43) -> 0 | Z40: =SUM(Z41:Z43) -> 0 | AB40: =SUM(AB41:AB43) -> 0 | AD40: =SUM(AD41:AD43) -> 0
C41: Unit name 1 | H41: 0 | J41: 0 | L41: 0 | N41: 0 | P41: 0 | R41: 0 | T41: 0 | V41: 0 | X41: 0 | Z41: =H41-(J41+L41+N41+P41+R41+T41+V41+X41) -> 0 | AB41: 0 | AD41: 0
C42: Unit name 2 | H42: 0 | J42: 0 | L42: 0 | N42: 0 | P42: 0 | R42: 0 | T42: 0 | V42: 0 | X42: 0 | Z42: =H42-(J42+L42+N42+P42+R42+T42+V42+X42) -> 0 | AB42: 0 | AD42: 0
C43: Unit name 3 | H43: 0 | J43: 0 | L43: 0 | N43: 0 | P43: 0 | R43: 0 | T43: 0 | V43: 0 | X43: 0 | Z43: =H43-(J43+L43+N43+P43+R43+T43+V43+X43) -> 0 | AB43: 0 | AD43: 0
B44: 1h | C44: Full inclusion foreign base company income (total) | H44: =SUM(H45:H47) -> 0 | J44: =SUM(J45:J47) -> 0 | L44: =SUM(L45:L47) -> 0 | N44: =SUM(N45:N47) -> 0 | P44: =SUM(P45:P47) -> 0 | R44: =SUM(R45:R47) -> 0 | T44: =SUM(T45:T47) -> 0 | V44: =SUM(V45:V47) -> 0 | X44: =SUM(X45:X47) -> 0 | Z44: =SUM(Z45:Z47) -> 0 | AB44: =SUM(AB45:AB47) -> 0 | AD44: =SUM(AD45:AD47) -> 0
C45: Unit name 1 | H45: 0 | J45: 0 | L45: 0 | N45: 0 | P45: 0 | R45: 0 | T45: 0 | V45: 0 | X45: 0 | Z45: =H45-(J45+L45+N45+P45+R45+T45+V45+X45) -> 0 | AB45: 0 | AD45: 0
C46: Unit name 2 | H46: 0 | J46: 0 | L46: 0 | N46: 0 | P46: 0 | R46: 0 | T46: 0 | V46: 0 | X46: 0 | Z46: =H46-(J46+L46+N46+P46+R46+T46+V46+X46) -> 0 | AB46: 0 | AD46: 0
C47: Unit name 3 | H47: 0 | J47: 0 | L47: 0 | N47: 0 | P47: 0 | R47: 0 | T47: 0 | V47: 0 | X47: 0 | Z47: =H47-(J47+L47+N47+P47+R47+T47+V47+X47) -> 0 | AB47: 0 | AD47: 0
B48: 1i | C48: Insurance inocme | H48: =SUM(H49:H51) -> 0 | J48: =SUM(J49:J51) -> 0 | L48: =SUM(L49:L51) -> 0 | N48: =SUM(N49:N51) -> 0 | P48: =SUM(P49:P51) -> 0 | R48: =SUM(R49:R51) -> 0 | T48: =SUM(T49:T51) -> 0 | V48: =SUM(V49:V51) -> 0 | X48: =SUM(X49:X51) -> 0 | Z48: =SUM(Z49:Z51) -> 0 | AB48: =SUM(AB49:AB51) -> 0 | AD48: =SUM(AD49:AD51) -> 0
C49: Unit name 1 | H49: 0 | J49: 0 | L49: 0 | N49: 0 | P49: 0 | R49: 0 | T49: 0 | V49: 0 | X49: 0 | Z49: =H49-(J49+L49+N49+P49+R49+T49+V49+X49) -> 0 | AB49: 0 | AD49: 0
C50: Unit name 2 | H50: 0 | J50: 0 | L50: 0 | N50: 0 | P50: 0 | R50: 0 | T50: 0 | V50: 0 | X50: 0 | Z50: =H50-(J50+L50+N50+P50+R50+T50+V50+X50) -> 0 | AB50: 0 | AD50: 0
C51: Unit name 3 | H51: 0 | J51: 0 | L51: 0 | N51: 0 | P51: 0 | R51: 0 | T51: 0 | V51: 0 | X51: 0 | Z51: =H51-(J51+L51+N51+P51+R51+T51+V51+X51) -> 0 | AB51: 0 | AD51: 0
B52: 1j | C52: International boycott income | H52: 0 | J52: 0 | L52: 0 | N52: 0 | P52: 0 | R52: 0 | T52: 0 | V52: 0 | X52: 0 | Z52: 0 | AB52: 0 | AD52: 0
B53: 1k | C53: Bribes, kickbacks, and other payments | H53: 0 | J53: 0 | L53: 0 | N53: 0 | P53: 0 | R53: 0 | T53: 0 | V53: 0 | X53: 0 | Z53: 0 | AB53: 0 | AD53: 0
B54: 1l | C54: Section 901(j) income | H54: 0 | J54: 0 | L54: 0 | N54: 0 | P54: 0 | R54: 0 | T54: 0 | V54: 0 | X54: 0 | Z54: 0 | AB54: 0 | AD54: 0
B55: 2 | C55: Recaptured Subpart F income | Z55: 0
B56: 3 | C56: Tested income group (total) | H56: =SUM(H57:H59) -> 0 | J56: =SUM(J57:J59) -> 0 | L56: =SUM(L57:L59) -> 0 | N56: =SUM(N57:N59) -> 0 | P56: =SUM(P57:P59) -> 0 | R56: =SUM(R57:R59) -> 0 | T56: =SUM(T57:T59) -> 0 | V56: =SUM(V57:V59) -> 0 | X56: =SUM(X57:X59) -> 0 | Z56: =SUM(Z57:Z59) -> 0 | AB56: =SUM(AB57:AB59) -> 0 | AD56: =SUM(AD57:AD59) -> 0
C57: Unit name 1 | H57: 0 | J57: 0 | L57: 0 | N57: 0 | P57: 0 | R57: 0 | T57: 0 | V57: 0 | X57: 0 | Z57: =H57-(J57+L57+N57+P57+R57+T57+V57+X57) -> 0 | AB57: 0 | AD57: 0
C58: Unit name 2 | H58: 0 | J58: 0 | L58: 0 | N58: 0 | P58: 0 | R58: 0 | T58: 0 | V58: 0 | X58: 0 | Z58: =H58-(J58+L58+N58+P58+R58+T58+V58+X58) -> 0 | AB58: 0 | AD58: 0
C59: Unit name 3 | H59: 0 | J59: 0 | L59: 0 | N59: 0 | P59: 0 | R59: 0 | T59: 0 | V59: 0 | X59: 0 | Z59: =H59-(J59+L59+N59+P59+R59+T59+V59+X59) -> 0 | AB59: 0 | AD59: 0
B60: 4 | C60: Residual income group (total) | H60: =SUM(H61:H63) -> 0 | J60: =SUM(J61:J63) -> 0 | L60: =SUM(L61:L63) -> 0 | N60: =SUM(N61:N63) -> 0 | P60: =SUM(P61:P63) -> 0 | R60: =SUM(R61:R63) -> 0 | T60: =SUM(T61:T63) -> 0 | V60: =SUM(V61:V63) -> 0 | X60: =SUM(X61:X63) -> 0 | Z60: =SUM(Z61:Z63) -> 0 | AB60: =SUM(AB61:AB63) -> 0 | AD60: =SUM(AD61:AD63) -> 0
C61: Unit name 1 | H61: 0 | J61: 0 | L61: 0 | N61: 0 | P61: 0 | R61: 0 | T61: 0 | V61: 0 | X61: 0 | Z61: =H61-(J61+L61+N61+P61+R61+T61+V61+X61) -> 0 | AB61: 0 | AD61: 0
C62: Unit name 2 | H62: 0 | J62: 0 | L62: 0 | N62: 0 | P62: 0 | R62: 0 | T62: 0 | V62: 0 | X62: 0 | Z62: =H62-(J62+L62+N62+P62+R62+T62+V62+X62) -> 0 | AB62: 0 | AD62: 0
C63: Unit name 3 | H63: 0 | J63: 0 | L63: 0 | N63: 0 | P63: 0 | R63: 0 | T63: 0 | V63: 0 | X63: 0 | Z63: =H63-(J63+L63+N63+P63+R63+T63+V63+X63) -> 0 | AB63: 0 | AD63: 0
B64: 5 | C64: Total | H64: =H16+H20+H24+H28+H32+H36+H40+H44+H48+H52+H53+H54+H56+H60 -> 0 | J64: =J16+J20+J24+J28+J32+J36+J40+J44+J48+J52+J53+J54+J56+J60 -> 0 | L64: =L16+L20+L24+L28+L32+L36+L40+L44+L48+L52+L53+L54+L56+L60 -> 0 | N64: =N16+N20+N24+N28+N32+N36+N40+N44+N48+N52+N53+N54+N56+N60 -> 0 | P64: =P16+P20+P24+P28+P32+P36+P40+P44+P48+P52+P53+P54+P56+P60 -> 0 | R64: =R16+R20+R24+R28+R32+R36+R40+R44+R48+R52+R53+R54+R56+R60 -> 0 | T64: =T16+T20+T24+T28+T32+T36+T40+T44+T48+T52+T53+T54+T56+T60 -> 0 | V64: =V16+V20+V24+V28+V32+V36+V40+V44+V48+V52+V53+V54+V56+V60 -> 0 | X64: =X16+X20+X24+X28+X32+X36+X40+X44+X48+X52+X53+X54+X56+X60 -> 0 | Z64: =Z16+Z20+Z24+Z28+Z32+Z36+Z40+Z44+Z48+Z52+Z53+Z54+Z56+Z60 -> 0 | AB64: =AB16+AB20+AB24+AB28+AB32+AB36+AB40+AB44+AB48+AB52+AB53+AB54+AB56+AB60 -> 0 | AD64: =AD16+AD20+AD24+AD28+AD32+AD36+AD40+AD44+AD48+AD52+AD53+AD54+AD56+AD60 -> 0

Sheet Schedule R
A1: ='Basic Information'!B4 -> 0
A2: DISTRIBUTIONS FROM A FOREIGN CORPORATION - SCHEDULE R
A3: ='Basic Information'!B1 -> 12/31/24
A4: (Amounts in US Dollars)
B8: (a) | E8: (b) | G8: (c) | I8: (d)
B9: (a) Description of distributions | D9: REF | E9: Date of distributions | F9: REF | G9: Amount of distribution in foreign corporation's functional currency | H9: REF | I9: Amount of E&P in foreign corporation's functional currency
A10: 1 | C10: 1
A11: 2 | C11: 2
A12: 3 | C12: 3
A13: 4 | C13: 4
A14: 5 | C14: 5
A15: 6 | C15: 6
A16: 7 | C16: 7
A17: 8 | C17: 8
A18: 9 | C18: 9
A19: 10 | C19: 10
A20: 11 | C20: 11
A21: 12 | C21: 12
... A29: 20 | C29: 20

Sheet Worksheet A
A1: ='Basic Information'!B4 -> 0
A2: WORKSHEET A
A3: ='Basic Information'!B1 -> 12/31/24
A4: (Amounts in Local Currency)
A7: Worksheet A - Summary of US Shareholder's Pro-Rata Share of Subpart F
C8: REF | E8: REF
A9: 1 | B9: Gross foreign personal holding company income
A10: a | B10: Dividends, interest, royalties, rents and annuities
A11: b | B11: Excess of gains over losses from property transactions
A12: c | B12: Excess of gains over losses from commodity transactions
A13: d | B13: Excess of foreign currency gains over foreign currency losses
A14: e | B14: Non-interest income equivalent to interest
A15: f | B15: Net income from a notional principal contract
A16: g | B16: Payments in lieu of dividends
A17: h | B17: Certain amounts received from personal service contracts
A18: i | B18: Certain amounts from sales of partnership interests
A19: 2 | B19: Gross foreign personal holding company income | F19: =SUM(D10:D18) -> 0
A20: 3 | B20: Gross foreign base company sales income
A21: 4 | B21: Gross foreign base company services income
A22: 5 | B22: Gross foreign base company income | F22: =SUM(F19:F21) -> 0
A23: 6 | B23: Gross insurance income
A24: 7 | B24: Gross foreign base company income and gross insurance income | F24: =F22+F23 -> 0
A25: 8 | B25: 5% of total gross income | F25: =0.05*('Income Statement'!L7+SUMIF('Income Statement'!L14:L20,">0",'Income Statement'!L14:L20)+SUMIF('Income Statement'!L22:L24,">0",'Income Statement'!L22:L24)) -> #DIV/0!
A26: 9 | B26: 70% of total gross income | F26: =0.7*('Income Statement'!L7+SUMIF('Income Statement'!L14:L20,">0",'Income Statement'!L14:L20)+SUMIF('Income Statement'!L22:L24,">0",'Income Statement'!L22:L24)) -> #DIV/0!
A27: 10 | B27: De minimis exceeded? | F27: =IF(F24=0,"No",IF(AND(F24<F25,F24<1000000),"No","Yes")) -> No
A28: 11 | B28: Full inclusion check | F28: =IF(F24>F26,('Income Statement'!L7+SUMIF('Income Statement'!L14:L20,">0",'Income Statement'!L14:L20)+SUMIF('Income Statement'!L22:L24,">0",'Income Statement'!L22:L24)),0) -> #DIV/0!
A29: 12 | B29: Total adjusted gross foreign base company income and insurance income | F29: =IF(F24>F28,F24,F28) -> #DIV/0!
A30: 13 | B30: Adjusted net foreign personal holding company income
A31: a | B31: Gross foreign personal holding company income | D31: =F19 -> 0
A32: b | B32: Expenses directly related to gross foreign personal holding company income
A33: c | B33: Tentative net FPHCI | D33: =D31-D32 -> 0
A34: d | B34: Related person interest expense
A35: e | B35: Other expenses allocated and apportioned to gross FPHCI under 954(b)(5)
A36: f | B36: Net foreign personal holding company income | D36: =D33-D34-D35 -> 0
A37: g | B37: Net foreign personal holding company income excluded under high-tax exception
A38: h | B38: Net FPHCI excl high-tax exception income | F38: =D36-D37 -> 0
A39: 14 | B39: Adjusted net foreign base company sales income
A40: a | B40: Gross foreign base company sales income | D40: =F20 -> 0
A41: b | B41: Expenses directly related to gross foreign base company sales income
A42: c | B42: Tentative net foreign base company sales income | D42: =D40-D41 -> 0
A43: d | B43: Net foreign base company sales income excluded under high-tax exception
A44: e | B44: Net foreign base company sales income | F44: =D42-D43 -> 0
A45: 15 | B45: Adjusted net foreign base company services income
A46: a | B46: Gross foreign base company services income | D46: =F21 -> 0
A47: b | B47: Expenses directly related to gross foreign base company services income
A48: c | B48: Tentative net foreign base company services income | D48: =D46-D47 -> 0
A49: d | B49: Net foreign base company services income excluded under high-tax exception
A50: e | B50: Net foreign base company services income | F50: =D48-D49 -> 0
A51: 16 | B51: Adjusted net full inclusion foreign base company income
A52: a | B52: Excess of full inclusion income over gross FBCI and insurance income | D52: =IF(F28-F24>0,F28-F24,0) -> #DIV/0!
A53: b | B53: Expenses allocated and apportioned under 954(b)(5)
A54: c | B54: Tentative net full inclusion foreign base company income | D54: =D52-D53 -> #DIV/0!
A55: d | B55: Net full inclusion foreign base company income excluded under high-tax exception
A56: e | B56: Net full inclusion foreign base company income | F56: =D54-D55 -> #DIV/0!
A57: 17 | B57: Adjusted net foreign base company income | F57: =F38+F44+F50+F56 -> #DIV/0!
A58: 18 | B58: Adjusted net insurance income
A59: a | B59: Gross insurance income excl related party insurance income
A60: b | B60: Expenses allocated to gross insurance income
A61: c | B61: Tentative net insurance income | D61: =D59-D60 -> 0
A62: d | B62: Net insurance income excluded under high-tax exception
A63: e | B63: Net insurance income | F63: =D61-D62 -> 0
A64: 19 | B64: Adjusted net related person insurance income
A65: a | B65: Related person insurance income | D65: =F23-D59 -> 0
A66: b | B66: Expenses allocated to related person insurance income
A67: c | B67: Tentative net related person insurance income | D67: =D65-D66 -> 0
A68: d | B68: Net related person insurance income excluded under high-tax exception
A69: e | B69: Net related person insurance income | F69: =D67-D68 -> 0
A70: 20 | B70: International boycott income
A71: 21 | B71: Illegal bribes, kickbacks and other payments
A72: 22 | B72: Income disallowed under 901(j)
A73: 23 | B73: Subpart F income before application of 952(b), (c), and 959(b) | F73: =F57+F63+F69+SUM(F70:F72) -> #DIV/0!
A74: 24 | B74: Portion of line 23 that is ECI
A75: 25 | B75: Exclusions under 959(b)
A76: 26 | B76: Total Subpart F income | F76: =F73-D74-D75 -> #DIV/0!
A77: 27 | B77: Current E&P limitation computation
A78: a | B78: Current E&P | D78: ='Sch - H'!I26 -> 0
A79: b | B79: Tested loss | D79: =ABS('Schedule I & I-1'!D44) -> 0
A80: c | B80: Total current E&P limitation | D80: =D78+D79 -> 0
A81: 28 | B81: Subpart F subject to E&P limitation | F81: =IF(F76>D80,D80,F76) -> #DIV/0!
A82: 29 | B82: Shareholder's pro-rata share of line 28 | D82: =F81*'Shareholding Details'!N16 -> #DIV/0!
A83: 30 | B83: Shareholder's pro-rata share of export trade income
A84: 31 | B84: Shareholder's pro-rata Subpart F, less export trade income | D84: =D82-D83 -> #DIV/0!
A85: 32 | B85: CFC annualised line 31 | D85: 1
A86: 33 | B86: Dividends paid to any person other than filer during year
A87: 34 | B87: Filer annualised line 31 | D87: 1
A88: 35 | B88: Lesser of line 33 and 34 | D88: =IF(D86>D87,D87,D86) -> 0
A89: 36a | B89: Shareholder's pro-rata share of Subpart F income - FC | F89: =D85-D88 -> 1
A90: b | B90: Shareholder's pro-rata share of Subpart F income - USD | F90: =F89*'Income Statement'!L5 -> 0

Sheet Worksheet B
A1: ='Basic Information'!B4 -> 0
A2: WORKSHEET B
A3: ='Basic Information'!B1 -> 12/31/24
A4: (Amounts in Local Currency)
A7: Worksheet B - US Shareholder's Pro-Rata Share of Earnings of a CFC Invested in US Property
C8: REF | E8: REF
A9: 1 | B9: Amount of US property held by CFC as of the close of:
A10: a | B10: First quarter of tax year
A11: b | B11: Second quarter of tax year
A12: c | B12: Third quarter of tax year
A13: d | B13: Fourth quarter of tax year
A14: 2 | B14: Number of quarter-ends the foreign corporation was a CFC during the tax year | F14: =IF(D10<>0,1)+IF(D11<>0,1)+IF(D12<>0,1)+IF(D13<>0,1) -> 0
A15: 3 | B15: Average amount of US property held as of the close of each quarter | F15: =IFERROR(SUM(D10:D13)/F14,0) -> 0
A16: 4 | B16: US Shareholder's pro-rata share of US property | F16: =F15*'Shareholding Details'!N16 -> 0
A17: 5 | B17: E&P described in 959(c)(1)(A) with respect to US shareholder after distributions
A18: 6 | B18: Section 956(a)(1) amount | F18: =F16-F17 -> 0
A19: 7 | B19: Applicable earnings | F19: =F17+F18 -> 0
A20: a | B20: Current year E&P | D20: ='Sch - H'!I26 -> 0
A21: b | B21: Accumulated E&P at EOY | D21: ='Schedule J'!AH41 -> 0
A22: 8 | B22: Greater of 7a or 7b | F22: =IF(D20>D21,D20,D21) -> 0
A23: 9 | B23: Distributions made by CFC during the year | F23: =Dividends!C12 -> 0
A24: 10 | B24: Line 8 less line 9 | F24: =F22-F23 -> 0
A25: 11 | B25: Earnings and Profits described in 959(c)(1)
A26: 12 | B26: Applicable earnings | F26: =F24-F25 -> 0
A27: 13 | B27: Section 956(a)(2) amount | F27: =F26*'Shareholding Details'!N16 -> 0
A28: 14 | B28: Section 956(a) amount | F28: =IF(F18<F27,F18,F27) -> 0
A29: 15 | B29: Amount of E&P described in 959(a)(2) with respect to US shareholder
A30: 16 | B30: Tentative section 956 amount | F30: =F28-F29 -> 0
A31: 17 | B31: 245A deduction that the shareholder would be allowed if the shareholder received a hypothetical distribution within meaning of Reg. Sec. 1.956-1(a)(2).
A32: 18 | B32: Section 956 Inclusion FC | F32: =F30-F31 -> 0
A33: 19 | B33: Section 956 Inclusion USD | F33: =F32*'Balance Sheet'!H6 -> 0

Sheet 8992 Information
A1: ='Basic Information'!B4 -> 0
A2: SUMMARY OF FOREIGN INCOME AND GILTI
A3: ='Basic Information'!B1 -> 12/31/24
A4: (Amounts in US Dollars)
A5: D-300
A7: Schedule A for US Shareholder Calculation of GILTI | D7: Shareholder ownership | F7: ='Shareholding Details'!N16 -> 0.6
C8: REF
A9: a | B9: Name of CFC | D9: ='Basic Information'!B11:F11 -> 0
A10: b | B10: EIN
A11: c | B11: Tested Income | D11: =IF('Schedule I & I-1'!H44>0,'Schedule I & I-1'!H44,0) -> #DIV/0!
A12: d | B12: Tested Loss | D12: =IF('Schedule I & I-1'!H44<0,'Schedule I & I-1'!H44,0) -> #DIV/0!
A13: e | B13: Pro-rata share of tested income | D13: =ROUND(D11*F7,0) -> #DIV/0!
A14: f | B14: Pro-rata share of tested loss | D14: =ROUND(D12*F7,0) -> #DIV/0!
A15: g | B15: Pro-rata share of 10% of QBAI | D15: =ROUND('Schedule I & I-1'!H46*F7,0) -> #DIV/0!
A16: h | B16: Pro-rata share of tested interest expense | D16: =ROUND('Schedule I & I-1'!H50*F7,0) -> #DIV/0!
A17: i | B17: Pro-rata share of tested interest income | D17: =ROUND('Schedule I & I-1'!H53*F7,0) -> #DIV/0!
B20: Update this section with numbers from Individual GILTI Calc
A21: k | B21: GILTI Allocation Ratio
A22: l | B22: GILTI Allocated to CFCS with Tested Income (8992 Part II Line 5) | E22: to Schedule J

Sheet Depr & Amort Summary
A1: ='Basic Information'!B4 -> 0
A2: DEPRECIATION & AMORTIZATION SUMMARY
A3: ='Basic Information'!B1 -> 12/31/24
A4: (Amounts in Local Currency)
A8: E&P depreciation is calculated the same as ACE
D10: REF
A11: Depreciation for book
A12: Depreciation for tax | E12: ='Depr & Amort Summary'!D46 -> 0
A13: E&P adjustment | E13: =E11-E12 -> 0
A16: Amortization for book
A17: Amortization for tax | D17: D-402/ | E17: ='Depr & Amort Summary'!D76 -> 0
A18: E&P adjustment | E18: =E17-E16 -> 0
A23: ='Basic Information'!B4 -> 0
A24: DEPRECIATION DETAIL
A25: ='Basic Information'!B1 -> 12/31/24
A26: (Amounts in Local Currency)
G29: Remaining Cost Basis
B30: Year Added | C30: Month Added | D30: Book Cost | E30: Asset Life | F30: Annual Depreciation | G30: =H30-1 -> 2014 | H30: =I30-1 -> 2015 | I30: =J30-1 -> 2016 | J30: =K30-1 -> 2017 | K30: =L30-1 -> 2018 | L30: =M30-1 -> 2019 | M30: =N30-1 -> 2020 | N30: =O30-1 -> 2021 | ... P30: =Q30-1 -> 2023 | Q30: ="20"&RIGHT(A25,2) -> 2024 | R30: =Q30+1 -> 2025 | S30: =R30+1 -> 2026 | T30: =S30+1 -> 2027 | U30: =T30+1 -> 2028 | V30: =U30+1 -> 2029 | W30: =V30+1 -> 2030 | X30: =W30+1 -> 2031 | Y30: =X30+1 -> 2032 | ... AA30: =Z30+1 -> 2034
A31: Asset | F31: =IFERROR(D31/E31,0) -> 0 | G31: =IF(IF(G$30-$B31>=0,IF(G$30=$B31,IF($C31=0,(($D31-(((G$30-$B31)+1)*$F31)/2)),(($D31-(((G$30-$B31)+1)*$F31)*($C31/12)))),IF($C31=0,($D31-((G$30-$B31)*$F31))-($F31/2),($D31-((G$30-$B31)*$F31))-($F31*($C31/12)))),0)>0,IF(G$30-$B31>=0,IF(G$30=$B31,IF($C31=0,(($D31-(((G$30-$B31)+1)*$F31)/2)),(($D31-(((G$30-$B31)+1)*$F31)*($C31/12)))),IF($C31=0,($D31-((G$30-$B31)*$F31))-($F31/2),($D31-((G$30-$B31)*$F31))-($F31*($C31/12)))),0),0) -> 0 | H31: =IF(IF(H$30-$B31>=0,IF(H$30=$B31,IF($C31=0,(($D31-(((H$30-$B31)+1)*$F31)/2)),(($D31-(((H$30-$B31)+1)*$F31)*($C31/12)))),IF($C31=0,($D31-((H$30-$B31)*$F31))-($F31/2),($D31-((H$30-$B31)*$F31))-($F31*($C31/12)))),0)>0,IF(H$30-$B31>=0,IF(H$30=$B31,IF($C31=0,(($D31-(((H$30-$B31)+1)*$F31)/2)),(($D31-(((H$30-$B31)+1)*$F31)*($C31/12)))),IF($C31=0,($D31-((H$30-$B31)*$F31))-($F31/2),($D31-((H$30-$B31)*$F31))-($F31*($C31/12)))),0),0) -> 0 | I31: =IF(IF(I$30-$B31>=0,IF(I$30=$B31,IF($C31=0,(($D31-(((I$30-$B31)+1)*$F31)/2)),(($D31-(((I$30-$B31)+1)*$F31)*($C31/12)))),IF($C31=0,($D31-((I$30-$B31)*$F31))-($F31/2),($D31-((I$30-$B31)*$F31))-($F31*($C31/12)))),0)>0,IF(I$30-$B31>=0,IF(I$30=$B31,IF($C31=0,(($D31-(((I$30-$B31)+1)*$F31)/2)),(($D31-(((I$30-$B31)+1)*$F31)*($C31/12)))),IF($C31=0,($D31-((I$30-$B31)*$F31))-($F31/2),($D31-((I$30-$B31)*$F31))-($F31*($C31/12)))),0),0) -> 0 | J31: =IF(IF(J$30-$B31>=0,IF(J$30=$B31,IF($C31=0,(($D31-(((J$30-$B31)+1)*$F31)/2)),(($D31-(((J$30-$B31)+1)*$F31)*($C31/12)))),IF($C31=0,($D31-((J$30-$B31)*$F31))-($F31/2),($D31-((J$30-$B31)*$F31))-($F31*($C31/12)))),0)>0,IF(J$30-$B31>=0,IF(J$30=$B31,IF($C31=0,(($D31-(((J$30-$B31)+1)*$F31)/2)),(($D31-(((J$30-$B31)+1)*$F31)*($C31/12)))),IF($C31=0,($D31-((J$30-$B31)*$F31))-($F31/2),($D31-((J$30-$B31)*$F31))-($F31*($C31/12)))),0),0) -> 0 | K31: =IF(IF(K$30-$B31>=0,IF(K$30=$B31,IF($C31=0,(($D31-(((K$30-$B31)+1)*$F31)/2)),(($D31-(((K$30-$B31)+1)*$F31)*($C31/12)))),IF($C31=0,($D31-((K$30-$B31)*$F31))-($F31/2),($D31-((K$30-$B31)*$F31))-($F31*($C31/12)))),0)>0,IF(K$30-$B31>=0,IF(K$30=$B31,IF($C31=0,(($D31-(((K$30-$B31)+1)*$F31)/2)),(($D31-(((K$30-$B31)+1)*$F31)*($C31/12)))),IF($C31=0,($D31-((K$30-$B31)*$F31))-($F31/2),($D31-((K$30-$B31)*$F31))-($F31*($C31/12)))),0),0) -> 0 | L31: =IF(IF(L$30-$B31>=0,IF(L$30=$B31,IF($C31=0,(($D31-(((L$30-$B31)+1)*$F31)/2)),(($D31-(((L$30-$B31)+1)*$F31)*($C31/12)))),IF($C31=0,($D31-((L$30-$B31)*$F31))-($F31/2),($D31-((L$30-$B31)*$F31))-($F31*($C31/12)))),0)>0,IF(L$30-$B31>=0,IF(L$30=$B31,IF($C31=0,(($D31-(((L$30-$B31)+1)*$F31)/2)),(($D31-(((L$30-$B31)+1)*$F31)*($C31/12)))),IF($C31=0,($D31-((L$30-$B31)*$F31))-($F31/2),($D31-((L$30-$B31)*$F31))-($F31*($C31/12)))),0),0) -> 0 | M31: =IF(IF(M$30-$B31>=0,IF(M$30=$B31,IF($C31=0,(($D31-(((M$30-$B31)+1)*$F31)/2)),(($D31-(((M$30-$B31)+1)*$F31)*($C31/12)))),IF($C31=0,($D31-((M$30-$B31)*$F31))-($F31/2),($D31-((M$30-$B31)*$F31))-($F31*($C31/12)))),0)>0,IF(M$30-$B31>=0,IF(M$30=$B31,IF($C31=0,(($D31-(((M$30-$B31)+1)*$F31)/2)),(($D31-(((M$30-$B31)+1)*$F31)*($C31/12)))),IF($C31=0,($D31-((M$30-$B31)*$F31))-($F31/2),($D31-((M$30-$B31)*$F31))-($F31*($C31/12)))),0),0) -> 0 | N31: =IF(IF(N$30-$B31>=0,IF(N$30=$B31,IF($C31=0,(($D31-(((N$30-$B31)+1)*$F31)/2)),(($D31-(((N$30-$B31)+1)*$F31)*($C31/12)))),IF($C31=0,($D31-((N$30-$B31)*$F31))-($F31/2),($D31-((N$30-$B31)*$F31))-($F31*($C31/12)))),0)>0,IF(N$30-$B31>=0,IF(N$30=$B31,IF($C31=0,(($D31-(((N$30-$B31)+1)*$F31)/2)),(($D31-(((N$30-$B31)+1)*$F31)*($C31/12)))),IF($C31=0,($D31-((N$30-$B31)*$F31))-($F31/2),($D31-((N$30-$B31)*$F31))-($F31*($C31/12)))),0),0) -> 0 | ... AA31: =IF(IF(AA$30-$B31>=0,IF(AA$30=$B31,IF($C31=0,(($D31-(((AA$30-$B31)+1)*$F31)/2)),(($D31-(((AA$30-$B31)+1)*$F31)*($C31/12)))),IF($C31=0,($D31-((AA$30-$B31)*$F31))-($F31/2),($D31-((AA$30-$B31)*$F31))-($F31*($C31/12)))),0)>0,IF(AA$30-$B31>=0,IF(AA$30=$B31,IF($C31=0,(($D31-(((AA$30-$B31)+1)*$F31)/2)),(($D31-(((AA$30-$B31)+1)*$F31)*($C31/12)))),IF($C31=0,($D31-((AA$30-$B31)*$F31))-($F31/2),($D31-((AA$30-$B31)*$F31))-($F31*($C31/12)))),0),0) -> 0
A32: Asset | F32: =IFERROR(D32/E32,0) -> 0 | G32: =IF(IF(G$30-$B32>=0,IF(G$30=$B32,IF($C32=0,(($D32-(((G$30-$B32)+1)*$F32)/2)),(($D32-(((G$30-$B32)+1)*$F32)*($C32/12)))),IF($C32=0,($D32-((G$30-$B32)*$F32))-($F32/2),($D32-((G$30-$B32)*$F32))-($F32*($C32/12)))),0)>0,IF(G$30-$B32>=0,IF(G$30=$B32,IF($C32=0,(($D32-(((G$30-$B32)+1)*$F32)/2)),(($D32-(((G$30-$B32)+1)*$F32)*($C32/12)))),IF($C32=0,($D32-((G$30-$B32)*$F32))-($F32/2),($D32-((G$30-$B32)*$F32))-($F32*($C32/12)))),0),0) -> 0 | H32: =IF(IF(H$30-$B32>=0,IF(H$30=$B32,IF($C32=0,(($D32-(((H$30-$B32)+1)*$F32)/2)),(($D32-(((H$30-$B32)+1)*$F32)*($C32/12)))),IF($C32=0,($D32-((H$30-$B32)*$F32))-($F32/2),($D32-((H$30-$B32)*$F32))-($F32*($C32/12)))),0)>0,IF(H$30-$B32>=0,IF(H$30=$B32,IF($C32=0,(($D32-(((H$30-$B32)+1)*$F32)/2)),(($D32-(((H$30-$B32)+1)*$F32)*($C32/12)))),IF($C32=0,($D32-((H$30-$B32)*$F32))-($F32/2),($D32-((H$30-$B32)*$F32))-($F32*($C32/12)))),0),0) -> 0 | I32: =IF(IF(I$30-$B32>=0,IF(I$30=$B32,IF($C32=0,(($D32-(((I$30-$B32)+1)*$F32)/2)),(($D32-(((I$30-$B32)+1)*$F32)*($C32/12)))),IF($C32=0,($D32-((I$30-$B32)*$F32))-($F32/2),($D32-((I$30-$B32)*$F32))-($F32*($C32/12)))),0)>0,IF(I$30-$B32>=0,IF(I$30=$B32,IF($C32=0,(($D32-(((I$30-$B32)+1)*$F32)/2)),(($D32-(((I$30-$B32)+1)*$F32)*($C32/12)))),IF($C32=0,($D32-((I$30-$B32)*$F32))-($F32/2),($D32-((I$30-$B32)*$F32))-($F32*($C32/12)))),0),0) -> 0 | J32: =IF(IF(J$30-$B32>=0,IF(J$30=$B32,IF($C32=0,(($D32-(((J$30-$B32)+1)*$F32)/2)),(($D32-(((J$30-$B32)+1)*$F32)*($C32/12)))),IF($C32=0,($D32-((J$30-$B32)*$F32))-($F32/2),($D32-((J$30-$B32)*$F32))-($F32*($C32/12)))),0)>0,IF(J$30-$B32>=0,IF(J$30=$B32,IF($C32=0,(($D32-(((J$30-$B32)+1)*$F32)/2)),(($D32-(((J$30-$B32)+1)*$F32)*($C32/12)))),IF($C32=0,($D32-((J$30-$B32)*$F32))-($F32/2),($D32-((J$30-$B32)*$F32))-($F32*($C32/12)))),0),0) -> 0 | K32: =IF(IF(K$30-$B32>=0,IF(K$30=$B32,IF($C32=0,(($D32-(((K$30-$B32)+1)*$F32)/2)),(($D32-(((K$30-$B32)+1)*$F32)*($C32/12)))),IF($C32=0,($D32-((K$30-$B32)*$F32))-($F32/2),($D32-((K$30-$B32)*$F32))-($F32*($C32/12)))),0)>0,IF(K$30-$B32>=0,IF(K$30=$B32,IF($C32=0,(($D32-(((K$30-$B32)+1)*$F32)/2)),(($D32-(((K$30-$B32)+1)*$F32)*($C32/12)))),IF($C32=0,($D32-((K$30-$B32)*$F32))-($F32/2),($D32-((K$30-$B32)*$F32))-($F32*($C32/12)))),0),0) -> 0 | L32: =IF(IF(L$30-$B32>=0,IF(L$30=$B32,IF($C32=0,(($D32-(((L$30-$B32)+1)*$F32)/2)),(($D32-(((L$30-$B32)+1)*$F32)*($C32/12)))),IF($C32=0,($D32-((L$30-$B32)*$F32))-($F32/2),($D32-((L$30-$B32)*$F32))-($F32*($C32/12)))),0)>0,IF(L$30-$B32>=0,IF(L$30=$B32,IF($C32=0,(($D32-(((L$30-$B32)+1)*$F32)/2)),(($D32-(((L$30-$B32)+1)*$F32)*($C32/12)))),IF($C32=0,($D32-((L$30-$B32)*$F32))-($F32/2),($D32-((L$30-$B32)*$F32))-($F32*($C32/12)))),0),0) -> 0 | M32: =IF(IF(M$30-$B32>=0,IF(M$30=$B32,IF($C32=0,(($D32-(((M$30-$B32)+1)*$F32)/2)),(($D32-(((M$30-$B32)+1)*$F32)*($C32/12)))),IF($C32=0,($D32-((M$30-$B32)*$F32))-($F32/2),($D32-((M$30-$B32)*$F32))-($F32*($C32/12)))),0)>0,IF(M$30-$B32>=0,IF(M$30=$B32,IF($C32=0,(($D32-(((M$30-$B32)+1)*$F32)/2)),(($D32-(((M$30-$B32)+1)*$F32)*($C32/12)))),IF($C32=0,($D32-((M$30-$B32)*$F32))-($F32/2),($D32-((M$30-$B32)*$F32))-($F32*($C32/12)))),0),0) -> 0 | N32: =IF(IF(N$30-$B32>=0,IF(N$30=$B32,IF($C32=0,(($D32-(((N$30-$B32)+1)*$F32)/2)),(($D32-(((N$30-$B32)+1)*$F32)*($C32/12)))),IF($C32=0,($D32-((N$30-$B32)*$F32))-($F32/2),($D32-((N$30-$B32)*$F32))-($F32*($C32/12)))),0)>0,IF(N$30-$B32>=0,IF(N$30=$B32,IF($C32=0,(($D32-(((N$30-$B32)+1)*$F32)/2)),(($D32-(((N$30-$B32)+1)*$F32)*($C32/12)))),IF($C32=0,($D32-((N$30-$B32)*$F32))-($F32/2),($D32-((N$30-$B32)*$F32))-($F32*($C32/12)))),0),0) -> 0 | ... AA32: =IF(IF(AA$30-$B32>=0,IF(AA$30=$B32,IF($C32=0,(($D32-(((AA$30-$B32)+1)*$F32)/2)),(($D32-(((AA$30-$B32)+1)*$F32)*($C32/12)))),IF($C32=0,($D32-((AA$30-$B32)*$F32))-($F32/2),($D32-((AA$30-$B32)*$F32))-($F32*($C32/12)))),0)>0,IF(AA$30-$B32>=0,IF(AA$30=$B32,IF($C32=0,(($D32-(((AA$30-$B32)+1)*$F32)/2)),(($D32-(((AA$30-$B32)+1)*$F32)*($C32/12)))),IF($C32=0,($D32-((AA$30-$B32)*$F32))-($F32/2),($D32-((AA$30-$B32)*$F32))-($F32*($C32/12)))),0),0) -> 0
A33: Asset | F33: =IFERROR(D33/E33,0) -> 0 | G33: =IF(IF(G$30-$B33>=0,IF(G$30=$B33,IF($C33=0,(($D33-(((G$30-$B33)+1)*$F33)/2)),(($D33-(((G$30-$B33)+1)*$F33)*($C33/12)))),IF($C33=0,($D33-((G$30-$B33)*$F33))-($F33/2),($D33-((G$30-$B33)*$F33))-($F33*($C33/12)))),0)>0,IF(G$30-$B33>=0,IF(G$30=$B33,IF($C33=0,(($D33-(((G$30-$B33)+1)*$F33)/2)),(($D33-(((G$30-$B33)+1)*$F33)*($C33/12)))),IF($C33=0,($D33-((G$30-$B33)*$F33))-($F33/2),($D33-((G$30-$B33)*$F33))-($F33*($C33/12)))),0),0) -> 0 | H33: =IF(IF(H$30-$B33>=0,IF(H$30=$B33,IF($C33=0,(($D33-(((H$30-$B33)+1)*$F33)/2)),(($D33-(((H$30-$B33)+1)*$F33)*($C33/12)))),IF($C33=0,($D33-((H$30-$B33)*$F33))-($F33/2),($D33-((H$30-$B33)*$F33))-($F33*($C33/12)))),0)>0,IF(H$30-$B33>=0,IF(H$30=$B33,IF($C33=0,(($D33-(((H$30-$B33)+1)*$F33)/2)),(($D33-(((H$30-$B33)+1)*$F33)*($C33/12)))),IF($C33=0,($D33-((H$30-$B33)*$F33))-($F33/2),($D33-((H$30-$B33)*$F33))-($F33*($C33/12)))),0),0) -> 0 | I33: =IF(IF(I$30-$B33>=0,IF(I$30=$B33,IF($C33=0,(($D33-(((I$30-$B33)+1)*$F33)/2)),(($D33-(((I$30-$B33)+1)*$F33)*($C33/12)))),IF($C33=0,($D33-((I$30-$B33)*$F33))-($F33/2),($D33-((I$30-$B33)*$F33))-($F33*($C33/12)))),0)>0,IF(I$30-$B33>=0,IF(I$30=$B33,IF($C33=0,(($D33-(((I$30-$B33)+1)*$F33)/2)),(($D33-(((I$30-$B33)+1)*$F33)*($C33/12)))),IF($C33=0,($D33-((I$30-$B33)*$F33))-($F33/2),($D33-((I$30-$B33)*$F33))-($F33*($C33/12)))),0),0) -> 0 | J33: =IF(IF(J$30-$B33>=0,IF(J$30=$B33,IF($C33=0,(($D33-(((J$30-$B33)+1)*$F33)/2)),(($D33-(((J$30-$B33)+1)*$F33)*($C33/12)))),IF($C33=0,($D33-((J$30-$B33)*$F33))-($F33/2),($D33-((J$30-$B33)*$F33))-($F33*($C33/12)))),0)>0,IF(J$30-$B33>=0,IF(J$30=$B33,IF($C33=0,(($D33-(((J$30-$B33)+1)*$F33)/2)),(($D33-(((J$30-$B33)+1)*$F33)*($C33/12)))),IF($C33=0,($D33-((J$30-$B33)*$F33))-($F33/2),($D33-((J$30-$B33)*$F33))-($F33*($C33/12)))),0),0) -> 0 | K33: =IF(IF(K$30-$B33>=0,IF(K$30=$B33,IF($C33=0,(($D33-(((K$30-$B33)+1)*$F33)/2)),(($D33-(((K$30-$B33)+1)*$F33)*($C33/12)))),IF($C33=0,($D33-((K$30-$B33)*$F33))-($F33/2),($D33-((K$30-$B33)*$F33))-($F33*($C33/12)))),0)>0,IF(K$30-$B33>=0,IF(K$30=$B33,IF($C33=0,(($D33-(((K$30-$B33)+1)*$F33)/2)),(($D33-(((K$30-$B33)+1)*$F33)*($C33/12)))),IF($C33=0,($D33-((K$30-$B33)*$F33))-($F33/2),($D33-((K$30-$B33)*$F33))-($F33*($C33/12)))),0),0) -> 0 | L33: =IF(IF(L$30-$B33>=0,IF(L$30=$B33,IF($C33=0,(($D33-(((L$30-$B33)+1)*$F33)/2)),(($D33-(((L$30-$B33)+1)*$F33)*($C33/12)))),IF($C33=0,($D33-((L$30-$B33)*$F33))-($F33/2),($D33-((L$30-$B33)*$F33))-($F33*($C33/12)))),0)>0,IF(L$30-$B33>=0,IF(L$30=$B33,IF($C33=0,(($D33-(((L$30-$B33)+1)*$F33)/2)),(($D33-(((L$30-$B33)+1)*$F33)*($C33/12)))),IF($C33=0,($D33-((L$30-$B33)*$F33))-($F33/2),($D33-((L$30-$B33)*$F33))-($F33*($C33/12)))),0),0) -> 0 | M33: =IF(IF(M$30-$B33>=0,IF(M$30=$B33,IF($C33=0,(($D33-(((M$30-$B33)+1)*$F33)/2)),(($D33-(((M$30-$B33)+1)*$F33)*($C33/12)))),IF($C33=0,($D33-((M$30-$B33)*$F33))-($F33/2),($D33-((M$30-$B33)*$F33))-($F33*($C33/12)))),0)>0,IF(M$30-$B33>=0,IF(M$30=$B33,IF($C33=0,(($D33-(((M$30-$B33)+1)*$F33)/2)),(($D33-(((M$30-$B33)+1)*$F33)*($C33/12)))),IF($C33=0,($D33-((M$30-$B33)*$F33))-($F33/2),($D33-((M$30-$B33)*$F33))-($F33*($C33/12)))),0),0) -> 0 | N33: =IF(IF(N$30-$B33>=0,IF(N$30=$B33,IF($C33=0,(($D33-(((N$30-$B33)+1)*$F33)/2)),(($D33-(((N$30-$B33)+1)*$F33)*($C33/12)))),IF($C33=0,($D33-((N$30-$B33)*$F33))-($F33/2),($D33-((N$30-$B33)*$F33))-($F33*($C33/12)))),0)>0,IF(N$30-$B33>=0,IF(N$30=$B33,IF($C33=0,(($D33-(((N$30-$B33)+1)*$F33)/2)),(($D33-(((N$30-$B33)+1)*$F33)*($C33/12)))),IF($C33=0,($D33-((N$30-$B33)*$F33))-($F33/2),($D33-((N$30-$B33)*$F33))-($F33*($C33/12)))),0),0) -> 0 | ... AA33: =IF(IF(AA$30-$B33>=0,IF(AA$30=$B33,IF($C33=0,(($D33-(((AA$30-$B33)+1)*$F33)/2)),(($D33-(((AA$30-$B33)+1)*$F33)*($C33/12)))),IF($C33=0,($D33-((AA$30-$B33)*$F33))-($F33/2),($D33-((AA$30-$B33)*$F33))-($F33*($C33/12)))),0)>0,IF(AA$30-$B33>=0,IF(AA$30=$B33,IF($C33=0,(($D33-(((AA$30-$B33)+1)*$F33)/2)),(($D33-(((AA$30-$B33)+1)*$F33)*($C33/12)))),IF($C33=0,($D33-((AA$30-$B33)*$F33))-($F33/2),($D33-((AA$30-$B33)*$F33))-($F33*($C33/12)))),0),0) -> 0
A34: Asset | F34: =IFERROR(D34/E34,0) -> 0 | G34: =IF(IF(G$30-$B34>=0,IF(G$30=$B34,IF($C34=0,(($D34-(((G$30-$B34)+1)*$F34)/2)),(($D34-(((G$30-$B34)+1)*$F34)*($C34/12)))),IF($C34=0,($D34-((G$30-$B34)*$F34))-($F34/2),($D34-((G$30-$B34)*$F34))-($F34*($C34/12)))),0)>0,IF(G$30-$B34>=0,IF(G$30=$B34,IF($C34=0,(($D34-(((G$30-$B34)+1)*$F34)/2)),(($D34-(((G$30-$B34)+1)*$F34)*($C34/12)))),IF($C34=0,($D34-((G$30-$B34)*$F34))-($F34/2),($D34-((G$30-$B34)*$F34))-($F34*($C34/12)))),0),0) -> 0 | H34: =IF(IF(H$30-$B34>=0,IF(H$30=$B34,IF($C34=0,(($D34-(((H$30-$B34)+1)*$F34)/2)),(($D34-(((H$30-$B34)+1)*$F34)*($C34/12)))),IF($C34=0,($D34-((H$30-$B34)*$F34))-($F34/2),($D34-((H$30-$B34)*$F34))-($F34*($C34/12)))),0)>0,IF(H$30-$B34>=0,IF(H$30=$B34,IF($C34=0,(($D34-(((H$30-$B34)+1)*$F34)/2)),(($D34-(((H$30-$B34)+1)*$F34)*($C34/12)))),IF($C34=0,($D34-((H$30-$B34)*$F34))-($F34/2),($D34-((H$30-$B34)*$F34))-($F34*($C34/12)))),0),0) -> 0 | I34: =IF(IF(I$30-$B34>=0,IF(I$30=$B34,IF($C34=0,(($D34-(((I$30-$B34)+1)*$F34)/2)),(($D34-(((I$30-$B34)+1)*$F34)*($C34/12)))),IF($C34=0,($D34-((I$30-$B34)*$F34))-($F34/2),($D34-((I$30-$B34)*$F34))-($F34*($C34/12)))),0)>0,IF(I$30-$B34>=0,IF(I$30=$B34,IF($C34=0,(($D34-(((I$30-$B34)+1)*$F34)/2)),(($D34-(((I$30-$B34)+1)*$F34)*($C34/12)))),IF($C34=0,($D34-((I$30-$B34)*$F34))-($F34/2),($D34-((I$30-$B34)*$F34))-($F34*($C34/12)))),0),0) -> 0 | J34: =IF(IF(J$30-$B34>=0,IF(J$30=$B34,IF($C34=0,(($D34-(((J$30-$B34)+1)*$F34)/2)),(($D34-(((J$30-$B34)+1)*$F34)*($C34/12)))),IF($C34=0,($D34-((J$30-$B34)*$F34))-($F34/2),($D34-((J$30-$B34)*$F34))-($F34*($C34/12)))),0)>0,IF(J$30-$B34>=0,IF(J$30=$B34,IF($C34=0,(($D34-(((J$30-$B34)+1)*$F34)/2)),(($D34-(((J$30-$B34)+1)*$F34)*($C34/12)))),IF($C34=0,($D34-((J$30-$B34)*$F34))-($F34/2),($D34-((J$30-$B34)*$F34))-($F34*($C34/12)))),0),0) -> 0 | K34: =IF(IF(K$30-$B34>=0,IF(K$30=$B34,IF($C34=0,(($D34-(((K$30-$B34)+1)*$F34)/2)),(($D34-(((K$30-$B34)+1)*$F34)*($C34/12)))),IF($C34=0,($D34-((K$30-$B34)*$F34))-($F34/2),($D34-((K$30-$B34)*$F34))-($F34*($C34/12)))),0)>0,IF(K$30-$B34>=0,IF(K$30=$B34,IF($C34=0,(($D34-(((K$30-$B34)+1)*$F34)/2)),(($D34-(((K$30-$B34)+1)*$F34)*($C34/12)))),IF($C34=0,($D34-((K$30-$B34)*$F34))-($F34/2),($D34-((K$30-$B34)*$F34))-($F34*($C34/12)))),0),0) -> 0 | L34: =IF(IF(L$30-$B34>=0,IF(L$30=$B34,IF($C34=0,(($D34-(((L$30-$B34)+1)*$F34)/2)),(($D34-(((L$30-$B34)+1)*$F34)*($C34/12)))),IF($C34=0,($D34-((L$30-$B34)*$F34))-($F34/2),($D34-((L$30-$B34)*$F34))-($F34*($C34/12)))),0)>0,IF(L$30-$B34>=0,IF(L$30=$B34,IF($C34=0,(($D34-(((L$30-$B34)+1)*$F34)/2)),(($D34-(((L$30-$B34)+1)*$F34)*($C34/12)))),IF($C34=0,($D34-((L$30-$B34)*$F34))-($F34/2),($D34-((L$30-$B34)*$F34))-($F34*($C34/12)))),0),0) -> 0 | M34: =IF(IF(M$30-$B34>=0,IF(M$30=$B34,IF($C34=0,(($D34-(((M$30-$B34)+1)*$F34)/2)),(($D34-(((M$30-$B34)+1)*$F34)*($C34/12)))),IF($C34=0,($D34-((M$30-$B34)*$F34))-($F34/2),($D34-((M$30-$B34)*$F34))-($F34*($C34/12)))),0)>0,IF(M$30-$B34>=0,IF(M$30=$B34,IF($C34=0,(($D34-(((M$30-$B34)+1)*$F34)/2)),(($D34-(((M$30-$B34)+1)*$F34)*($C34/12)))),IF($C34=0,($D34-((M$30-$B34)*$F34))-($F34/2),($D34-((M$30-$B34)*$F34))-($F34*($C34/12)))),0),0) -> 0 | N34: =IF(IF(N$30-$B34>=0,IF(N$30=$B34,IF($C34=0,(($D34-(((N$30-$B34)+1)*$F34)/2)),(($D34-(((N$30-$B34)+1)*$F34)*($C34/12)))),IF($C34=0,($D34-((N$30-$B34)*$F34))-($F34/2),($D34-((N$30-$B34)*$F34))-($F34*($C34/12)))),0)>0,IF(N$30-$B34>=0,IF(N$30=$B34,IF($C34=0,(($D34-(((N$30-$B34)+1)*$F34)/2)),(($D34-(((N$30-$B34)+1)*$F34)*($C34/12)))),IF($C34=0,($D34-((N$30-$B34)*$F34))-($F34/2),($D34-((N$30-$B34)*$F34))-($F34*($C34/12)))),0),0) -> 0 | ... AA34: =IF(IF(AA$30-$B34>=0,IF(AA$30=$B34,IF($C34=0,(($D34-(((AA$30-$B34)+1)*$F34)/2)),(($D34-(((AA$30-$B34)+1)*$F34)*($C34/12)))),IF($C34=0,($D34-((AA$30-$B34)*$F34))-($F34/2),($D34-((AA$30-$B34)*$F34))-($F34*($C34/12)))),0)>0,IF(AA$30-$B34>=0,IF(AA$30=$B34,IF($C34=0,(($D34-(((AA$30-$B34)+1)*$F34)/2)),(($D34-(((AA$30-$B34)+1)*$F34)*($C34/12)))),IF($C34=0,($D34-((AA$30-$B34)*$F34))-($F34/2),($D34-((AA$30-$B34)*$F34))-($F34*($C34/12)))),0),0) -> 0
A35: Asset | F35: =IFERROR(D35/E35,0) -> 0 | G35: =IF(IF(G$30-$B35>=0,IF(G$30=$B35,IF($C35=0,(($D35-(((G$30-$B35)+1)*$F35)/2)),(($D35-(((G$30-$B35)+1)*$F35)*($C35/12)))),IF($C35=0,($D35-((G$30-$B35)*$F35))-($F35/2),($D35-((G$30-$B35)*$F35))-($F35*($C35/12)))),0)>0,IF(G$30-$B35>=0,IF(G$30=$B35,IF($C35=0,(($D35-(((G$30-$B35)+1)*$F35)/2)),(($D35-(((G$30-$B35)+1)*$F35)*($C35/12)))),IF($C35=0,($D35-((G$30-$B35)*$F35))-($F35/2),($D35-((G$30-$B35)*$F35))-($F35*($C35/12)))),0),0) -> 0 | H35: =IF(IF(H$30-$B35>=0,IF(H$30=$B35,IF($C35=0,(($D35-(((H$30-$B35)+1)*$F35)/2)),(($D35-(((H$30-$B35)+1)*$F35)*($C35/12)))),IF($C35=0,($D35-((H$30-$B35)*$F35))-($F35/2),($D35-((H$30-$B35)*$F35))-($F35*($C35/12)))),0)>0,IF(H$30-$B35>=0,IF(H$30=$B35,IF($C35=0,(($D35-(((H$30-$B35)+1)*$F35)/2)),(($D35-(((H$30-$B35)+1)*$F35)*($C35/12)))),IF($C35=0,($D35-((H$30-$B35)*$F35))-($F35/2),($D35-((H$30-$B35)*$F35))-($F35*($C35/12)))),0),0) -> 0 | I35: =IF(IF(I$30-$B35>=0,IF(I$30=$B35,IF($C35=0,(($D35-(((I$30-$B35)+1)*$F35)/2)),(($D35-(((I$30-$B35)+1)*$F35)*($C35/12)))),IF($C35=0,($D35-((I$30-$B35)*$F35))-($F35/2),($D35-((I$30-$B35)*$F35))-($F35*($C35/12)))),0)>0,IF(I$30-$B35>=0,IF(I$30=$B35,IF($C35=0,(($D35-(((I$30-$B35)+1)*$F35)/2)),(($D35-(((I$30-$B35)+1)*$F35)*($C35/12)))),IF($C35=0,($D35-((I$30-$B35)*$F35))-($F35/2),($D35-((I$30-$B35)*$F35))-($F35*($C35/12)))),0),0) -> 0 | J35: =IF(IF(J$30-$B35>=0,IF(J$30=$B35,IF($C35=0,(($D35-(((J$30-$B35)+1)*$F35)/2)),(($D35-(((J$30-$B35)+1)*$F35)*($C35/12)))),IF($C35=0,($D35-((J$30-$B35)*$F35))-($F35/2),($D35-((J$30-$B35)*$F35))-($F35*($C35/12)))),0)>0,IF(J$30-$B35>=0,IF(J$30=$B35,IF($C35=0,(($D35-(((J$30-$B35)+1)*$F35)/2)),(($D35-(((J$30-$B35)+1)*$F35)*($C35/12)))),IF($C35=0,($D35-((J$30-$B35)*$F35))-($F35/2),($D35-((J$30-$B35)*$F35))-($F35*($C35/12)))),0),0) -> 0 | K35: =IF(IF(K$30-$B35>=0,IF(K$30=$B35,IF($C35=0,(($D35-(((K$30-$B35)+1)*$F35)/2)),(($D35-(((K$30-$B35)+1)*$F35)*($C35/12)))),IF($C35=0,($D35-((K$30-$B35)*$F35))-($F35/2),($D35-((K$30-$B35)*$F35))-($F35*($C35/12)))),0)>0,IF(K$30-$B35>=0,IF(K$30=$B35,IF($C35=0,(($D35-(((K$30-$B35)+1)*$F35)/2)),(($D35-(((K$30-$B35)+1)*$F35)*($C35/12)))),IF($C35=0,($D35-((K$30-$B35)*$F35))-($F35/2),($D35-((K$30-$B35)*$F35))-($F35*($C35/12)))),0),0) -> 0 | L35: =IF(IF(L$30-$B35>=0,IF(L$30=$B35,IF($C35=0,(($D35-(((L$30-$B35)+1)*$F35)/2)),(($D35-(((L$30-$B35)+1)*$F35)*($C35/12)))),IF($C35=0,($D35-((L$30-$B35)*$F35))-($F35/2),($D35-((L$30-$B35)*$F35))-($F35*($C35/12)))),0)>0,IF(L$30-$B35>=0,IF(L$30=$B35,IF($C35=0,(($D35-(((L$30-$B35)+1)*$F35)/2)),(($D35-(((L$30-$B35)+1)*$F35)*($C35/12)))),IF($C35=0,($D35-((L$30-$B35)*$F35))-($F35/2),($D35-((L$30-$B35)*$F35))-($F35*($C35/12)))),0),0) -> 0 | M35: =IF(IF(M$30-$B35>=0,IF(M$30=$B35,IF($C35=0,(($D35-(((M$30-$B35)+1)*$F35)/2)),(($D35-(((M$30-$B35)+1)*$F35)*($C35/12)))),IF($C35=0,($D35-((M$30-$B35)*$F35))-($F35/2),($D35-((M$30-$B35)*$F35))-($F35*($C35/12)))),0)>0,IF(M$30-$B35>=0,IF(M$30=$B35,IF($C35=0,(($D35-(((M$30-$B35)+1)*$F35)/2)),(($D35-(((M$30-$B35)+1)*$F35)*($C35/12)))),IF($C35=0,($D35-((M$30-$B35)*$F35))-($F35/2),($D35-((M$30-$B35)*$F35))-($F35*($C35/12)))),0),0) -> 0 | N35: =IF(IF(N$30-$B35>=0,IF(N$30=$B35,IF($C35=0,(($D35-(((N$30-$B35)+1)*$F35)/2)),(($D35-(((N$30-$B35)+1)*$F35)*($C35/12)))),IF($C35=0,($D35-((N$30-$B35)*$F35))-($F35/2),($D35-((N$30-$B35)*$F35))-($F35*($C35/12)))),0)>0,IF(N$30-$B35>=0,IF(N$30=$B35,IF($C35=0,(($D35-(((N$30-$B35)+1)*$F35)/2)),(($D35-(((N$30-$B35)+1)*$F35)*($C35/12)))),IF($C35=0,($D35-((N$30-$B35)*$F35))-($F35/2),($D35-((N$30-$B35)*$F35))-($F35*($C35/12)))),0),0) -> 0 | ... AA35: =IF(IF(AA$30-$B35>=0,IF(AA$30=$B35,IF($C35=0,(($D35-(((AA$30-$B35)+1)*$F35)/2)),(($D35-(((AA$30-$B35)+1)*$F35)*($C35/12)))),IF($C35=0,($D35-((AA$30-$B35)*$F35))-($F35/2),($D35-((AA$30-$B35)*$F35))-($F35*($C35/12)))),0)>0,IF(AA$30-$B35>=0,IF(AA$30=$B35,IF($C35=0,(($D35-(((AA$30-$B35)+1)*$F35)/2)),(($D35-(((AA$30-$B35)+1)*$F35)*($C35/12)))),IF($C35=0,($D35-((AA$30-$B35)*$F35))-($F35/2),($D35-((AA$30-$B35)*$F35))-($F35*($C35/12)))),0),0) -> 0
A36: Asset | F36: =IFERROR(D36/E36,0) -> 0 | G36: =IF(IF(G$30-$B36>=0,IF(G$30=$B36,IF($C36=0,(($D36-(((G$30-$B36)+1)*$F36)/2)),(($D36-(((G$30-$B36)+1)*$F36)*($C36/12)))),IF($C36=0,($D36-((G$30-$B36)*$F36))-($F36/2),($D36-((G$30-$B36)*$F36))-($F36*($C36/12)))),0)>0,IF(G$30-$B36>=0,IF(G$30=$B36,IF($C36=0,(($D36-(((G$30-$B36)+1)*$F36)/2)),(($D36-(((G$30-$B36)+1)*$F36)*($C36/12)))),IF($C36=0,($D36-((G$30-$B36)*$F36))-($F36/2),($D36-((G$30-$B36)*$F36))-($F36*($C36/12)))),0),0) -> 0 | H36: =IF(IF(H$30-$B36>=0,IF(H$30=$B36,IF($C36=0,(($D36-(((H$30-$B36)+1)*$F36)/2)),(($D36-(((H$30-$B36)+1)*$F36)*($C36/12)))),IF($C36=0,($D36-((H$30-$B36)*$F36))-($F36/2),($D36-((H$30-$B36)*$F36))-($F36*($C36/12)))),0)>0,IF(H$30-$B36>=0,IF(H$30=$B36,IF($C36=0,(($D36-(((H$30-$B36)+1)*$F36)/2)),(($D36-(((H$30-$B36)+1)*$F36)*($C36/12)))),IF($C36=0,($D36-((H$30-$B36)*$F36))-($F36/2),($D36-((H$30-$B36)*$F36))-($F36*($C36/12)))),0),0) -> 0 | I36: =IF(IF(I$30-$B36>=0,IF(I$30=$B36,IF($C36=0,(($D36-(((I$30-$B36)+1)*$F36)/2)),(($D36-(((I$30-$B36)+1)*$F36)*($C36/12)))),IF($C36=0,($D36-((I$30-$B36)*$F36))-($F36/2),($D36-((I$30-$B36)*$F36))-($F36*($C36/12)))),0)>0,IF(I$30-$B36>=0,IF(I$30=$B36,IF($C36=0,(($D36-(((I$30-$B36)+1)*$F36)/2)),(($D36-(((I$30-$B36)+1)*$F36)*($C36/12)))),IF($C36=0,($D36-((I$30-$B36)*$F36))-($F36/2),($D36-((I$30-$B36)*$F36))-($F36*($C36/12)))),0),0) -> 0 | J36: =IF(IF(J$30-$B36>=0,IF(J$30=$B36,IF($C36=0,(($D36-(((J$30-$B36)+1)*$F36)/2)),(($D36-(((J$30-$B36)+1)*$F36)*($C36/12)))),IF($C36=0,($D36-((J$30-$B36)*$F36))-($F36/2),($D36-((J$30-$B36)*$F36))-($F36*($C36/12)))),0)>0,IF(J$30-$B36>=0,IF(J$30=$B36,IF($C36=0,(($D36-(((J$30-$B36)+1)*$F36)/2)),(($D36-(((J$30-$B36)+1)*$F36)*($C36/12)))),IF($C36=0,($D36-((J$30-$B36)*$F36))-($F36/2),($D36-((J$30-$B36)*$F36))-($F36*($C36/12)))),0),0) -> 0 | K36: =IF(IF(K$30-$B36>=0,IF(K$30=$B36,IF($C36=0,(($D36-(((K$30-$B36)+1)*$F36)/2)),(($D36-(((K$30-$B36)+1)*$F36)*($C36/12)))),IF($C36=0,($D36-((K$30-$B36)*$F36))-($F36/2),($D36-((K$30-$B36)*$F36))-($F36*($C36/12)))),0)>0,IF(K$30-$B36>=0,IF(K$30=$B36,IF($C36=0,(($D36-(((K$30-$B36)+1)*$F36)/2)),(($D36-(((K$30-$B36)+1)*$F36)*($C36/12)))),IF($C36=0,($D36-((K$30-$B36)*$F36))-($F36/2),($D36-((K$30-$B36)*$F36))-($F36*($C36/12)))),0),0) -> 0 | L36: =IF(IF(L$30-$B36>=0,IF(L$30=$B36,IF($C36=0,(($D36-(((L$30-$B36)+1)*$F36)/2)),(($D36-(((L$30-$B36)+1)*$F36)*($C36/12)))),IF($C36=0,($D36-((L$30-$B36)*$F36))-($F36/2),($D36-((L$30-$B36)*$F36))-($F36*($C36/12)))),0)>0,IF(L$30-$B36>=0,IF(L$30=$B36,IF($C36=0,(($D36-(((L$30-$B36)+1)*$F36)/2)),(($D36-(((L$30-$B36)+1)*$F36)*($C36/12)))),IF($C36=0,($D36-((L$30-$B36)*$F36))-($F36/2),($D36-((L$30-$B36)*$F36))-($F36*($C36/12)))),0),0) -> 0 | M36: =IF(IF(M$30-$B36>=0,IF(M$30=$B36,IF($C36=0,(($D36-(((M$30-$B36)+1)*$F36)/2)),(($D36-(((M$30-$B36)+1)*$F36)*($C36/12)))),IF($C36=0,($D36-((M$30-$B36)*$F36))-($F36/2),($D36-((M$30-$B36)*$F36))-($F36*($C36/12)))),0)>0,IF(M$30-$B36>=0,IF(M$30=$B36,IF($C36=0,(($D36-(((M$30-$B36)+1)*$F36)/2)),(($D36-(((M$30-$B36)+1)*$F36)*($C36/12)))),IF($C36=0,($D36-((M$30-$B36)*$F36))-($F36/2),($D36-((M$30-$B36)*$F36))-($F36*($C36/12)))),0),0) -> 0 | N36: =IF(IF(N$30-$B36>=0,IF(N$30=$B36,IF($C36=0,(($D36-(((N$30-$B36)+1)*$F36)/2)),(($D36-(((N$30-$B36)+1)*$F36)*($C36/12)))),IF($C36=0,($D36-((N$30-$B36)*$F36))-($F36/2),($D36-((N$30-$B36)*$F36))-($F36*($C36/12)))),0)>0,IF(N$30-$B36>=0,IF(N$30=$B36,IF($C36=0,(($D36-(((N$30-$B36)+1)*$F36)/2)),(($D36-(((N$30-$B36)+1)*$F36)*($C36/12)))),IF($C36=0,($D36-((N$30-$B36)*$F36))-($F36/2),($D36-((N$30-$B36)*$F36))-($F36*($C36/12)))),0),0) -> 0 | ... AA36: =IF(IF(AA$30-$B36>=0,IF(AA$30=$B36,IF($C36=0,(($D36-(((AA$30-$B36)+1)*$F36)/2)),(($D36-(((AA$30-$B36)+1)*$F36)*($C36/12)))),IF($C36=0,($D36-((AA$30-$B36)*$F36))-($F36/2),($D36-((AA$30-$B36)*$F36))-($F36*($C36/12)))),0)>0,IF(AA$30-$B36>=0,IF(AA$30=$B36,IF($C36=0,(($D36-(((AA$30-$B36)+1)*$F36)/2)),(($D36-(((AA$30-$B36)+1)*$F36)*($C36/12)))),IF($C36=0,($D36-((AA$30-$B36)*$F36))-($F36/2),($D36-((AA$30-$B36)*$F36))-($F36*($C36/12)))),0),0) -> 0
A37: Asset | F37: =IFERROR(D37/E37,0) -> 0 | G37: =IF(IF(G$30-$B37>=0,IF(G$30=$B37,IF($C37=0,(($D37-(((G$30-$B37)+1)*$F37)/2)),(($D37-(((G$30-$B37)+1)*$F37)*($C37/12)))),IF($C37=0,($D37-((G$30-$B37)*$F37))-($F37/2),($D37-((G$30-$B37)*$F37))-($F37*($C37/12)))),0)>0,IF(G$30-$B37>=0,IF(G$30=$B37,IF($C37=0,(($D37-(((G$30-$B37)+1)*$F37)/2)),(($D37-(((G$30-$B37)+1)*$F37)*($C37/12)))),IF($C37=0,($D37-((G$30-$B37)*$F37))-($F37/2),($D37-((G$30-$B37)*$F37))-($F37*($C37/12)))),0),0) -> 0 | H37: =IF(IF(H$30-$B37>=0,IF(H$30=$B37,IF($C37=0,(($D37-(((H$30-$B37)+1)*$F37)/2)),(($D37-(((H$30-$B37)+1)*$F37)*($C37/12)))),IF($C37=0,($D37-((H$30-$B37)*$F37))-($F37/2),($D37-((H$30-$B37)*$F37))-($F37*($C37/12)))),0)>0,IF(H$30-$B37>=0,IF(H$30=$B37,IF($C37=0,(($D37-(((H$30-$B37)+1)*$F37)/2)),(($D37-(((H$30-$B37)+1)*$F37)*($C37/12)))),IF($C37=0,($D37-((H$30-$B37)*$F37))-($F37/2),($D37-((H$30-$B37)*$F37))-($F37*($C37/12)))),0),0) -> 0 | I37: =IF(IF(I$30-$B37>=0,IF(I$30=$B37,IF($C37=0,(($D37-(((I$30-$B37)+1)*$F37)/2)),(($D37-(((I$30-$B37)+1)*$F37)*($C37/12)))),IF($C37=0,($D37-((I$30-$B37)*$F37))-($F37/2),($D37-((I$30-$B37)*$F37))-($F37*($C37/12)))),0)>0,IF(I$30-$B37>=0,IF(I$30=$B37,IF($C37=0,(($D37-(((I$30-$B37)+1)*$F37)/2)),(($D37-(((I$30-$B37)+1)*$F37)*($C37/12)))),IF($C37=0,($D37-((I$30-$B37)*$F37))-($F37/2),($D37-((I$30-$B37)*$F37))-($F37*($C37/12)))),0),0) -> 0 | J37: =IF(IF(J$30-$B37>=0,IF(J$30=$B37,IF($C37=0,(($D37-(((J$30-$B37)+1)*$F37)/2)),(($D37-(((J$30-$B37)+1)*$F37)*($C37/12)))),IF($C37=0,($D37-((J$30-$B37)*$F37))-($F37/2),($D37-((J$30-$B37)*$F37))-($F37*($C37/12)))),0)>0,IF(J$30-$B37>=0,IF(J$30=$B37,IF($C37=0,(($D37-(((J$30-$B37)+1)*$F37)/2)),(($D37-(((J$30-$B37)+1)*$F37)*($C37/12)))),IF($C37=0,($D37-((J$30-$B37)*$F37))-($F37/2),($D37-((J$30-$B37)*$F37))-($F37*($C37/12)))),0),0) -> 0 | K37: =IF(IF(K$30-$B37>=0,IF(K$30=$B37,IF($C37=0,(($D37-(((K$30-$B37)+1)*$F37)/2)),(($D37-(((K$30-$B37)+1)*$F37)*($C37/12)))),IF($C37=0,($D37-((K$30-$B37)*$F37))-($F37/2),($D37-((K$30-$B37)*$F37))-($F37*($C37/12)))),0)>0,IF(K$30-$B37>=0,IF(K$30=$B37,IF($C37=0,(($D37-(((K$30-$B37)+1)*$F37)/2)),(($D37-(((K$30-$B37)+1)*$F37)*($C37/12)))),IF($C37=0,($D37-((K$30-$B37)*$F37))-($F37/2),($D37-((K$30-$B37)*$F37))-($F37*($C37/12)))),0),0) -> 0 | L37: =IF(IF(L$30-$B37>=0,IF(L$30=$B37,IF($C37=0,(($D37-(((L$30-$B37)+1)*$F37)/2)),(($D37-(((L$30-$B37)+1)*$F37)*($C37/12)))),IF($C37=0,($D37-((L$30-$B37)*$F37))-($F37/2),($D37-((L$30-$B37)*$F37))-($F37*($C37/12)))),0)>0,IF(L$30-$B37>=0,IF(L$30=$B37,IF($C37=0,(($D37-(((L$30-$B37)+1)*$F37)/2)),(($D37-(((L$30-$B37)+1)*$F37)*($C37/12)))),IF($C37=0,($D37-((L$30-$B37)*$F37))-($F37/2),($D37-((L$30-$B37)*$F37))-($F37*($C37/12)))),0),0) -> 0 | M37: =IF(IF(M$30-$B37>=0,IF(M$30=$B37,IF($C37=0,(($D37-(((M$30-$B37)+1)*$F37)/2)),(($D37-(((M$30-$B37)+1)*$F37)*($C37/12)))),IF($C37=0,($D37-((M$30-$B37)*$F37))-($F37/2),($D37-((M$30-$B37)*$F37))-($F37*($C37/12)))),0)>0,IF(M$30-$B37>=0,IF(M$30=$B37,IF($C37=0,(($D37-(((M$30-$B37)+1)*$F37)/2)),(($D37-(((M$30-$B37)+1)*$F37)*($C37/12)))),IF($C37=0,($D37-((M$30-$B37)*$F37))-($F37/2),($D37-((M$30-$B37)*$F37))-($F37*($C37/12)))),0),0) -> 0 | N37: =IF(IF(N$30-$B37>=0,IF(N$30=$B37,IF($C37=0,(($D37-(((N$30-$B37)+1)*$F37)/2)),(($D37-(((N$30-$B37)+1)*$F37)*($C37/12)))),IF($C37=0,($D37-((N$30-$B37)*$F37))-($F37/2),($D37-((N$30-$B37)*$F37))-($F37*($C37/12)))),0)>0,IF(N$30-$B37>=0,IF(N$30=$B37,IF($C37=0,(($D37-(((N$30-$B37)+1)*$F37)/2)),(($D37-(((N$30-$B37)+1)*$F37)*($C37/12)))),IF($C37=0,($D37-((N$30-$B37)*$F37))-($F37/2),($D37-((N$30-$B37)*$F37))-($F37*($C37/12)))),0),0) -> 0 | ... AA37: =IF(IF(AA$30-$B37>=0,IF(AA$30=$B37,IF($C37=0,(($D37-(((AA$30-$B37)+1)*$F37)/2)),(($D37-(((AA$30-$B37)+1)*$F37)*($C37/12)))),IF($C37=0,($D37-((AA$30-$B37)*$F37))-($F37/2),($D37-((AA$30-$B37)*$F37))-($F37*($C37/12)))),0)>0,IF(AA$30-$B37>=0,IF(AA$30=$B37,IF($C37=0,(($D37-(((AA$30-$B37)+1)*$F37)/2)),(($D37-(((AA$30-$B37)+1)*$F37)*($C37/12)))),IF($C37=0,($D37-((AA$30-$B37)*$F37))-($F37/2),($D37-((AA$30-$B37)*$F37))-($F37*($C37/12)))),0),0) -> 0
A38: Asset | F38: =IFERROR(D38/E38,0) -> 0 | G38: =IF(IF(G$30-$B38>=0,IF(G$30=$B38,IF($C38=0,(($D38-(((G$30-$B38)+1)*$F38)/2)),(($D38-(((G$30-$B38)+1)*$F38)*($C38/12)))),IF($C38=0,($D38-((G$30-$B38)*$F38))-($F38/2),($D38-((G$30-$B38)*$F38))-($F38*($C38/12)))),0)>0,IF(G$30-$B38>=0,IF(G$30=$B38,IF($C38=0,(($D38-(((G$30-$B38)+1)*$F38)/2)),(($D38-(((G$30-$B38)+1)*$F38)*($C38/12)))),IF($C38=0,($D38-((G$30-$B38)*$F38))-($F38/2),($D38-((G$30-$B38)*$F38))-($F38*($C38/12)))),0),0) -> 0 | H38: =IF(IF(H$30-$B38>=0,IF(H$30=$B38,IF($C38=0,(($D38-(((H$30-$B38)+1)*$F38)/2)),(($D38-(((H$30-$B38)+1)*$F38)*($C38/12)))),IF($C38=0,($D38-((H$30-$B38)*$F38))-($F38/2),($D38-((H$30-$B38)*$F38))-($F38*($C38/12)))),0)>0,IF(H$30-$B38>=0,IF(H$30=$B38,IF($C38=0,(($D38-(((H$30-$B38)+1)*$F38)/2)),(($D38-(((H$30-$B38)+1)*$F38)*($C38/12)))),IF($C38=0,($D38-((H$30-$B38)*$F38))-($F38/2),($D38-((H$30-$B38)*$F38))-($F38*($C38/12)))),0),0) -> 0 | I38: =IF(IF(I$30-$B38>=0,IF(I$30=$B38,IF($C38=0,(($D38-(((I$30-$B38)+1)*$F38)/2)),(($D38-(((I$30-$B38)+1)*$F38)*($C38/12)))),IF($C38=0,($D38-((I$30-$B38)*$F38))-($F38/2),($D38-((I$30-$B38)*$F38))-($F38*($C38/12)))),0)>0,IF(I$30-$B38>=0,IF(I$30=$B38,IF($C38=0,(($D38-(((I$30-$B38)+1)*$F38)/2)),(($D38-(((I$30-$B38)+1)*$F38)*($C38/12)))),IF($C38=0,($D38-((I$30-$B38)*$F38))-($F38/2),($D38-((I$30-$B38)*$F38))-($F38*($C38/12)))),0),0) -> 0 | J38: =IF(IF(J$30-$B38>=0,IF(J$30=$B38,IF($C38=0,(($D38-(((J$30-$B38)+1)*$F38)/2)),(($D38-(((J$30-$B38)+1)*$F38)*($C38/12)))),IF($C38=0,($D38-((J$30-$B38)*$F38))-($F38/2),($D38-((J$30-$B38)*$F38))-($F38*($C38/12)))),0)>0,IF(J$30-$B38>=0,IF(J$30=$B38,IF($C38=0,(($D38-(((J$30-$B38)+1)*$F38)/2)),(($D38-(((J$30-$B38)+1)*$F38)*($C38/12)))),IF($C38=0,($D38-((J$30-$B38)*$F38))-($F38/2),($D38-((J$30-$B38)*$F38))-($F38*($C38/12)))),0),0) -> 0 | K38: =IF(IF(K$30-$B38>=0,IF(K$30=$B38,IF($C38=0,(($D38-(((K$30-$B38)+1)*$F38)/2)),(($D38-(((K$30-$B38)+1)*$F38)*($C38/12)))),IF($C38=0,($D38-((K$30-$B38)*$F38))-($F38/2),($D38-((K$30-$B38)*$F38))-($F38*($C38/12)))),0)>0,IF(K$30-$B38>=0,IF(K$30=$B38,IF($C38=0,(($D38-(((K$30-$B38)+1)*$F38)/2)),(($D38-(((K$30-$B38)+1)*$F38)*($C38/12)))),IF($C38=0,($D38-((K$30-$B38)*$F38))-($F38/2),($D38-((K$30-$B38)*$F38))-($F38*($C38/12)))),0),0) -> 0 | L38: =IF(IF(L$30-$B38>=0,IF(L$30=$B38,IF($C38=0,(($D38-(((L$30-$B38)+1)*$F38)/2)),(($D38-(((L$30-$B38)+1)*$F38)*($C38/12)))),IF($C38=0,($D38-((L$30-$B38)*$F38))-($F38/2),($D38-((L$30-$B38)*$F38))-($F38*($C38/12)))),0)>0,IF(L$30-$B38>=0,IF(L$30=$B38,IF($C38=0,(($D38-(((L$30-$B38)+1)*$F38)/2)),(($D38-(((L$30-$B38)+1)*$F38)*($C38/12)))),IF($C38=0,($D38-((L$30-$B38)*$F38))-($F38/2),($D38-((L$30-$B38)*$F38))-($F38*($C38/12)))),0),0) -> 0 | M38: =IF(IF(M$30-$B38>=0,IF(M$30=$B38,IF($C38=0,(($D38-(((M$30-$B38)+1)*$F38)/2)),(($D38-(((M$30-$B38)+1)*$F38)*($C38/12)))),IF($C38=0,($D38-((M$30-$B38)*$F38))-($F38/2),($D38-((M$30-$B38)*$F38))-($F38*($C38/12)))),0)>0,IF(M$30-$B38>=0,IF(M$30=$B38,IF($C38=0,(($D38-(((M$30-$B38)+1)*$F38)/2)),(($D38-(((M$30-$B38)+1)*$F38)*($C38/12)))),IF($C38=0,($D38-((M$30-$B38)*$F38))-($F38/2),($D38-((M$30-$B38)*$F38))-($F38*($C38/12)))),0),0) -> 0 | N38: =IF(IF(N$30-$B38>=0,IF(N$30=$B38,IF($C38=0,(($D38-(((N$30-$B38)+1)*$F38)/2)),(($D38-(((N$30-$B38)+1)*$F38)*($C38/12)))),IF($C38=0,($D38-((N$30-$B38)*$F38))-($F38/2),($D38-((N$30-$B38)*$F38))-($F38*($C38/12)))),0)>0,IF(N$30-$B38>=0,IF(N$30=$B38,IF($C38=0,(($D38-(((N$30-$B38)+1)*$F38)/2)),(($D38-(((N$30-$B38)+1)*$F38)*($C38/12)))),IF($C38=0,($D38-((N$30-$B38)*$F38))-($F38/2),($D38-((N$30-$B38)*$F38))-($F38*($C38/12)))),0),0) -> 0 | ... AA38: =IF(IF(AA$30-$B38>=0,IF(AA$30=$B38,IF($C38=0,(($D38-(((AA$30-$B38)+1)*$F38)/2)),(($D38-(((AA$30-$B38)+1)*$F38)*($C38/12)))),IF($C38=0,($D38-((AA$30-$B38)*$F38))-($F38/2),($D38-((AA$30-$B38)*$F38))-($F38*($C38/12)))),0)>0,IF(AA$30-$B38>=0,IF(AA$30=$B38,IF($C38=0,(($D38-(((AA$30-$B38)+1)*$F38)/2)),(($D38-(((AA$30-$B38)+1)*$F38)*($C38/12)))),IF($C38=0,($D38-((AA$30-$B38)*$F38))-($F38/2),($D38-((AA$30-$B38)*$F38))-($F38*($C38/12)))),0),0) -> 0
A39: Asset | F39: =IFERROR(D39/E39,0) -> 0 | G39: =IF(IF(G$30-$B39>=0,IF(G$30=$B39,IF($C39=0,(($D39-(((G$30-$B39)+1)*$F39)/2)),(($D39-(((G$30-$B39)+1)*$F39)*($C39/12)))),IF($C39=0,($D39-((G$30-$B39)*$F39))-($F39/2),($D39-((G$30-$B39)*$F39))-($F39*($C39/12)))),0)>0,IF(G$30-$B39>=0,IF(G$30=$B39,IF($C39=0,(($D39-(((G$30-$B39)+1)*$F39)/2)),(($D39-(((G$30-$B39)+1)*$F39)*($C39/12)))),IF($C39=0,($D39-((G$30-$B39)*$F39))-($F39/2),($D39-((G$30-$B39)*$F39))-($F39*($C39/12)))),0),0) -> 0 | H39: =IF(IF(H$30-$B39>=0,IF(H$30=$B39,IF($C39=0,(($D39-(((H$30-$B39)+1)*$F39)/2)),(($D39-(((H$30-$B39)+1)*$F39)*($C39/12)))),IF($C39=0,($D39-((H$30-$B39)*$F39))-($F39/2),($D39-((H$30-$B39)*$F39))-($F39*($C39/12)))),0)>0,IF(H$30-$B39>=0,IF(H$30=$B39,IF($C39=0,(($D39-(((H$30-$B39)+1)*$F39)/2)),(($D39-(((H$30-$B39)+1)*$F39)*($C39/12)))),IF($C39=0,($D39-((H$30-$B39)*$F39))-($F39/2),($D39-((H$30-$B39)*$F39))-($F39*($C39/12)))),0),0) -> 0 | I39: =IF(IF(I$30-$B39>=0,IF(I$30=$B39,IF($C39=0,(($D39-(((I$30-$B39)+1)*$F39)/2)),(($D39-(((I$30-$B39)+1)*$F39)*($C39/12)))),IF($C39=0,($D39-((I$30-$B39)*$F39))-($F39/2),($D39-((I$30-$B39)*$F39))-($F39*($C39/12)))),0)>0,IF(I$30-$B39>=0,IF(I$30=$B39,IF($C39=0,(($D39-(((I$30-$B39)+1)*$F39)/2)),(($D39-(((I$30-$B39)+1)*$F39)*($C39/12)))),IF($C39=0,($D39-((I$30-$B39)*$F39))-($F39/2),($D39-((I$30-$B39)*$F39))-($F39*($C39/12)))),0),0) -> 0 | J39: =IF(IF(J$30-$B39>=0,IF(J$30=$B39,IF($C39=0,(($D39-(((J$30-$B39)+1)*$F39)/2)),(($D39-(((J$30-$B39)+1)*$F39)*($C39/12)))),IF($C39=0,($D39-((J$30-$B39)*$F39))-($F39/2),($D39-((J$30-$B39)*$F39))-($F39*($C39/12)))),0)>0,IF(J$30-$B39>=0,IF(J$30=$B39,IF($C39=0,(($D39-(((J$30-$B39)+1)*$F39)/2)),(($D39-(((J$30-$B39)+1)*$F39)*($C39/12)))),IF($C39=0,($D39-((J$30-$B39)*$F39))-($F39/2),($D39-((J$30-$B39)*$F39))-($F39*($C39/12)))),0),0) -> 0 | K39: =IF(IF(K$30-$B39>=0,IF(K$30=$B39,IF($C39=0,(($D39-(((K$30-$B39)+1)*$F39)/2)),(($D39-(((K$30-$B39)+1)*$F39)*($C39/12)))),IF($C39=0,($D39-((K$30-$B39)*$F39))-($F39/2),($D39-((K$30-$B39)*$F39))-($F39*($C39/12)))),0)>0,IF(K$30-$B39>=0,IF(K$30=$B39,IF($C39=0,(($D39-(((K$30-$B39)+1)*$F39)/2)),(($D39-(((K$30-$B39)+1)*$F39)*($C39/12)))),IF($C39=0,($D39-((K$30-$B39)*$F39))-($F39/2),($D39-((K$30-$B39)*$F39))-($F39*($C39/12)))),0),0) -> 0 | L39: =IF(IF(L$30-$B39>=0,IF(L$30=$B39,IF($C39=0,(($D39-(((L$30-$B39)+1)*$F39)/2)),(($D39-(((L$30-$B39)+1)*$F39)*($C39/12)))),IF($C39=0,($D39-((L$30-$B39)*$F39))-($F39/2),($D39-((L$30-$B39)*$F39))-($F39*($C39/12)))),0)>0,IF(L$30-$B39>=0,IF(L$30=$B39,IF($C39=0,(($D39-(((L$30-$B39)+1)*$F39)/2)),(($D39-(((L$30-$B39)+1)*$F39)*($C39/12)))),IF($C39=0,($D39-((L$30-$B39)*$F39))-($F39/2),($D39-((L$30-$B39)*$F39))-($F39*($C39/12)))),0),0) -> 0 | M39: =IF(IF(M$30-$B39>=0,IF(M$30=$B39,IF($C39=0,(($D39-(((M$30-$B39)+1)*$F39)/2)),(($D39-(((M$30-$B39)+1)*$F39)*($C39/12)))),IF($C39=0,($D39-((M$30-$B39)*$F39))-($F39/2),($D39-((M$30-$B39)*$F39))-($F39*($C39/12)))),0)>0,IF(M$30-$B39>=0,IF(M$30=$B39,IF($C39=0,(($D39-(((M$30-$B39)+1)*$F39)/2)),(($D39-(((M$30-$B39)+1)*$F39)*($C39/12)))),IF($C39=0,($D39-((M$30-$B39)*$F39))-($F39/2),($D39-((M$30-$B39)*$F39))-($F39*($C39/12)))),0),0) -> 0 | N39: =IF(IF(N$30-$B39>=0,IF(N$30=$B39,IF($C39=0,(($D39-(((N$30-$B39)+1)*$F39)/2)),(($D39-(((N$30-$B39)+1)*$F39)*($C39/12)))),IF($C39=0,($D39-((N$30-$B39)*$F39))-($F39/2),($D39-((N$30-$B39)*$F39))-($F39*($C39/12)))),0)>0,IF(N$30-$B39>=0,IF(N$30=$B39,IF($C39=0,(($D39-(((N$30-$B39)+1)*$F39)/2)),(($D39-(((N$30-$B39)+1)*$F39)*($C39/12)))),IF($C39=0,($D39-((N$30-$B39)*$F39))-($F39/2),($D39-((N$30-$B39)*$F39))-($F39*($C39/12)))),0),0) -> 0 | ... AA39: =IF(IF(AA$30-$B39>=0,IF(AA$30=$B39,IF($C39=0,(($D39-(((AA$30-$B39)+1)*$F39)/2)),(($D39-(((AA$30-$B39)+1)*$F39)*($C39/12)))),IF($C39=0,($D39-((AA$30-$B39)*$F39))-($F39/2),($D39-((AA$30-$B39)*$F39))-($F39*($C39/12)))),0)>0,IF(AA$30-$B39>=0,IF(AA$30=$B39,IF($C39=0,(($D39-(((AA$30-$B39)+1)*$F39)/2)),(($D39-(((AA$30-$B39)+1)*$F39)*($C39/12)))),IF($C39=0,($D39-((AA$30-$B39)*$F39))-($F39/2),($D39-((AA$30-$B39)*$F39))-($F39*($C39/12)))),0),0) -> 0
A41: Total | D41: =SUM(D31:D39) -> 0 | F41: =SUM(F31:F37) -> 0 | G41: =SUM(G31:G37) -> 0 | H41: =SUM(H31:H37) -> 0 | I41: =SUM(I31:I37) -> 0 | J41: =SUM(J31:J37) -> 0 | K41: =SUM(K31:K37) -> 0 | L41: =SUM(L31:L37) -> 0 | M41: =SUM(M31:M37) -> 0 | ... P41: =SUM(P31:P37) -> 0 | Q41: =SUM(Q31:Q39) -> 0 | R41: =SUM(R31:R39) -> 0 | S41: =SUM(S31:S39) -> 0 | T41: =SUM(T31:T39) -> 0 | U41: =SUM(U31:U39) -> 0 | V41: =SUM(V31:V39) -> 0 | W41: =SUM(W31:W39) -> 0 | X41: =SUM(X31:X39) -> 0 | ... AA41: =SUM(AA31:AA39) -> 0
A44: Remaining Cost Basis at beginning of year | D44: =P41 -> 0
A45: ="20"&RIGHT(A25,2)&" Additions" -> 2024 Additions | D45: =SUMIF($B$31:$B$39,"20"&RIGHT(A25,2),$D$31:$D$39) -> 0
A46: ="20"&RIGHT(A25,2)&" Tax Depreciation" -> 2024 Tax Depreciation | D46: =D44+D45-Q41 -> 0
A49: Note: 50% Depreciation is taken in initial and final year of asset life unless specific month of service is entered.
A53: ='Basic Information'!B4 -> 0
A54: AMORTIZATION DETAIL
A55: ='Basic Information'!B1 -> 12/31/24
A56: (Amounts in Local Currency)
G59: Remaining Cost Basis
B60: Year Added | C60: Month Added | D60: Book Cost | E60: Asset Life | F60: Annual Amortization | G60: =H60-1 -> 2014 | H60: =I60-1 -> 2015 | I60: =J60-1 -> 2016 | J60: =K60-1 -> 2017 | K60: =L60-1 -> 2018 | L60: =M60-1 -> 2019 | M60: =N60-1 -> 2020 | N60: =O60-1 -> 2021 | ... P60: =Q60-1 -> 2023 | Q60: ="20"&RIGHT(A55,2) -> 2024 | R60: =Q60+1 -> 2025 | S60: =R60+1 -> 2026 | T60: =S60+1 -> 2027 | U60: =T60+1 -> 2028 | V60: =U60+1 -> 2029 | W60: =V60+1 -> 2030 | X60: =W60+1 -> 2031 | Y60: =X60+1 -> 2032 | ... AA60: =Z60+1 -> 2034
A61: Asset | F61: =IFERROR(D61/E61,0) -> 0 | G61: =IF(IF(G$60-$B61>=0,IF(G$60=$B61,IF($C61=0,(($D61-(((G$60-$B61)+1)*$F61)/2)),(($D61-(((G$60-$B61)+1)*$F61)*($C61/12)))),IF($C61=0,($D61-((G$60-$B61)*$F61))-($F61/2),($D61-((G$60-$B61)*$F61))-($F61*($C61/12)))),0)>0,IF(G$60-$B61>=0,IF(G$60=$B61,IF($C61=0,(($D61-(((G$60-$B61)+1)*$F61)/2)),(($D61-(((G$60-$B61)+1)*$F61)*($C61/12)))),IF($C61=0,($D61-((G$60-$B61)*$F61))-($F61/2),($D61-((G$60-$B61)*$F61))-($F61*($C61/12)))),0),0) -> 0 | H61: =IF(IF(H$60-$B61>=0,IF(H$60=$B61,IF($C61=0,(($D61-(((H$60-$B61)+1)*$F61)/2)),(($D61-(((H$60-$B61)+1)*$F61)*($C61/12)))),IF($C61=0,($D61-((H$60-$B61)*$F61))-($F61/2),($D61-((H$60-$B61)*$F61))-($F61*($C61/12)))),0)>0,IF(H$60-$B61>=0,IF(H$60=$B61,IF($C61=0,(($D61-(((H$60-$B61)+1)*$F61)/2)),(($D61-(((H$60-$B61)+1)*$F61)*($C61/12)))),IF($C61=0,($D61-((H$60-$B61)*$F61))-($F61/2),($D61-((H$60-$B61)*$F61))-($F61*($C61/12)))),0),0) -> 0 | I61: =IF(IF(I$60-$B61>=0,IF(I$60=$B61,IF($C61=0,(($D61-(((I$60-$B61)+1)*$F61)/2)),(($D61-(((I$60-$B61)+1)*$F61)*($C61/12)))),IF($C61=0,($D61-((I$60-$B61)*$F61))-($F61/2),($D61-((I$60-$B61)*$F61))-($F61*($C61/12)))),0)>0,IF(I$60-$B61>=0,IF(I$60=$B61,IF($C61=0,(($D61-(((I$60-$B61)+1)*$F61)/2)),(($D61-(((I$60-$B61)+1)*$F61)*($C61/12)))),IF($C61=0,($D61-((I$60-$B61)*$F61))-($F61/2),($D61-((I$60-$B61)*$F61))-($F61*($C61/12)))),0),0) -> 0 | J61: =IF(IF(J$60-$B61>=0,IF(J$60=$B61,IF($C61=0,(($D61-(((J$60-$B61)+1)*$F61)/2)),(($D61-(((J$60-$B61)+1)*$F61)*($C61/12)))),IF($C61=0,($D61-((J$60-$B61)*$F61))-($F61/2),($D61-((J$60-$B61)*$F61))-($F61*($C61/12)))),0)>0,IF(J$60-$B61>=0,IF(J$60=$B61,IF($C61=0,(($D61-(((J$60-$B61)+1)*$F61)/2)),(($D61-(((J$60-$B61)+1)*$F61)*($C61/12)))),IF($C61=0,($D61-((J$60-$B61)*$F61))-($F61/2),($D61-((J$60-$B61)*$F61))-($F61*($C61/12)))),0),0) -> 0 | K61: =IF(IF(K$60-$B61>=0,IF(K$60=$B61,IF($C61=0,(($D61-(((K$60-$B61)+1)*$F61)/2)),(($D61-(((K$60-$B61)+1)*$F61)*($C61/12)))),IF($C61=0,($D61-((K$60-$B61)*$F61))-($F61/2),($D61-((K$60-$B61)*$F61))-($F61*($C61/12)))),0)>0,IF(K$60-$B61>=0,IF(K$60=$B61,IF($C61=0,(($D61-(((K$60-$B61)+1)*$F61)/2)),(($D61-(((K$60-$B61)+1)*$F61)*($C61/12)))),IF($C61=0,($D61-((K$60-$B61)*$F61))-($F61/2),($D61-((K$60-$B61)*$F61))-($F61*($C61/12)))),0),0) -> 0 | L61: =IF(IF(L$60-$B61>=0,IF(L$60=$B61,IF($C61=0,(($D61-(((L$60-$B61)+1)*$F61)/2)),(($D61-(((L$60-$B61)+1)*$F61)*($C61/12)))),IF($C61=0,($D61-((L$60-$B61)*$F61))-($F61/2),($D61-((L$60-$B61)*$F61))-($F61*($C61/12)))),0)>0,IF(L$60-$B61>=0,IF(L$60=$B61,IF($C61=0,(($D61-(((L$60-$B61)+1)*$F61)/2)),(($D61-(((L$60-$B61)+1)*$F61)*($C61/12)))),IF($C61=0,($D61-((L$60-$B61)*$F61))-($F61/2),($D61-((L$60-$B61)*$F61))-($F61*($C61/12)))),0),0) -> 0 | M61: =IF(IF(M$60-$B61>=0,IF(M$60=$B61,IF($C61=0,(($D61-(((M$60-$B61)+1)*$F61)/2)),(($D61-(((M$60-$B61)+1)*$F61)*($C61/12)))),IF($C61=0,($D61-((M$60-$B61)*$F61))-($F61/2),($D61-((M$60-$B61)*$F61))-($F61*($C61/12)))),0)>0,IF(M$60-$B61>=0,IF(M$60=$B61,IF($C61=0,(($D61-(((M$60-$B61)+1)*$F61)/2)),(($D61-(((M$60-$B61)+1)*$F61)*($C61/12)))),IF($C61=0,($D61-((M$60-$B61)*$F61))-($F61/2),($D61-((M$60-$B61)*$F61))-($F61*($C61/12)))),0),0) -> 0 | N61: =IF(IF(N$60-$B61>=0,IF(N$60=$B61,IF($C61=0,(($D61-(((N$60-$B61)+1)*$F61)/2)),(($D61-(((N$60-$B61)+1)*$F61)*($C61/12)))),IF($C61=0,($D61-((N$60-$B61)*$F61))-($F61/2),($D61-((N$60-$B61)*$F61))-($F61*($C61/12)))),0)>0,IF(N$60-$B61>=0,IF(N$60=$B61,IF($C61=0,(($D61-(((N$60-$B61)+1)*$F61)/2)),(($D61-(((N$60-$B61)+1)*$F61)*($C61/12)))),IF($C61=0,($D61-((N$60-$B61)*$F61))-($F61/2),($D61-((N$60-$B61)*$F61))-($F61*($C61/12)))),0),0) -> 0 | ... AA61: =IF(IF(AA$60-$B61>=0,IF(AA$60=$B61,IF($C61=0,(($D61-(((AA$60-$B61)+1)*$F61)/2)),(($D61-(((AA$60-$B61)+1)*$F61)*($C61/12)))),IF($C61=0,($D61-((AA$60-$B61)*$F61))-($F61/2),($D61-((AA$60-$B61)*$F61))-($F61*($C61/12)))),0)>0,IF(AA$60-$B61>=0,IF(AA$60=$B61,IF($C61=0,(($D61-(((AA$60-$B61)+1)*$F61)/2)),(($D61-(((AA$60-$B61)+1)*$F61)*($C61/12)))),IF($C61=0,($D61-((AA$60-$B61)*$F61))-($F61/2),($D61-((AA$60-$B61)*$F61))-($F61*($C61/12)))),0),0) -> 0
A62: Asset | F62: =IFERROR(D62/E62,0) -> 0 | G62: =IF(IF(G$60-$B62>=0,IF(G$60=$B62,IF($C62=0,(($D62-(((G$60-$B62)+1)*$F62)/2)),(($D62-(((G$60-$B62)+1)*$F62)*($C62/12)))),IF($C62=0,($D62-((G$60-$B62)*$F62))-($F62/2),($D62-((G$60-$B62)*$F62))-($F62*($C62/12)))),0)>0,IF(G$60-$B62>=0,IF(G$60=$B62,IF($C62=0,(($D62-(((G$60-$B62)+1)*$F62)/2)),(($D62-(((G$60-$B62)+1)*$F62)*($C62/12)))),IF($C62=0,($D62-((G$60-$B62)*$F62))-($F62/2),($D62-((G$60-$B62)*$F62))-($F62*($C62/12)))),0),0) -> 0 | H62: =IF(IF(H$60-$B62>=0,IF(H$60=$B62,IF($C62=0,(($D62-(((H$60-$B62)+1)*$F62)/2)),(($D62-(((H$60-$B62)+1)*$F62)*($C62/12)))),IF($C62=0,($D62-((H$60-$B62)*$F62))-($F62/2),($D62-((H$60-$B62)*$F62))-($F62*($C62/12)))),0)>0,IF(H$60-$B62>=0,IF(H$60=$B62,IF($C62=0,(($D62-(((H$60-$B62)+1)*$F62)/2)),(($D62-(((H$60-$B62)+1)*$F62)*($C62/12)))),IF($C62=0,($D62-((H$60-$B62)*$F62))-($F62/2),($D62-((H$60-$B62)*$F62))-($F62*($C62/12)))),0),0) -> 0 | I62: =IF(IF(I$60-$B62>=0,IF(I$60=$B62,IF($C62=0,(($D62-(((I$60-$B62)+1)*$F62)/2)),(($D62-(((I$60-$B62)+1)*$F62)*($C62/12)))),IF($C62=0,($D62-((I$60-$B62)*$F62))-($F62/2),($D62-((I$60-$B62)*$F62))-($F62*($C62/12)))),0)>0,IF(I$60-$B62>=0,IF(I$60=$B62,IF($C62=0,(($D62-(((I$60-$B62)+1)*$F62)/2)),(($D62-(((I$60-$B62)+1)*$F62)*($C62/12)))),IF($C62=0,($D62-((I$60-$B62)*$F62))-($F62/2),($D62-((I$60-$B62)*$F62))-($F62*($C62/12)))),0),0) -> 0 | J62: =IF(IF(J$60-$B62>=0,IF(J$60=$B62,IF($C62=0,(($D62-(((J$60-$B62)+1)*$F62)/2)),(($D62-(((J$60-$B62)+1)*$F62)*($C62/12)))),IF($C62=0,($D62-((J$60-$B62)*$F62))-($F62/2),($D62-((J$60-$B62)*$F62))-($F62*($C62/12)))),0)>0,IF(J$60-$B62>=0,IF(J$60=$B62,IF($C62=0,(($D62-(((J$60-$B62)+1)*$F62)/2)),(($D62-(((J$60-$B62)+1)*$F62)*($C62/12)))),IF($C62=0,($D62-((J$60-$B62)*$F62))-($F62/2),($D62-((J$60-$B62)*$F62))-($F62*($C62/12)))),0),0) -> 0 | K62: =IF(IF(K$60-$B62>=0,IF(K$60=$B62,IF($C62=0,(($D62-(((K$60-$B62)+1)*$F62)/2)),(($D62-(((K$60-$B62)+1)*$F62)*($C62/12)))),IF($C62=0,($D62-((K$60-$B62)*$F62))-($F62/2),($D62-((K$60-$B62)*$F62))-($F62*($C62/12)))),0)>0,IF(K$60-$B62>=0,IF(K$60=$B62,IF($C62=0,(($D62-(((K$60-$B62)+1)*$F62)/2)),(($D62-(((K$60-$B62)+1)*$F62)*($C62/12)))),IF($C62=0,($D62-((K$60-$B62)*$F62))-($F62/2),($D62-((K$60-$B62)*$F62))-($F62*($C62/12)))),0),0) -> 0 | L62: =IF(IF(L$60-$B62>=0,IF(L$60=$B62,IF($C62=0,(($D62-(((L$60-$B62)+1)*$F62)/2)),(($D62-(((L$60-$B62)+1)*$F62)*($C62/12)))),IF($C62=0,($D62-((L$60-$B62)*$F62))-($F62/2),($D62-((L$60-$B62)*$F62))-($F62*($C62/12)))),0)>0,IF(L$60-$B62>=0,IF(L$60=$B62,IF($C62=0,(($D62-(((L$60-$B62)+1)*$F62)/2)),(($D62-(((L$60-$B62)+1)*$F62)*($C62/12)))),IF($C62=0,($D62-((L$60-$B62)*$F62))-($F62/2),($D62-((L$60-$B62)*$F62))-($F62*($C62/12)))),0),0) -> 0 | M62: =IF(IF(M$60-$B62>=0,IF(M$60=$B62,IF($C62=0,(($D62-(((M$60-$B62)+1)*$F62)/2)),(($D62-(((M$60-$B62)+1)*$F62)*($C62/12)))),IF($C62=0,($D62-((M$60-$B62)*$F62))-($F62/2),($D62-((M$60-$B62)*$F62))-($F62*($C62/12)))),0)>0,IF(M$60-$B62>=0,IF(M$60=$B62,IF($C62=0,(($D62-(((M$60-$B62)+1)*$F62)/2)),(($D62-(((M$60-$B62)+1)*$F62)*($C62/12)))),IF($C62=0,($D62-((M$60-$B62)*$F62))-($F62/2),($D62-((M$60-$B62)*$F62))-($F62*($C62/12)))),0),0) -> 0 | N62: =IF(IF(N$60-$B62>=0,IF(N$60=$B62,IF($C62=0,(($D62-(((N$60-$B62)+1)*$F62)/2)),(($D62-(((N$60-$B62)+1)*$F62)*($C62/12)))),IF($C62=0,($D62-((N$60-$B62)*$F62))-($F62/2),($D62-((N$60-$B62)*$F62))-($F62*($C62/12)))),0)>0,IF(N$60-$B62>=0,IF(N$60=$B62,IF($C62=0,(($D62-(((N$60-$B62)+1)*$F62)/2)),(($D62-(((N$60-$B62)+1)*$F62)*($C62/12)))),IF($C62=0,($D62-((N$60-$B62)*$F62))-($F62/2),($D62-((N$60-$B62)*$F62))-($F62*($C62/12)))),0),0) -> 0 | ... AA62: =IF(IF(AA$60-$B62>=0,IF(AA$60=$B62,IF($C62=0,(($D62-(((AA$60-$B62)+1)*$F62)/2)),(($D62-(((AA$60-$B62)+1)*$F62)*($C62/12)))),IF($C62=0,($D62-((AA$60-$B62)*$F62))-($F62/2),($D62-((AA$60-$B62)*$F62))-($F62*($C62/12)))),0)>0,IF(AA$60-$B62>=0,IF(AA$60=$B62,IF($C62=0,(($D62-(((AA$60-$B62)+1)*$F62)/2)),(($D62-(((AA$60-$B62)+1)*$F62)*($C62/12)))),IF($C62=0,($D62-((AA$60-$B62)*$F62))-($F62/2),($D62-((AA$60-$B62)*$F62))-($F62*($C62/12)))),0),0) -> 0
A63: Asset | F63: =IFERROR(D63/E63,0) -> 0 | G63: =IF(IF(G$60-$B63>=0,IF(G$60=$B63,IF($C63=0,(($D63-(((G$60-$B63)+1)*$F63)/2)),(($D63-(((G$60-$B63)+1)*$F63)*($C63/12)))),IF($C63=0,($D63-((G$60-$B63)*$F63))-($F63/2),($D63-((G$60-$B63)*$F63))-($F63*($C63/12)))),0)>0,IF(G$60-$B63>=0,IF(G$60=$B63,IF($C63=0,(($D63-(((G$60-$B63)+1)*$F63)/2)),(($D63-(((G$60-$B63)+1)*$F63)*($C63/12)))),IF($C63=0,($D63-((G$60-$B63)*$F63))-($F63/2),($D63-((G$60-$B63)*$F63))-($F63*($C63/12)))),0),0) -> 0 | H63: =IF(IF(H$60-$B63>=0,IF(H$60=$B63,IF($C63=0,(($D63-(((H$60-$B63)+1)*$F63)/2)),(($D63-(((H$60-$B63)+1)*$F63)*($C63/12)))),IF($C63=0,($D63-((H$60-$B63)*$F63))-($F63/2),($D63-((H$60-$B63)*$F63))-($F63*($C63/12)))),0)>0,IF(H$60-$B63>=0,IF(H$60=$B63,IF($C63=0,(($D63-(((H$60-$B63)+1)*$F63)/2)),(($D63-(((H$60-$B63)+1)*$F63)*($C63/12)))),IF($C63=0,($D63-((H$60-$B63)*$F63))-($F63/2),($D63-((H$60-$B63)*$F63))-($F63*($C63/12)))),0),0) -> 0 | I63: =IF(IF(I$60-$B63>=0,IF(I$60=$B63,IF($C63=0,(($D63-(((I$60-$B63)+1)*$F63)/2)),(($D63-(((I$60-$B63)+1)*$F63)*($C63/12)))),IF($C63=0,($D63-((I$60-$B63)*$F63))-($F63/2),($D63-((I$60-$B63)*$F63))-($F63*($C63/12)))),0)>0,IF(I$60-$B63>=0,IF(I$60=$B63,IF($C63=0,(($D63-(((I$60-$B63)+1)*$F63)/2)),(($D63-(((I$60-$B63)+1)*$F63)*($C63/12)))),IF($C63=0,($D63-((I$60-$B63)*$F63))-($F63/2),($D63-((I$60-$B63)*$F63))-($F63*($C63/12)))),0),0) -> 0 | J63: =IF(IF(J$60-$B63>=0,IF(J$60=$B63,IF($C63=0,(($D63-(((J$60-$B63)+1)*$F63)/2)),(($D63-(((J$60-$B63)+1)*$F63)*($C63/12)))),IF($C63=0,($D63-((J$60-$B63)*$F63))-($F63/2),($D63-((J$60-$B63)*$F63))-($F63*($C63/12)))),0)>0,IF(J$60-$B63>=0,IF(J$60=$B63,IF($C63=0,(($D63-(((J$60-$B63)+1)*$F63)/2)),(($D63-(((J$60-$B63)+1)*$F63)*($C63/12)))),IF($C63=0,($D63-((J$60-$B63)*$F63))-($F63/2),($D63-((J$60-$B63)*$F63))-($F63*($C63/12)))),0),0) -> 0 | K63: =IF(IF(K$60-$B63>=0,IF(K$60=$B63,IF($C63=0,(($D63-(((K$60-$B63)+1)*$F63)/2)),(($D63-(((K$60-$B63)+1)*$F63)*($C63/12)))),IF($C63=0,($D63-((K$60-$B63)*$F63))-($F63/2),($D63-((K$60-$B63)*$F63))-($F63*($C63/12)))),0)>0,IF(K$60-$B63>=0,IF(K$60=$B63,IF($C63=0,(($D63-(((K$60-$B63)+1)*$F63)/2)),(($D63-(((K$60-$B63)+1)*$F63)*($C63/12)))),IF($C63=0,($D63-((K$60-$B63)*$F63))-($F63/2),($D63-((K$60-$B63)*$F63))-($F63*($C63/12)))),0),0) -> 0 | L63: =IF(IF(L$60-$B63>=0,IF(L$60=$B63,IF($C63=0,(($D63-(((L$60-$B63)+1)*$F63)/2)),(($D63-(((L$60-$B63)+1)*$F63)*($C63/12)))),IF($C63=0,($D63-((L$60-$B63)*$F63))-($F63/2),($D63-((L$60-$B63)*$F63))-($F63*($C63/12)))),0)>0,IF(L$60-$B63>=0,IF(L$60=$B63,IF($C63=0,(($D63-(((L$60-$B63)+1)*$F63)/2)),(($D63-(((L$60-$B63)+1)*$F63)*($C63/12)))),IF($C63=0,($D63-((L$60-$B63)*$F63))-($F63/2),($D63-((L$60-$B63)*$F63))-($F63*($C63/12)))),0),0) -> 0 | M63: =IF(IF(M$60-$B63>=0,IF(M$60=$B63,IF($C63=0,(($D63-(((M$60-$B63)+1)*$F63)/2)),(($D63-(((M$60-$B63)+1)*$F63)*($C63/12)))),IF($C63=0,($D63-((M$60-$B63)*$F63))-($F63/2),($D63-((M$60-$B63)*$F63))-($F63*($C63/12)))),0)>0,IF(M$60-$B63>=0,IF(M$60=$B63,IF($C63=0,(($D63-(((M$60-$B63)+1)*$F63)/2)),(($D63-(((M$60-$B63)+1)*$F63)*($C63/12)))),IF($C63=0,($D63-((M$60-$B63)*$F63))-($F63/2),($D63-((M$60-$B63)*$F63))-($F63*($C63/12)))),0),0) -> 0 | N63: =IF(IF(N$60-$B63>=0,IF(N$60=$B63,IF($C63=0,(($D63-(((N$60-$B63)+1)*$F63)/2)),(($D63-(((N$60-$B63)+1)*$F63)*($C63/12)))),IF($C63=0,($D63-((N$60-$B63)*$F63))-($F63/2),($D63-((N$60-$B63)*$F63))-($F63*($C63/12)))),0)>0,IF(N$60-$B63>=0,IF(N$60=$B63,IF($C63=0,(($D63-(((N$60-$B63)+1)*$F63)/2)),(($D63-(((N$60-$B63)+1)*$F63)*($C63/12)))),IF($C63=0,($D63-((N$60-$B63)*$F63))-($F63/2),($D63-((N$60-$B63)*$F63))-($F63*($C63/12)))),0),0) -> 0 | ... AA63: =IF(IF(AA$60-$B63>=0,IF(AA$60=$B63,IF($C63=0,(($D63-(((AA$60-$B63)+1)*$F63)/2)),(($D63-(((AA$60-$B63)+1)*$F63)*($C63/12)))),IF($C63=0,($D63-((AA$60-$B63)*$F63))-($F63/2),($D63-((AA$60-$B63)*$F63))-($F63*($C63/12)))),0)>0,IF(AA$60-$B63>=0,IF(AA$60=$B63,IF($C63=0,(($D63-(((AA$60-$B63)+1)*$F63)/2)),(($D63-(((AA$60-$B63)+1)*$F63)*($C63/12)))),IF($C63=0,($D63-((AA$60-$B63)*$F63))-($F63/2),($D63-((AA$60-$B63)*$F63))-($F63*($C63/12)))),0),0) -> 0
A64: Asset | F64: =IFERROR(D64/E64,0) -> 0 | G64: =IF(IF(G$60-$B64>=0,IF(G$60=$B64,IF($C64=0,(($D64-(((G$60-$B64)+1)*$F64)/2)),(($D64-(((G$60-$B64)+1)*$F64)*($C64/12)))),IF($C64=0,($D64-((G$60-$B64)*$F64))-($F64/2),($D64-((G$60-$B64)*$F64))-($F64*($C64/12)))),0)>0,IF(G$60-$B64>=0,IF(G$60=$B64,IF($C64=0,(($D64-(((G$60-$B64)+1)*$F64)/2)),(($D64-(((G$60-$B64)+1)*$F64)*($C64/12)))),IF($C64=0,($D64-((G$60-$B64)*$F64))-($F64/2),($D64-((G$60-$B64)*$F64))-($F64*($C64/12)))),0),0) -> 0 | H64: =IF(IF(H$60-$B64>=0,IF(H$60=$B64,IF($C64=0,(($D64-(((H$60-$B64)+1)*$F64)/2)),(($D64-(((H$60-$B64)+1)*$F64)*($C64/12)))),IF($C64=0,($D64-((H$60-$B64)*$F64))-($F64/2),($D64-((H$60-$B64)*$F64))-($F64*($C64/12)))),0)>0,IF(H$60-$B64>=0,IF(H$60=$B64,IF($C64=0,(($D64-(((H$60-$B64)+1)*$F64)/2)),(($D64-(((H$60-$B64)+1)*$F64)*($C64/12)))),IF($C64=0,($D64-((H$60-$B64)*$F64))-($F64/2),($D64-((H$60-$B64)*$F64))-($F64*($C64/12)))),0),0) -> 0 | I64: =IF(IF(I$60-$B64>=0,IF(I$60=$B64,IF($C64=0,(($D64-(((I$60-$B64)+1)*$F64)/2)),(($D64-(((I$60-$B64)+1)*$F64)*($C64/12)))),IF($C64=0,($D64-((I$60-$B64)*$F64))-($F64/2),($D64-((I$60-$B64)*$F64))-($F64*($C64/12)))),0)>0,IF(I$60-$B64>=0,IF(I$60=$B64,IF($C64=0,(($D64-(((I$60-$B64)+1)*$F64)/2)),(($D64-(((I$60-$B64)+1)*$F64)*($C64/12)))),IF($C64=0,($D64-((I$60-$B64)*$F64))-($F64/2),($D64-((I$60-$B64)*$F64))-($F64*($C64/12)))),0),0) -> 0 | J64: =IF(IF(J$60-$B64>=0,IF(J$60=$B64,IF($C64=0,(($D64-(((J$60-$B64)+1)*$F64)/2)),(($D64-(((J$60-$B64)+1)*$F64)*($C64/12)))),IF($C64=0,($D64-((J$60-$B64)*$F64))-($F64/2),($D64-((J$60-$B64)*$F64))-($F64*($C64/12)))),0)>0,IF(J$60-$B64>=0,IF(J$60=$B64,IF($C64=0,(($D64-(((J$60-$B64)+1)*$F64)/2)),(($D64-(((J$60-$B64)+1)*$F64)*($C64/12)))),IF($C64=0,($D64-((J$60-$B64)*$F64))-($F64/2),($D64-((J$60-$B64)*$F64))-($F64*($C64/12)))),0),0) -> 0 | K64: =IF(IF(K$60-$B64>=0,IF(K$60=$B64,IF($C64=0,(($D64-(((K$60-$B64)+1)*$F64)/2)),(($D64-(((K$60-$B64)+1)*$F64)*($C64/12)))),IF($C64=0,($D64-((K$60-$B64)*$F64))-($F64/2),($D64-((K$60-$B64)*$F64))-($F64*($C64/12)))),0)>0,IF(K$60-$B64>=0,IF(K$60=$B64,IF($C64=0,(($D64-(((K$60-$B64)+1)*$F64)/2)),(($D64-(((K$60-$B64)+1)*$F64)*($C64/12)))),IF($C64=0,($D64-((K$60-$B64)*$F64))-($F64/2),($D64-((K$60-$B64)*$F64))-($F64*($C64/12)))),0),0) -> 0 | L64: =IF(IF(L$60-$B64>=0,IF(L$60=$B64,IF($C64=0,(($D64-(((L$60-$B64)+1)*$F64)/2)),(($D64-(((L$60-$B64)+1)*$F64)*($C64/12)))),IF($C64=0,($D64-((L$60-$B64)*$F64))-($F64/2),($D64-((L$60-$B64)*$F64))-($F64*($C64/12)))),0)>0,IF(L$60-$B64>=0,IF(L$60=$B64,IF($C64=0,(($D64-(((L$60-$B64)+1)*$F64)/2)),(($D64-(((L$60-$B64)+1)*$F64)*($C64/12)))),IF($C64=0,($D64-((L$60-$B64)*$F64))-($F64/2),($D64-((L$60-$B64)*$F64))-($F64*($C64/12)))),0),0) -> 0 | M64: =IF(IF(M$60-$B64>=0,IF(M$60=$B64,IF($C64=0,(($D64-(((M$60-$B64)+1)*$F64)/2)),(($D64-(((M$60-$B64)+1)*$F64)*($C64/12)))),IF($C64=0,($D64-((M$60-$B64)*$F64))-($F64/2),($D64-((M$60-$B64)*$F64))-($F64*($C64/12)))),0)>0,IF(M$60-$B64>=0,IF(M$60=$B64,IF($C64=0,(($D64-(((M$60-$B64)+1)*$F64)/2)),(($D64-(((M$60-$B64)+1)*$F64)*($C64/12)))),IF($C64=0,($D64-((M$60-$B64)*$F64))-($F64/2),($D64-((M$60-$B64)*$F64))-($F64*($C64/12)))),0),0) -> 0 | N64: =IF(IF(N$60-$B64>=0,IF(N$60=$B64,IF($C64=0,(($D64-(((N$60-$B64)+1)*$F64)/2)),(($D64-(((N$60-$B64)+1)*$F64)*($C64/12)))),IF($C64=0,($D64-((N$60-$B64)*$F64))-($F64/2),($D64-((N$60-$B64)*$F64))-($F64*($C64/12)))),0)>0,IF(N$60-$B64>=0,IF(N$60=$B64,IF($C64=0,(($D64-(((N$60-$B64)+1)*$F64)/2)),(($D64-(((N$60-$B64)+1)*$F64)*($C64/12)))),IF($C64=0,($D64-((N$60-$B64)*$F64))-($F64/2),($D64-((N$60-$B64)*$F64))-($F64*($C64/12)))),0),0) -> 0 | ... AA64: =IF(IF(AA$60-$B64>=0,IF(AA$60=$B64,IF($C64=0,(($D64-(((AA$60-$B64)+1)*$F64)/2)),(($D64-(((AA$60-$B64)+1)*$F64)*($C64/12)))),IF($C64=0,($D64-((AA$60-$B64)*$F64))-($F64/2),($D64-((AA$60-$B64)*$F64))-($F64*($C64/12)))),0)>0,IF(AA$60-$B64>=0,IF(AA$60=$B64,IF($C64=0,(($D64-(((AA$60-$B64)+1)*$F64)/2)),(($D64-(((AA$60-$B64)+1)*$F64)*($C64/12)))),IF($C64=0,($D64-((AA$60-$B64)*$F64))-($F64/2),($D64-((AA$60-$B64)*$F64))-($F64*($C64/12)))),0),0) -> 0
A65: Asset | F65: =IFERROR(D65/E65,0) -> 0 | G65: =IF(IF(G$60-$B65>=0,IF(G$60=$B65,IF($C65=0,(($D65-(((G$60-$B65)+1)*$F65)/2)),(($D65-(((G$60-$B65)+1)*$F65)*($C65/12)))),IF($C65=0,($D65-((G$60-$B65)*$F65))-($F65/2),($D65-((G$60-$B65)*$F65))-($F65*($C65/12)))),0)>0,IF(G$60-$B65>=0,IF(G$60=$B65,IF($C65=0,(($D65-(((G$60-$B65)+1)*$F65)/2)),(($D65-(((G$60-$B65)+1)*$F65)*($C65/12)))),IF($C65=0,($D65-((G$60-$B65)*$F65))-($F65/2),($D65-((G$60-$B65)*$F65))-($F65*($C65/12)))),0),0) -> 0 | H65: =IF(IF(H$60-$B65>=0,IF(H$60=$B65,IF($C65=0,(($D65-(((H$60-$B65)+1)*$F65)/2)),(($D65-(((H$60-$B65)+1)*$F65)*($C65/12)))),IF($C65=0,($D65-((H$60-$B65)*$F65))-($F65/2),($D65-((H$60-$B65)*$F65))-($F65*($C65/12)))),0)>0,IF(H$60-$B65>=0,IF(H$60=$B65,IF($C65=0,(($D65-(((H$60-$B65)+1)*$F65)/2)),(($D65-(((H$60-$B65)+1)*$F65)*($C65/12)))),IF($C65=0,($D65-((H$60-$B65)*$F65))-($F65/2),($D65-((H$60-$B65)*$F65))-($F65*($C65/12)))),0),0) -> 0 | I65: =IF(IF(I$60-$B65>=0,IF(I$60=$B65,IF($C65=0,(($D65-(((I$60-$B65)+1)*$F65)/2)),(($D65-(((I$60-$B65)+1)*$F65)*($C65/12)))),IF($C65=0,($D65-((I$60-$B65)*$F65))-($F65/2),($D65-((I$60-$B65)*$F65))-($F65*($C65/12)))),0)>0,IF(I$60-$B65>=0,IF(I$60=$B65,IF($C65=0,(($D65-(((I$60-$B65)+1)*$F65)/2)),(($D65-(((I$60-$B65)+1)*$F65)*($C65/12)))),IF($C65=0,($D65-((I$60-$B65)*$F65))-($F65/2),($D65-((I$60-$B65)*$F65))-($F65*($C65/12)))),0),0) -> 0 | J65: =IF(IF(J$60-$B65>=0,IF(J$60=$B65,IF($C65=0,(($D65-(((J$60-$B65)+1)*$F65)/2)),(($D65-(((J$60-$B65)+1)*$F65)*($C65/12)))),IF($C65=0,($D65-((J$60-$B65)*$F65))-($F65/2),($D65-((J$60-$B65)*$F65))-($F65*($C65/12)))),0)>0,IF(J$60-$B65>=0,IF(J$60=$B65,IF($C65=0,(($D65-(((J$60-$B65)+1)*$F65)/2)),(($D65-(((J$60-$B65)+1)*$F65)*($C65/12)))),IF($C65=0,($D65-((J$60-$B65)*$F65))-($F65/2),($D65-((J$60-$B65)*$F65))-($F65*($C65/12)))),0),0) -> 0 | K65: =IF(IF(K$60-$B65>=0,IF(K$60=$B65,IF($C65=0,(($D65-(((K$60-$B65)+1)*$F65)/2)),(($D65-(((K$60-$B65)+1)*$F65)*($C65/12)))),IF($C65=0,($D65-((K$60-$B65)*$F65))-($F65/2),($D65-((K$60-$B65)*$F65))-($F65*($C65/12)))),0)>0,IF(K$60-$B65>=0,IF(K$60=$B65,IF($C65=0,(($D65-(((K$60-$B65)+1)*$F65)/2)),(($D65-(((K$60-$B65)+1)*$F65)*($C65/12)))),IF($C65=0,($D65-((K$60-$B65)*$F65))-($F65/2),($D65-((K$60-$B65)*$F65))-($F65*($C65/12)))),0),0) -> 0 | L65: =IF(IF(L$60-$B65>=0,IF(L$60=$B65,IF($C65=0,(($D65-(((L$60-$B65)+1)*$F65)/2)),(($D65-(((L$60-$B65)+1)*$F65)*($C65/12)))),IF($C65=0,($D65-((L$60-$B65)*$F65))-($F65/2),($D65-((L$60-$B65)*$F65))-($F65*($C65/12)))),0)>0,IF(L$60-$B65>=0,IF(L$60=$B65,IF($C65=0,(($D65-(((L$60-$B65)+1)*$F65)/2)),(($D65-(((L$60-$B65)+1)*$F65)*($C65/12)))),IF($C65=0,($D65-((L$60-$B65)*$F65))-($F65/2),($D65-((L$60-$B65)*$F65))-($F65*($C65/12)))),0),0) -> 0 | M65: =IF(IF(M$60-$B65>=0,IF(M$60=$B65,IF($C65=0,(($D65-(((M$60-$B65)+1)*$F65)/2)),(($D65-(((M$60-$B65)+1)*$F65)*($C65/12)))),IF($C65=0,($D65-((M$60-$B65)*$F65))-($F65/2),($D65-((M$60-$B65)*$F65))-($F65*($C65/12)))),0)>0,IF(M$60-$B65>=0,IF(M$60=$B65,IF($C65=0,(($D65-(((M$60-$B65)+1)*$F65)/2)),(($D65-(((M$60-$B65)+1)*$F65)*($C65/12)))),IF($C65=0,($D65-((M$60-$B65)*$F65))-($F65/2),($D65-((M$60-$B65)*$F65))-($F65*($C65/12)))),0),0) -> 0 | N65: =IF(IF(N$60-$B65>=0,IF(N$60=$B65,IF($C65=0,(($D65-(((N$60-$B65)+1)*$F65)/2)),(($D65-(((N$60-$B65)+1)*$F65)*($C65/12)))),IF($C65=0,($D65-((N$60-$B65)*$F65))-($F65/2),($D65-((N$60-$B65)*$F65))-($F65*($C65/12)))),0)>0,IF(N$60-$B65>=0,IF(N$60=$B65,IF($C65=0,(($D65-(((N$60-$B65)+1)*$F65)/2)),(($D65-(((N$60-$B65)+1)*$F65)*($C65/12)))),IF($C65=0,($D65-((N$60-$B65)*$F65))-($F65/2),($D65-((N$60-$B65)*$F65))-($F65*($C65/12)))),0),0) -> 0 | ... AA65: =IF(IF(AA$60-$B65>=0,IF(AA$60=$B65,IF($C65=0,(($D65-(((AA$60-$B65)+1)*$F65)/2)),(($D65-(((AA$60-$B65)+1)*$F65)*($C65/12)))),IF($C65=0,($D65-((AA$60-$B65)*$F65))-($F65/2),($D65-((AA$60-$B65)*$F65))-($F65*($C65/12)))),0)>0,IF(AA$60-$B65>=0,IF(AA$60=$B65,IF($C65=0,(($D65-(((AA$60-$B65)+1)*$F65)/2)),(($D65-(((AA$60-$B65)+1)*$F65)*($C65/12)))),IF($C65=0,($D65-((AA$60-$B65)*$F65))-($F65/2),($D65-((AA$60-$B65)*$F65))-($F65*($C65/12)))),0),0) -> 0
A66: Asset | F66: =IFERROR(D66/E66,0) -> 0 | G66: =IF(IF(G$60-$B66>=0,IF(G$60=$B66,IF($C66=0,(($D66-(((G$60-$B66)+1)*$F66)/2)),(($D66-(((G$60-$B66)+1)*$F66)*($C66/12)))),IF($C66=0,($D66-((G$60-$B66)*$F66))-($F66/2),($D66-((G$60-$B66)*$F66))-($F66*($C66/12)))),0)>0,IF(G$60-$B66>=0,IF(G$60=$B66,IF($C66=0,(($D66-(((G$60-$B66)+1)*$F66)/2)),(($D66-(((G$60-$B66)+1)*$F66)*($C66/12)))),IF($C66=0,($D66-((G$60-$B66)*$F66))-($F66/2),($D66-((G$60-$B66)*$F66))-($F66*($C66/12)))),0),0) -> 0 | H66: =IF(IF(H$60-$B66>=0,IF(H$60=$B66,IF($C66=0,(($D66-(((H$60-$B66)+1)*$F66)/2)),(($D66-(((H$60-$B66)+1)*$F66)*($C66/12)))),IF($C66=0,($D66-((H$60-$B66)*$F66))-($F66/2),($D66-((H$60-$B66)*$F66))-($F66*($C66/12)))),0)>0,IF(H$60-$B66>=0,IF(H$60=$B66,IF($C66=0,(($D66-(((H$60-$B66)+1)*$F66)/2)),(($D66-(((H$60-$B66)+1)*$F66)*($C66/12)))),IF($C66=0,($D66-((H$60-$B66)*$F66))-($F66/2),($D66-((H$60-$B66)*$F66))-($F66*($C66/12)))),0),0) -> 0 | I66: =IF(IF(I$60-$B66>=0,IF(I$60=$B66,IF($C66=0,(($D66-(((I$60-$B66)+1)*$F66)/2)),(($D66-(((I$60-$B66)+1)*$F66)*($C66/12)))),IF($C66=0,($D66-((I$60-$B66)*$F66))-($F66/2),($D66-((I$60-$B66)*$F66))-($F66*($C66/12)))),0)>0,IF(I$60-$B66>=0,IF(I$60=$B66,IF($C66=0,(($D66-(((I$60-$B66)+1)*$F66)/2)),(($D66-(((I$60-$B66)+1)*$F66)*($C66/12)))),IF($C66=0,($D66-((I$60-$B66)*$F66))-($F66/2),($D66-((I$60-$B66)*$F66))-($F66*($C66/12)))),0),0) -> 0 | J66: =IF(IF(J$60-$B66>=0,IF(J$60=$B66,IF($C66=0,(($D66-(((J$60-$B66)+1)*$F66)/2)),(($D66-(((J$60-$B66)+1)*$F66)*($C66/12)))),IF($C66=0,($D66-((J$60-$B66)*$F66))-($F66/2),($D66-((J$60-$B66)*$F66))-($F66*($C66/12)))),0)>0,IF(J$60-$B66>=0,IF(J$60=$B66,IF($C66=0,(($D66-(((J$60-$B66)+1)*$F66)/2)),(($D66-(((J$60-$B66)+1)*$F66)*($C66/12)))),IF($C66=0,($D66-((J$60-$B66)*$F66))-($F66/2),($D66-((J$60-$B66)*$F66))-($F66*($C66/12)))),0),0) -> 0 | K66: =IF(IF(K$60-$B66>=0,IF(K$60=$B66,IF($C66=0,(($D66-(((K$60-$B66)+1)*$F66)/2)),(($D66-(((K$60-$B66)+1)*$F66)*($C66/12)))),IF($C66=0,($D66-((K$60-$B66)*$F66))-($F66/2),($D66-((K$60-$B66)*$F66))-($F66*($C66/12)))),0)>0,IF(K$60-$B66>=0,IF(K$60=$B66,IF($C66=0,(($D66-(((K$60-$B66)+1)*$F66)/2)),(($D66-(((K$60-$B66)+1)*$F66)*($C66/12)))),IF($C66=0,($D66-((K$60-$B66)*$F66))-($F66/2),($D66-((K$60-$B66)*$F66))-($F66*($C66/12)))),0),0) -> 0 | L66: =IF(IF(L$60-$B66>=0,IF(L$60=$B66,IF($C66=0,(($D66-(((L$60-$B66)+1)*$F66)/2)),(($D66-(((L$60-$B66)+1)*$F66)*($C66/12)))),IF($C66=0,($D66-((L$60-$B66)*$F66))-($F66/2),($D66-((L$60-$B66)*$F66))-($F66*($C66/12)))),0)>0,IF(L$60-$B66>=0,IF(L$60=$B66,IF($C66=0,(($D66-(((L$60-$B66)+1)*$F66)/2)),(($D66-(((L$60-$B66)+1)*$F66)*($C66/12)))),IF($C66=0,($D66-((L$60-$B66)*$F66))-($F66/2),($D66-((L$60-$B66)*$F66))-($F66*($C66/12)))),0),0) -> 0 | M66: =IF(IF(M$60-$B66>=0,IF(M$60=$B66,IF($C66=0,(($D66-(((M$60-$B66)+1)*$F66)/2)),(($D66-(((M$60-$B66)+1)*$F66)*($C66/12)))),IF($C66=0,($D66-((M$60-$B66)*$F66))-($F66/2),($D66-((M$60-$B66)*$F66))-($F66*($C66/12)))),0)>0,IF(M$60-$B66>=0,IF(M$60=$B66,IF($C66=0,(($D66-(((M$60-$B66)+1)*$F66)/2)),(($D66-(((M$60-$B66)+1)*$F66)*($C66/12)))),IF($C66=0,($D66-((M$60-$B66)*$F66))-($F66/2),($D66-((M$60-$B66)*$F66))-($F66*($C66/12)))),0),0) -> 0 | N66: =IF(IF(N$60-$B66>=0,IF(N$60=$B66,IF($C66=0,(($D66-(((N$60-$B66)+1)*$F66)/2)),(($D66-(((N$60-$B66)+1)*$F66)*($C66/12)))),IF($C66=0,($D66-((N$60-$B66)*$F66))-($F66/2),($D66-((N$60-$B66)*$F66))-($F66*($C66/12)))),0)>0,IF(N$60-$B66>=0,IF(N$60=$B66,IF($C66=0,(($D66-(((N$60-$B66)+1)*$F66)/2)),(($D66-(((N$60-$B66)+1)*$F66)*($C66/12)))),IF($C66=0,($D66-((N$60-$B66)*$F66))-($F66/2),($D66-((N$60-$B66)*$F66))-($F66*($C66/12)))),0),0) -> 0 | ... AA66: =IF(IF(AA$60-$B66>=0,IF(AA$60=$B66,IF($C66=0,(($D66-(((AA$60-$B66)+1)*$F66)/2)),(($D66-(((AA$60-$B66)+1)*$F66)*($C66/12)))),IF($C66=0,($D66-((AA$60-$B66)*$F66))-($F66/2),($D66-((AA$60-$B66)*$F66))-($F66*($C66/12)))),0)>0,IF(AA$60-$B66>=0,IF(AA$60=$B66,IF($C66=0,(($D66-(((AA$60-$B66)+1)*$F66)/2)),(($D66-(((AA$60-$B66)+1)*$F66)*($C66/12)))),IF($C66=0,($D66-((AA$60-$B66)*$F66))-($F66/2),($D66-((AA$60-$B66)*$F66))-($F66*($C66/12)))),0),0) -> 0
A67: Asset | F67: =IFERROR(D67/E67,0) -> 0 | G67: =IF(IF(G$60-$B67>=0,IF(G$60=$B67,IF($C67=0,(($D67-(((G$60-$B67)+1)*$F67)/2)),(($D67-(((G$60-$B67)+1)*$F67)*($C67/12)))),IF($C67=0,($D67-((G$60-$B67)*$F67))-($F67/2),($D67-((G$60-$B67)*$F67))-($F67*($C67/12)))),0)>0,IF(G$60-$B67>=0,IF(G$60=$B67,IF($C67=0,(($D67-(((G$60-$B67)+1)*$F67)/2)),(($D67-(((G$60-$B67)+1)*$F67)*($C67/12)))),IF($C67=0,($D67-((G$60-$B67)*$F67))-($F67/2),($D67-((G$60-$B67)*$F67))-($F67*($C67/12)))),0),0) -> 0 | H67: =IF(IF(H$60-$B67>=0,IF(H$60=$B67,IF($C67=0,(($D67-(((H$60-$B67)+1)*$F67)/2)),(($D67-(((H$60-$B67)+1)*$F67)*($C67/12)))),IF($C67=0,($D67-((H$60-$B67)*$F67))-($F67/2),($D67-((H$60-$B67)*$F67))-($F67*($C67/12)))),0)>0,IF(H$60-$B67>=0,IF(H$60=$B67,IF($C67=0,(($D67-(((H$60-$B67)+1)*$F67)/2)),(($D67-(((H$60-$B67)+1)*$F67)*($C67/12)))),IF($C67=0,($D67-((H$60-$B67)*$F67))-($F67/2),($D67-((H$60-$B67)*$F67))-($F67*($C67/12)))),0),0) -> 0 | I67: =IF(IF(I$60-$B67>=0,IF(I$60=$B67,IF($C67=0,(($D67-(((I$60-$B67)+1)*$F67)/2)),(($D67-(((I$60-$B67)+1)*$F67)*($C67/12)))),IF($C67=0,($D67-((I$60-$B67)*$F67))-($F67/2),($D67-((I$60-$B67)*$F67))-($F67*($C67/12)))),0)>0,IF(I$60-$B67>=0,IF(I$60=$B67,IF($C67=0,(($D67-(((I$60-$B67)+1)*$F67)/2)),(($D67-(((I$60-$B67)+1)*$F67)*($C67/12)))),IF($C67=0,($D67-((I$60-$B67)*$F67))-($F67/2),($D67-((I$60-$B67)*$F67))-($F67*($C67/12)))),0),0) -> 0 | J67: =IF(IF(J$60-$B67>=0,IF(J$60=$B67,IF($C67=0,(($D67-(((J$60-$B67)+1)*$F67)/2)),(($D67-(((J$60-$B67)+1)*$F67)*($C67/12)))),IF($C67=0,($D67-((J$60-$B67)*$F67))-($F67/2),($D67-((J$60-$B67)*$F67))-($F67*($C67/12)))),0)>0,IF(J$60-$B67>=0,IF(J$60=$B67,IF($C67=0,(($D67-(((J$60-$B67)+1)*$F67)/2)),(($D67-(((J$60-$B67)+1)*$F67)*($C67/12)))),IF($C67=0,($D67-((J$60-$B67)*$F67))-($F67/2),($D67-((J$60-$B67)*$F67))-($F67*($C67/12)))),0),0) -> 0 | K67: =IF(IF(K$60-$B67>=0,IF(K$60=$B67,IF($C67=0,(($D67-(((K$60-$B67)+1)*$F67)/2)),(($D67-(((K$60-$B67)+1)*$F67)*($C67/12)))),IF($C67=0,($D67-((K$60-$B67)*$F67))-($F67/2),($D67-((K$60-$B67)*$F67))-($F67*($C67/12)))),0)>0,IF(K$60-$B67>=0,IF(K$60=$B67,IF($C67=0,(($D67-(((K$60-$B67)+1)*$F67)/2)),(($D67-(((K$60-$B67)+1)*$F67)*($C67/12)))),IF($C67=0,($D67-((K$60-$B67)*$F67))-($F67/2),($D67-((K$60-$B67)*$F67))-($F67*($C67/12)))),0),0) -> 0 | L67: =IF(IF(L$60-$B67>=0,IF(L$60=$B67,IF($C67=0,(($D67-(((L$60-$B67)+1)*$F67)/2)),(($D67-(((L$60-$B67)+1)*$F67)*($C67/12)))),IF($C67=0,($D67-((L$60-$B67)*$F67))-($F67/2),($D67-((L$60-$B67)*$F67))-($F67*($C67/12)))),0)>0,IF(L$60-$B67>=0,IF(L$60=$B67,IF($C67=0,(($D67-(((L$60-$B67)+1)*$F67)/2)),(($D67-(((L$60-$B67)+1)*$F67)*($C67/12)))),IF($C67=0,($D67-((L$60-$B67)*$F67))-($F67/2),($D67-((L$60-$B67)*$F67))-($F67*($C67/12)))),0),0) -> 0 | M67: =IF(IF(M$60-$B67>=0,IF(M$60=$B67,IF($C67=0,(($D67-(((M$60-$B67)+1)*$F67)/2)),(($D67-(((M$60-$B67)+1)*$F67)*($C67/12)))),IF($C67=0,($D67-((M$60-$B67)*$F67))-($F67/2),($D67-((M$60-$B67)*$F67))-($F67*($C67/12)))),0)>0,IF(M$60-$B67>=0,IF(M$60=$B67,IF($C67=0,(($D67-(((M$60-$B67)+1)*$F67)/2)),(($D67-(((M$60-$B67)+1)*$F67)*($C67/12)))),IF($C67=0,($D67-((M$60-$B67)*$F67))-($F67/2),($D67-((M$60-$B67)*$F67))-($F67*($C67/12)))),0),0) -> 0 | N67: =IF(IF(N$60-$B67>=0,IF(N$60=$B67,IF($C67=0,(($D67-(((N$60-$B67)+1)*$F67)/2)),(($D67-(((N$60-$B67)+1)*$F67)*($C67/12)))),IF($C67=0,($D67-((N$60-$B67)*$F67))-($F67/2),($D67-((N$60-$B67)*$F67))-($F67*($C67/12)))),0)>0,IF(N$60-$B67>=0,IF(N$60=$B67,IF($C67=0,(($D67-(((N$60-$B67)+1)*$F67)/2)),(($D67-(((N$60-$B67)+1)*$F67)*($C67/12)))),IF($C67=0,($D67-((N$60-$B67)*$F67))-($F67/2),($D67-((N$60-$B67)*$F67))-($F67*($C67/12)))),0),0) -> 0 | ... AA67: =IF(IF(AA$60-$B67>=0,IF(AA$60=$B67,IF($C67=0,(($D67-(((AA$60-$B67)+1)*$F67)/2)),(($D67-(((AA$60-$B67)+1)*$F67)*($C67/12)))),IF($C67=0,($D67-((AA$60-$B67)*$F67))-($F67/2),($D67-((AA$60-$B67)*$F67))-($F67*($C67/12)))),0)>0,IF(AA$60-$B67>=0,IF(AA$60=$B67,IF($C67=0,(($D67-(((AA$60-$B67)+1)*$F67)/2)),(($D67-(((AA$60-$B67)+1)*$F67)*($C67/12)))),IF($C67=0,($D67-((AA$60-$B67)*$F67))-($F67/2),($D67-((AA$60-$B67)*$F67))-($F67*($C67/12)))),0),0) -> 0
A68: Asset | F68: =IFERROR(D68/E68,0) -> 0 | G68: =IF(IF(G$60-$B68>=0,IF(G$60=$B68,IF($C68=0,(($D68-(((G$60-$B68)+1)*$F68)/2)),(($D68-(((G$60-$B68)+1)*$F68)*($C68/12)))),IF($C68=0,($D68-((G$60-$B68)*$F68))-($F68/2),($D68-((G$60-$B68)*$F68))-($F68*($C68/12)))),0)>0,IF(G$60-$B68>=0,IF(G$60=$B68,IF($C68=0,(($D68-(((G$60-$B68)+1)*$F68)/2)),(($D68-(((G$60-$B68)+1)*$F68)*($C68/12)))),IF($C68=0,($D68-((G$60-$B68)*$F68))-($F68/2),($D68-((G$60-$B68)*$F68))-($F68*($C68/12)))),0),0) -> 0 | H68: =IF(IF(H$60-$B68>=0,IF(H$60=$B68,IF($C68=0,(($D68-(((H$60-$B68)+1)*$F68)/2)),(($D68-(((H$60-$B68)+1)*$F68)*($C68/12)))),IF($C68=0,($D68-((H$60-$B68)*$F68))-($F68/2),($D68-((H$60-$B68)*$F68))-($F68*($C68/12)))),0)>0,IF(H$60-$B68>=0,IF(H$60=$B68,IF($C68=0,(($D68-(((H$60-$B68)+1)*$F68)/2)),(($D68-(((H$60-$B68)+1)*$F68)*($C68/12)))),IF($C68=0,($D68-((H$60-$B68)*$F68))-($F68/2),($D68-((H$60-$B68)*$F68))-($F68*($C68/12)))),0),0) -> 0 | I68: =IF(IF(I$60-$B68>=0,IF(I$60=$B68,IF($C68=0,(($D68-(((I$60-$B68)+1)*$F68)/2)),(($D68-(((I$60-$B68)+1)*$F68)*($C68/12)))),IF($C68=0,($D68-((I$60-$B68)*$F68))-($F68/2),($D68-((I$60-$B68)*$F68))-($F68*($C68/12)))),0)>0,IF(I$60-$B68>=0,IF(I$60=$B68,IF($C68=0,(($D68-(((I$60-$B68)+1)*$F68)/2)),(($D68-(((I$60-$B68)+1)*$F68)*($C68/12)))),IF($C68=0,($D68-((I$60-$B68)*$F68))-($F68/2),($D68-((I$60-$B68)*$F68))-($F68*($C68/12)))),0),0) -> 0 | J68: =IF(IF(J$60-$B68>=0,IF(J$60=$B68,IF($C68=0,(($D68-(((J$60-$B68)+1)*$F68)/2)),(($D68-(((J$60-$B68)+1)*$F68)*($C68/12)))),IF($C68=0,($D68-((J$60-$B68)*$F68))-($F68/2),($D68-((J$60-$B68)*$F68))-($F68*($C68/12)))),0)>0,IF(J$60-$B68>=0,IF(J$60=$B68,IF($C68=0,(($D68-(((J$60-$B68)+1)*$F68)/2)),(($D68-(((J$60-$B68)+1)*$F68)*($C68/12)))),IF($C68=0,($D68-((J$60-$B68)*$F68))-($F68/2),($D68-((J$60-$B68)*$F68))-($F68*($C68/12)))),0),0) -> 0 | K68: =IF(IF(K$60-$B68>=0,IF(K$60=$B68,IF($C68=0,(($D68-(((K$60-$B68)+1)*$F68)/2)),(($D68-(((K$60-$B68)+1)*$F68)*($C68/12)))),IF($C68=0,($D68-((K$60-$B68)*$F68))-($F68/2),($D68-((K$60-$B68)*$F68))-($F68*($C68/12)))),0)>0,IF(K$60-$B68>=0,IF(K$60=$B68,IF($C68=0,(($D68-(((K$60-$B68)+1)*$F68)/2)),(($D68-(((K$60-$B68)+1)*$F68)*($C68/12)))),IF($C68=0,($D68-((K$60-$B68)*$F68))-($F68/2),($D68-((K$60-$B68)*$F68))-($F68*($C68/12)))),0),0) -> 0 | L68: =IF(IF(L$60-$B68>=0,IF(L$60=$B68,IF($C68=0,(($D68-(((L$60-$B68)+1)*$F68)/2)),(($D68-(((L$60-$B68)+1)*$F68)*($C68/12)))),IF($C68=0,($D68-((L$60-$B68)*$F68))-($F68/2),($D68-((L$60-$B68)*$F68))-($F68*($C68/12)))),0)>0,IF(L$60-$B68>=0,IF(L$60=$B68,IF($C68=0,(($D68-(((L$60-$B68)+1)*$F68)/2)),(($D68-(((L$60-$B68)+1)*$F68)*($C68/12)))),IF($C68=0,($D68-((L$60-$B68)*$F68))-($F68/2),($D68-((L$60-$B68)*$F68))-($F68*($C68/12)))),0),0) -> 0 | M68: =IF(IF(M$60-$B68>=0,IF(M$60=$B68,IF($C68=0,(($D68-(((M$60-$B68)+1)*$F68)/2)),(($D68-(((M$60-$B68)+1)*$F68)*($C68/12)))),IF($C68=0,($D68-((M$60-$B68)*$F68))-($F68/2),($D68-((M$60-$B68)*$F68))-($F68*($C68/12)))),0)>0,IF(M$60-$B68>=0,IF(M$60=$B68,IF($C68=0,(($D68-(((M$60-$B68)+1)*$F68)/2)),(($D68-(((M$60-$B68)+1)*$F68)*($C68/12)))),IF($C68=0,($D68-((M$60-$B68)*$F68))-($F68/2),($D68-((M$60-$B68)*$F68))-($F68*($C68/12)))),0),0) -> 0 | N68: =IF(IF(N$60-$B68>=0,IF(N$60=$B68,IF($C68=0,(($D68-(((N$60-$B68)+1)*$F68)/2)),(($D68-(((N$60-$B68)+1)*$F68)*($C68/12)))),IF($C68=0,($D68-((N$60-$B68)*$F68))-($F68/2),($D68-((N$60-$B68)*$F68))-($F68*($C68/12)))),0)>0,IF(N$60-$B68>=0,IF(N$60=$B68,IF($C68=0,(($D68-(((N$60-$B68)+1)*$F68)/2)),(($D68-(((N$60-$B68)+1)*$F68)*($C68/12)))),IF($C68=0,($D68-((N$60-$B68)*$F68))-($F68/2),($D68-((N$60-$B68)*$F68))-($F68*($C68/12)))),0),0) -> 0 | ... AA68: =IF(IF(AA$60-$B68>=0,IF(AA$60=$B68,IF($C68=0,(($D68-(((AA$60-$B68)+1)*$F68)/2)),(($D68-(((AA$60-$B68)+1)*$F68)*($C68/12)))),IF($C68=0,($D68-((AA$60-$B68)*$F68))-($F68/2),($D68-((AA$60-$B68)*$F68))-($F68*($C68/12)))),0)>0,IF(AA$60-$B68>=0,IF(AA$60=$B68,IF($C68=0,(($D68-(((AA$60-$B68)+1)*$F68)/2)),(($D68-(((AA$60-$B68)+1)*$F68)*($C68/12)))),IF($C68=0,($D68-((AA$60-$B68)*$F68))-($F68/2),($D68-((AA$60-$B68)*$F68))-($F68*($C68/12)))),0),0) -> 0
A69: Asset | F69: =IFERROR(D69/E69,0) -> 0 | G69: =IF(IF(G$60-$B69>=0,IF(G$60=$B69,IF($C69=0,(($D69-(((G$60-$B69)+1)*$F69)/2)),(($D69-(((G$60-$B69)+1)*$F69)*($C69/12)))),IF($C69=0,($D69-((G$60-$B69)*$F69))-($F69/2),($D69-((G$60-$B69)*$F69))-($F69*($C69/12)))),0)>0,IF(G$60-$B69>=0,IF(G$60=$B69,IF($C69=0,(($D69-(((G$60-$B69)+1)*$F69)/2)),(($D69-(((G$60-$B69)+1)*$F69)*($C69/12)))),IF($C69=0,($D69-((G$60-$B69)*$F69))-($F69/2),($D69-((G$60-$B69)*$F69))-($F69*($C69/12)))),0),0) -> 0 | H69: =IF(IF(H$60-$B69>=0,IF(H$60=$B69,IF($C69=0,(($D69-(((H$60-$B69)+1)*$F69)/2)),(($D69-(((H$60-$B69)+1)*$F69)*($C69/12)))),IF($C69=0,($D69-((H$60-$B69)*$F69))-($F69/2),($D69-((H$60-$B69)*$F69))-($F69*($C69/12)))),0)>0,IF(H$60-$B69>=0,IF(H$60=$B69,IF($C69=0,(($D69-(((H$60-$B69)+1)*$F69)/2)),(($D69-(((H$60-$B69)+1)*$F69)*($C69/12)))),IF($C69=0,($D69-((H$60-$B69)*$F69))-($F69/2),($D69-((H$60-$B69)*$F69))-($F69*($C69/12)))),0),0) -> 0 | I69: =IF(IF(I$60-$B69>=0,IF(I$60=$B69,IF($C69=0,(($D69-(((I$60-$B69)+1)*$F69)/2)),(($D69-(((I$60-$B69)+1)*$F69)*($C69/12)))),IF($C69=0,($D69-((I$60-$B69)*$F69))-($F69/2),($D69-((I$60-$B69)*$F69))-($F69*($C69/12)))),0)>0,IF(I$60-$B69>=0,IF(I$60=$B69,IF($C69=0,(($D69-(((I$60-$B69)+1)*$F69)/2)),(($D69-(((I$60-$B69)+1)*$F69)*($C69/12)))),IF($C69=0,($D69-((I$60-$B69)*$F69))-($F69/2),($D69-((I$60-$B69)*$F69))-($F69*($C69/12)))),0),0) -> 0 | J69: =IF(IF(J$60-$B69>=0,IF(J$60=$B69,IF($C69=0,(($D69-(((J$60-$B69)+1)*$F69)/2)),(($D69-(((J$60-$B69)+1)*$F69)*($C69/12)))),IF($C69=0,($D69-((J$60-$B69)*$F69))-($F69/2),($D69-((J$60-$B69)*$F69))-($F69*($C69/12)))),0)>0,IF(J$60-$B69>=0,IF(J$60=$B69,IF($C69=0,(($D69-(((J$60-$B69)+1)*$F69)/2)),(($D69-(((J$60-$B69)+1)*$F69)*($C69/12)))),IF($C69=0,($D69-((J$60-$B69)*$F69))-($F69/2),($D69-((J$60-$B69)*$F69))-($F69*($C69/12)))),0),0) -> 0 | K69: =IF(IF(K$60-$B69>=0,IF(K$60=$B69,IF($C69=0,(($D69-(((K$60-$B69)+1)*$F69)/2)),(($D69-(((K$60-$B69)+1)*$F69)*($C69/12)))),IF($C69=0,($D69-((K$60-$B69)*$F69))-($F69/2),($D69-((K$60-$B69)*$F69))-($F69*($C69/12)))),0)>0,IF(K$60-$B69>=0,IF(K$60=$B69,IF($C69=0,(($D69-(((K$60-$B69)+1)*$F69)/2)),(($D69-(((K$60-$B69)+1)*$F69)*($C69/12)))),IF($C69=0,($D69-((K$60-$B69)*$F69))-($F69/2),($D69-((K$60-$B69)*$F69))-($F69*($C69/12)))),0),0) -> 0 | L69: =IF(IF(L$60-$B69>=0,IF(L$60=$B69,IF($C69=0,(($D69-(((L$60-$B69)+1)*$F69)/2)),(($D69-(((L$60-$B69)+1)*$F69)*($C69/12)))),IF($C69=0,($D69-((L$60-$B69)*$F69))-($F69/2),($D69-((L$60-$B69)*$F69))-($F69*($C69/12)))),0)>0,IF(L$60-$B69>=0,IF(L$60=$B69,IF($C69=0,(($D69-(((L$60-$B69)+1)*$F69)/2)),(($D69-(((L$60-$B69)+1)*$F69)*($C69/12)))),IF($C69=0,($D69-((L$60-$B69)*$F69))-($F69/2),($D69-((L$60-$B69)*$F69))-($F69*($C69/12)))),0),0) -> 0 | M69: =IF(IF(M$60-$B69>=0,IF(M$60=$B69,IF($C69=0,(($D69-(((M$60-$B69)+1)*$F69)/2)),(($D69-(((M$60-$B69)+1)*$F69)*($C69/12)))),IF($C69=0,($D69-((M$60-$B69)*$F69))-($F69/2),($D69-((M$60-$B69)*$F69))-($F69*($C69/12)))),0)>0,IF(M$60-$B69>=0,IF(M$60=$B69,IF($C69=0,(($D69-(((M$60-$B69)+1)*$F69)/2)),(($D69-(((M$60-$B69)+1)*$F69)*($C69/12)))),IF($C69=0,($D69-((M$60-$B69)*$F69))-($F69/2),($D69-((M$60-$B69)*$F69))-($F69*($C69/12)))),0),0) -> 0 | N69: =IF(IF(N$60-$B69>=0,IF(N$60=$B69,IF($C69=0,(($D69-(((N$60-$B69)+1)*$F69)/2)),(($D69-(((N$60-$B69)+1)*$F69)*($C69/12)))),IF($C69=0,($D69-((N$60-$B69)*$F69))-($F69/2),($D69-((N$60-$B69)*$F69))-($F69*($C69/12)))),0)>0,IF(N$60-$B69>=0,IF(N$60=$B69,IF($C69=0,(($D69-(((N$60-$B69)+1)*$F69)/2)),(($D69-(((N$60-$B69)+1)*$F69)*($C69/12)))),IF($C69=0,($D69-((N$60-$B69)*$F69))-($F69/2),($D69-((N$60-$B69)*$F69))-($F69*($C69/12)))),0),0) -> 0 | ... AA69: =IF(IF(AA$60-$B69>=0,IF(AA$60=$B69,IF($C69=0,(($D69-(((AA$60-$B69)+1)*$F69)/2)),(($D69-(((AA$60-$B69)+1)*$F69)*($C69/12)))),IF($C69=0,($D69-((AA$60-$B69)*$F69))-($F69/2),($D69-((AA$60-$B69)*$F69))-($F69*($C69/12)))),0)>0,IF(AA$60-$B69>=0,IF(AA$60=$B69,IF($C69=0,(($D69-(((AA$60-$B69)+1)*$F69)/2)),(($D69-(((AA$60-$B69)+1)*$F69)*($C69/12)))),IF($C69=0,($D69-((AA$60-$B69)*$F69))-($F69/2),($D69-((AA$60-$B69)*$F69))-($F69*($C69/12)))),0),0) -> 0
A71: Total | D71: =SUM(D61:D69) -> 0 | F71: =SUM(F61:F67) -> 0 | G71: =SUM(G61:G67) -> 0 | H71: =SUM(H61:H67) -> 0 | I71: =SUM(I61:I67) -> 0 | J71: =SUM(J61:J67) -> 0 | K71: =SUM(K61:K67) -> 0 | L71: =SUM(L61:L67) -> 0 | M71: =SUM(M61:M67) -> 0 | ... P71: =SUM(P61:P67) -> 0 | Q71: =SUM(Q61:Q69) -> 0 | R71: =SUM(R61:R69) -> 0 | S71: =SUM(S61:S69) -> 0 | T71: =SUM(T61:T69) -> 0 | U71: =SUM(U61:U69) -> 0 | V71: =SUM(V61:V69) -> 0 | W71: =SUM(W61:W69) -> 0 | X71: =SUM(X61:X69) -> 0 | ... AA71: =SUM(AA61:AA69) -> 0
A74: Remaining Cost Basis at beginning of year | D74: =P71 -> 0
A75: ="20"&RIGHT(A55,2)&" Additions" -> 2024 Additions | D75: =SUMIF($B$61:$B$69,"20"&RIGHT(A55,2),$D$61:$D$69) -> 0
A76: ="20"&RIGHT(A55,2)&" Tax Depreciation" -> 2024 Tax Depreciation | D76: =D74+D75-Q71 -> 0
A79: Note: 50% Amortization is taken in initial and final year of asset life unless specific month of service is entered.

Sheet Entity Structure and changes
B1: Taxpayer/Business Name | C1: Pragya
B2: Entity Type | C2: 1040/1120
B3: List of all Entities for which Form 5471 is to be prepared
C4: Entity 1 | D4: Entity 2 | E4: E3 | F4: E4 | G4: E5 | H4: E6
B5: Document Upload
B6: Language Identify +Translate
B7: Currency Identify + FX Rate
B8: Category Identification
B9: Schedules Required (Only hide not required schedules)
B10: P&L Mapping
B11: Balance Sheet Mapping
B13: WPs
C20: Totals of All Entities Schedule I-1
A24: Schedule I-1 - Information for Global Intangible Low-Taxed Income | C24: Entity 1 | D24: Entity 2 | E24: E3 | F24: E4 | G24: E5 | H24: E6 | I24: Total
C25: USD Total
A26: 1 | B26: Gross Income | I26: =SUM(H26) -> 0
A27: 2 | B27: Exclusions | I27: =SUM(H27) -> 0
A28: a | B28: Effectively connected income | I28: =SUM(H28) -> 0
A29: b | B29: Subpart F income | I29: =SUM(H29) -> 0
A30: c | B30: High-tax exception income | I30: =SUM(H30) -> 0
A31: d | B31: Related party dividends | I31: =SUM(H31) -> 0
A32: e | B32: Foreign oil and gas extraction income | I32: =SUM(H32) -> 0
A33: 3 | B33: Total exclusions | I33: =SUM(H33) -> 0
A34: 4 | B34: Gross income less total exclusions | I34: =SUM(H34) -> 0
A35: 5 | B35: Deductions properly allocable to line 4 | C35: =ROUND(F38/H38,0) -> #DIV/0! | I35: =SUM(H35) -> 0
A36: 6 | B36: Tested income (loss) | C36: =ROUND(F39/H39,0) -> #DIV/0! | I36: =SUM(H36) -> 0
A37: 7 | B37: Tested foreign income taxes | C37: =ROUND(F40/H40,0) -> #DIV/0! | I37: =SUM(H37) -> 0
A38: 8 | B38: Qualified business asset investment (QBAI) | C38: =ROUND(F41/H41,0) -> #DIV/0! | I38: =SUM(H38) -> 0
A39: 9a | B39: Interest expense (included on line 5) | I39: =SUM(H39) -> 0
A40: b | B40: Qualified interest Expense | I40: =SUM(H40) -> 0
A41: c | B41: Tested QBAI Amount | C41: =ROUND(F44/H44,0) -> #DIV/0! | I41: =SUM(H41) -> 0
A42: d | B42: Tested Interest Expense (Line 9a minus (9B + 9C). Enter Zero if < 0) | I42: =SUM(H42) -> 0
A43: 10a | B43: Interest Income Included in Line 4 | I43: =SUM(H43) -> 0
A44: b | B44: Qualified Interest Income | C44: =ROUND(F47/H47,0) -> #DIV/0! | I44: =SUM(H44) -> 0
A45: c | B45: Tested Interest Income (Line 10a minus line 10b. Enter Zero if < 0) | I45: =SUM(H45) -> 0
